Workbook

Sheet README
A1: Coliseum of Parliament — Starter Card & Stage Data
A2: Purpose | B2: Source-of-truth data for the rhetoric card battler (Godot). Each tab is one data table the engine reads. IDs are the join keys across tabs (see the ID-prefix list below) — keep IDs stable, rename display text freely.
A3: Status | B3: MASTER (v9.22.26 lineage), refreshed 2026-10-13 (Batches 1-3 adopted: bills BI31-BI50, 69 topic rooms ST32-ST100, levels LV63-LV82; Batch 1: eight topic rooms ST24-ST31, levels LV61-LV62, transitions switched on). Every Combat stage has at least one opponent; ST07 (Office Hours) and ST22 (Party Steering Committee Check-In) are Non-combat and ST23 (National Assembly Floor Voting) is a Vote. Fields not yet final are marked as drafts in their own Note/Why cells; the header of every column carries a note saying what it means and what blank does.
A5: TAB GUIDE
A6: Balance | B6: Global tuning levers (starting deck recipe, XP/Yen scaling, question multipliers, vote influence, party opinion weights). 24 levers.
A7: Suits | B7: The 6 canonical rhetorical Elements/suits (Earnest, Emotional, Appeal, Data Driven, Divisive, Duplicitous) with EN (join key) and JP display names. Referenced by Cards, Opponents, Flavor Text, Affinity and the 5 Question tabs.
A8: Stages | B8: 259 stages (ST01–ST259): 225 Combat, 33 Non-combat (Office Hours rooms and ST22 Party Steering Committee Check-In) and 1 Vote (ST23 Floor Voting). ST24 onward are bill-specific copies of a generic stage; each takes its Background ID (a Stages column) from its generic stage unless it has a picture of its own. Per-stage combat stats, audience-segment mix, favored suit (formula, reads Affinity), sequence mode, and win/loss deltas to Jiban/Yen/Reputation/XP/Party support.
A9: Levels | B9: 82 levels (LV01–LV82): LV01–LV30 are the ordinary levels, LV31–LV60 are one-time Floor Vote levels built around bills BI01–BI30, LV61–LV62 are topic levels (rail fares, fishing quotas) with no bill. Sequences 1–10 stage slots (an STxx, or a BIxx for a Floor Vote), XP unlock cost by Policy Research Assistant tier, bonus win-reward ranges, and per-level Win Δ for each organization.
A10: Affinity | B10: Suit × Stage power-multiplier grid; feeds each Stage's 'Favored suit' formula.
A11: Cards | B11: 54 cards (Card ID C01–C54), 9 per suit. Core stats (Cost/Self+/Opp−/Guard/Draw/Gaffe) plus a Special/Special value/Special note trio encoding conditional effects (see the Claude Code data guide for the dispatch keys).
A12: Segments | B12: 5 audience segments (Press, Party Members, Constituents, Donors, Bureaucrats/Other) with starting favorability; Stages mix these, Cards target them.
A13: Modifiers | B13: 45 modifiers (M01–M48, with gaps where some were retired), one or more per organization. Effect is the human-readable description; Effect Type/Target/Value are the machine-readable columns the game reads instead of parsing the prose.
A14: Boosters | B14: 32 booster/organization groups (BO01–BO32) across Party/Constituency/National tiers, each with a comma-separated Linked modifiers list pointing into Modifiers and an optional Starting Standing. Party-tier bodies also carry a Party Lean Multiplier. The Standing Links tab makes one organization follow, or rival, another organization or a meta value.
A15: Shop | B15: 20 shop items (SH01–SH20): XP-cost, Yen-cost and up to two free-text Bonus Condition fields (staff-tier discounts, stacking buffs, etc.).
A16: Staff | B16: 21 hireable staff rows (SF01–SF21) across 3 roles (Policy Research Assistant, Media Spokesperson, District Representative) × starting/upgrade tier combinations, each with free-text Tier 0/1/2 Reward strings in a '+N for <ID>' pattern.
A17: Opponents | B17: 125 opponents (OP01–OP125, journalists included): Title/Gender/Party/Affiliation, up to 3 ranked suits, and Intent Pattern Range for Attack/Gain/Block (range-string battle AI, '0' = never uses that move). Stage is a semicolon-separated list; most opponents fight in several stages.
... A27: Question Themes | B27: 272 question themes, each linked to the organization(s) a Strong answer pleases (Organization, semicolon list) and, optionally, those it sets back (Annoys).
A29: COLOR KEY
A30: Blue text | B30: Hardcoded input — edit freely.
A31: Black text | B31: Formula — do not overwrite.
A32: Green text | B32: Direct link to another tab.
A33: Yellow fill | B33: Open design decision — needs your call.
A35: KNOWN GAPS / OPEN ITEMS
A36: Repeated suits | B36: 19 opponents list the same suit more than once in Suit 1–3. Left as is on purpose: it simply weights that suit.
A37: Unused question ID | B37: Lobbyist Questions has no L63 (IDs run L01–L78). Harmless; the ID is simply unused.
A38: Questions with no Weak grade | B38: About 37 room questions have no W for any suit. The room tabs' footer rules allow it (at least 2 S, at most 2 W), so they are left; a W on each makes the choice of suit matter more.
A39: Newer tabs | B39: Tabs added after this guide (Player Cues, Stage Questions, Party Standing, Law Effects, Vote Influence Triggers/Cues, Level Intro Cues/Thoughts, Transition tabs, How To Play, Office Ticker and others) are described by the notes on their column headers; hover a header cell.

Sheet Balance
A1: Lever | B1: Value | C1: Note
A2: Starter deck size | B2: 15 | C2: Player and default opponent deck size
A3: Jiban: town hall trigger (≤) | B3: 15 | C3: Constituency support at or below this inserts a Town Hall into the level queue.
A4: Party support: funding freeze (≤) | B4: 0 | C4: Party support at or below this freezes Funds income until it rises back above.
A5: Party support: steering committee (<) | B5: 25 | C5: Party support below this inserts the Steering Committee check-in (ST22) into the level queue.
A6: Party support: allied buff (>) | B6: 75 | C6: Party support above this grants M09 (Party Backing) free, on top of anything owned.
A7: Gaffes: lifetime penalty threshold | B7: 50 | C7: Lifetime gaffes at or above this apply the one-time Jiban penalty below.
A8: Gaffes: lifetime penalty jiban delta | B8: -15 | C8: Applied once, the moment lifetime gaffes cross the threshold above.
A9: Vote influence: default threshold | B9: 85 | C9: Floor Vote influence swing (§7.7): how high an enabled trigger variable in the Vote Influence Triggers tab must be to pass the gate.
A10: Vote swing: resistance default | B10: 85 | C10: % of a party's own seats immune to the influence swing by default. A party's own Vote Resistance column (Parties tab) overrides this.
A11: Question: strong multiplier | B11: 1.3 | C11: How much a Strong-graded answer boosts the card's own self_plus/opp_minus this round, on top of stage affinity. Still pleases the asking organization as before.
A12: Question: weak multiplier | B12: 0.7 | C12: How much a Weak-graded answer penalizes the card's own self_plus/opp_minus this round, on top of stage affinity. No tone cost at all any more.
A13: Lean: Party Support Delta | B13: 2 | C13: First-draft Party support ± when the Level Intro screen’s bill-lean choice agrees with or disagrees with your own party’s disposition toward the level’s bill.
... A30: Party salience: Max Factor | B30: 2 | C30: Highest multiplier a high-salience bill can apply to a party's movement.
A31: Text scale: Small | B31: 90 | C31: Text size percent when the player picks Small (Administration menu). Normal is always 100.
A32: Text scale: Large | B32: 120 | C32: Text size percent when the player picks Large.
A33: Transition: Player Thought Chance | B33: 30 | C33: First-draft percent chance (0-100) that a stage transition opens with the player's own private thought (a PLAYER row in Transition Dialogue) before anyone speaks. A transition with nobody to speak always uses a thought if one is written.
A34: Starting Training Session Coupons | B34: 1 | C34: How many Training Session Coupons (SH21, a free Rhetoric Training draw) a new run begins with. 0 = none.
A35: Supermajority: Percent of House | B35: 67 | C35: Share of the whole house (rounded up) a bill flagged Supermajority in Floor Vote Bills' Vote Requirement column needs to pass. 67 is two thirds (68 of 101). First draft; no bill is flagged yet.
A36: Stance: Other Side Please Percent | B36: 50 | C36: First-draft percent (0-100) of a pleasing answer that counts for a bill stakeholder on the side AGAINST your lean (rounded down). 50 means two answers please them as one. Setting back an organization always lands in full.
A37: Stance: Win Drift | B37: 2 | C37: First-draft standing change per won Combat stage in a bill level: the side against your lean loses this much, your own side gains this much. A lost stage moves nothing.
A38: Stance: Vote Delta | B38: 2 | C38: First-draft standing change from your final vote: Aye gives the bill's supporters +this and its opponents -this; Nay the reverse. Abstain moves nothing.
A39: Stance: Flip Abandoned Penalty | B39: 5 | C39: First-draft penalty (instead of the Vote Delta) for the side you leaned with when your final vote contradicts your lean. Switching is never free.
A40: Stance: Flip Recovery Percent | B40: 25 | C40: First-draft percent (0-100, rounded down per organization) of what the stages cost the side you now vote with that you win back by switching. A future backing may raise it.
A41: Stance: Flip Party Support Away | B41: 3 | C41: First-draft Party support lost when you switch your vote to AGAINST your own party's position on the bill.
A42: Stance: Flip Party Support Toward | B42: 1 | C42: First-draft Party support gained when you switch your vote to WITH your own party's position on the bill.
A43: Bill Question Share Percent | B43: 50 | C43: First-draft percent (0-100) of a stage's questions that may come from the bill the level is about (Stage Questions rows with a Bill ID). The rest come from the room's own pools.
A44: Standing Links: Yen Per Point | B44: 10000 | C44: First-draft. How many yen of Funds count as one standing point when Funds drives an organization through the Standing Links tab (Funds is volatile, so this keeps its pull small).
A45: Opponent Cues: General Pool Chance | B45: 25 | C45: First-draft percent (0-100) chance that an opponent's move uses the shared pool for the style they rolled instead of their own personal lines. 0 = personal lines only.
A46: Special Level Delay | B46: 15 | C46: Hours (x3 with the 2026-10-23 calendar; was 5 units). How many hours of the game calendar pass between a crisis trigger (Constituency support at or below its Town Hall threshold, Party support below its Steering Committee threshold) and its special level appearing at the top of the level list. Each stage costs the hours in the Stages tab.
A47: Decay Interval | B47: 0 | C47: 2026-10-23: 0 = decay by hours is off. Standing and meta decay now run once at every week end instead (Week Decay Multiplier below). A positive number still runs decay every that-many hours as well.
... A100: Draft Bill: Cooldown Units | B100: 90 | C100: Hours (x3, 2026-10-23). Game-calendar hours before another bill can be drafted.
A101: Brief: Standard Energy | B101: 3 | C101: Cameron 2026-10-21. Energy per turn the Details panel treats as normal; a room differing from it prints its own number.
A102: Brief: Standard Hand | B102: 5 | C102: Cameron 2026-10-21. Hand size the Details panel treats as normal; a room differing from it prints its own number.
A103: Whip: Base Cost | B103: 10 | C103: Cameron 2026-10-22. Party support spent for each extra vote whipped on a bill vote.
A104: Whip: Against Party Multiplier | B104: 3 | C104: Cameron 2026-10-22. Whip cost is multiplied by this when the player's vote goes against their own party's position on the bill.
A105: Whip: Max Per Vote | B105: 3 | C105: Draft 2026-10-22. Most extra votes that can be whipped on one bill vote.
A106: Whip: Party Support Floor | B106: 30 | C106: Draft 2026-10-22. Stored Party support may never be spent below this, so a whip cannot push the player into the party crisis.
A107: Workday Hours | B107: 8 | C107: Cameron 2026-10-23. Hours in each weekday (Monday to Friday).
A108: Work Days Per Week | B108: 5 | C108: Cameron 2026-10-23. Weekdays in a work week.
A109: Weekend Day Hours | B109: 4 | C109: Cameron 2026-10-23. Hours in each weekend day (Saturday and Sunday).
A110: Weekend Days | B110: 2 | C110: Cameron 2026-10-23. Days in the weekend.
A111: Calendar Start Year | B111: 2018 | C111: Cameron 2026-10-23. The run begins on Monday 1 October 2018.
A112: Calendar Start Month | B112: 10 | C112: Cameron 2026-10-23. See Calendar Start Year.
A113: Calendar Start Day | B113: 1 | C113: Cameron 2026-10-23. See Calendar Start Year.
A114: Week Decay Multiplier | B114: 2.5 | C114: Draft 2026-10-23. Standing and meta decay now run once per week end. A week is about 2.4 levels, so each decay step (percent and neglect points) is multiplied by this to keep roughly the old pace.
A115: Dues: Base | B115: 50000 | C115: Cameron 2026-10-23. Yen owed to the party at each week end before any extras.
A116: Dues: Reward Percent | B116: 30 | C116: Cameron 2026-10-23. Percent of the Funds earned Monday to Friday that week that is added to the dues.
A117: Dues: Party Support Start | B117: 40 | C117: Cameron 2026-10-23. Party support above this adds to the base dues.
A118: Dues: Party Support Step | B118: 15 | C118: Cameron 2026-10-23. Every full this-many points of Party support above the start adds one step to the base dues.
... A185: Audience scale: Largest bonus | B185: 5 | C185: Moved from a script into the workbook 2026-10-27 (hard-coded audit). A card that scales with its audience share never adds or takes away more than this.

Sheet Player
A1: player_id | B1: name_en | C1: party | D1: blurb | E1: Constituency support | F1: Reputation | G1: Funds | H1: Party support | I1: starting_xp | J1: Gender | K1: Committee | L1: Positioning | M1: Element 1 | N1: Element 2 | O1: Region | P1: District Name | Q1: District Type
A2: PC01 | B2: Kenshin Sako | C2: Frontier Party | D2: A strong footing to begin with. Easy difficulty. | E2: 35 | F2: 25 | G2: 100000 | H2: 40 | I2: 60 | J2: M | K2: Committee on Ethics and Prosecution | L2: Liberal | M2: Earnest | N2: Emotional | O2: Sōya | P2: Sōya - Wakkanai | Q2: Single Member
A3: PC02 | B3: Haru Yashi | C3: Frontier Party | D3: A steady start. Normal difficulty. | E3: 20 | F3: 15 | G3: 50000 | H3: 10 | I3: 30 | J3: F | K3: Committee on Foreign Affairs | L3: Nationalist | M3: Earnest | N3: Divisive | O3: Iburi | P3: Tomakomai City | Q3: Single Member
A4: PC03 | B4: Arata Ran | C4: Keizaijiyuutou | D4: An uphill climb from day one. Hard difficulty. | E4: 10 | F4: 5 | G4: 25000 | H4: 15 | I4: 0 | J4: F | K4: Committee on Agriculture | L4: Capitalist | M4: Appeal | N4: Emotional | O4: Sapporo | P4: Sapporo Proportional Block 6 | Q4: Proportional Block
A5: PC04 | B5: Jyurou Nishihara | C5: Country Initiative | D5: Already in crisis before your first vote. Very Hard difficulty. | E5: 5 | F5: 0 | G5: 10000 | H5: 0 | I5: 0 | J5: M | K5: Committee on the National Assembly | L5: Traditionalist | M5: Appeal | N5: Duplicitous | O5: Aomori | P5: Aomori Proportional Block 3 | Q5: Proportional Block

Sheet Office Notices
A1: notice_id | B1: slot | C1: condition_type | D1: condition_target | E1: condition_op | F1: condition_value | G1: text_en
A2: ON01 | B2: staff_greeting | C2: staff_role | D2: District Representative | E2: hired | G2: {staff} is greeting visitors.
A3: ON02 | B3: staff_greeting | C3: staff_role | D3: District Representative | E3: not_hired | G3: No one is at the front desk to greet visitors.
A4: ON03 | B4: staff_greeting | C4: staff_role | D4: Policy Research Assistant | E4: hired | G4: {staff} is reviewing committee minutes and reports.
A5: ON04 | B5: staff_greeting | C5: staff_role | D5: Policy Research Assistant | E5: not_hired | G5: No one is reviewing new policy reports.
A6: ON05 | B6: staff_greeting | C6: staff_role | D6: Media Spokesperson | E6: hired | G6: {staff} is answering questions from reporters.
A7: ON06 | B7: staff_greeting | C7: staff_role | D7: Media Spokesperson | E7: not_hired | G7: Calls from the press are going unanswered.
A8: ON07 | B8: press | C8: meta | D8: Reputation | E8: < | F8: 30 | G8: Few visitors are seeking out your office.
A9: ON08 | B9: press | C9: meta | D9: Reputation | E9: >= | F9: 60 | G9: The office is using a waitlist for visitors.
A10: ON09 | B10: press | C10: meta | D10: SG01 | E10: < | F10: 30 | G10: A volunteer student journalist recently visited the office.
A11: ON10 | B11: press | C11: meta | D11: SG01 | E11: >= | F11: 60 | G11: Veteran journalists are visiting the office for a profile piece.
A12: ON11 | B12: press | C12: meta | D12: SG02 | E12: < | F12: 25 | G12: No party colleagues have visited to chat.
A13: ON12 | B13: press | C13: meta | D13: SG02 | E13: >= | F13: 60 | G13: Party members who want to take you to lunch can now use a scheduling system.
A14: ON13 | B14: press | C14: meta | D14: SG03 | E14: < | F14: 10 | G14: Security removed a constituent for shouting obscenities.
A15: ON14 | B15: press | C15: meta | D15: SG03 | E15: < | F15: 25 | G15: A constituent, allegedly, intended to graffiti on your office door.
A16: ON15 | B16: press | C16: meta | D16: SG03 | E16: >= | F16: 60 | G16: An elderly constituent visited and left a gift basket for the office.
A17: ON16 | B17: press | C17: meta | D17: SG03 | E17: >= | F17: 80 | G17: A family from your district visited to take a picture with you.
A18: ON17 | B18: press | C18: meta | D18: SG04 | E18: < | F18: 30 | G18: A former campaign donor left a note demanding the refund of 200,000円.
A19: ON18 | B19: press | C19: meta | D19: SG04 | E19: >= | F19: 70 | G19: A benefactor stopped by the office to deliver a 100,000円 check for use during the next election campaign.
... A21: ON20 | B21: press | C21: meta | D21: SG05 | E21: >= | F21: 80 | G21: Cabinet Legislation Bureau Chief Rika Ashikaga personally delivered the latest bill analysis reports.

Sheet Suits
A1: Element (canon) | B1: Suit (JP) | C1: Romaji | D1: Gloss | E1: Card Design Template
A2: Earnest | B2: 誠実 | C2: Seijitsu | D2: sincerity | E2: Sumo
A3: Emotional | B3: 情熱 | C3: Jōnetsu | D3: passion | E3: Sakura
A4: Appeal | B4: 求心 | C4: Kyūshin | D4: rallying pull | E4: Ukiyoe
A5: Data Driven | B5: 実証 | C5: Jisshō | D5: evidence | E5: Shoji
A6: Divisive | B6: 分断 | C6: Bundan | D6: division | E6: Castle
A7: Duplicitous | B7: 二枚舌 | C7: Nimaijita | D7: two tongues | E7: Ninja

Sheet Stages
A1: Stage ID | B1: Stage (EN) | C1: Stage (JP) | D1: Romaji | E1: Mode | F1: Bar unit | G1: Bar value | H1: Bar max | I1: Win threshold | J1: Win % | K1: Turn limit | L1: 持ち時間 / turn (energy) | M1: Hand size | N1: 失言 gaffe limit | O1: Player start | P1: Opp start | Q1: % Press | R1: % Party Members | S1: % Constituents | T1: % Boosters | U1: % Bureaucrats | V1: % Other | W1: Segment check | X1: Favored suit | Y1: Win ΔJiban | Z1: Win ΔYen | AA1: Win ΔReputation | AB1: Win ΔXP | AC1: Win ΔParty support | AD1: Loss ΔJiban | AE1: Loss ΔYen | AF1: Loss ΔReputation | AG1: Loss ΔXP | AH1: Loss ΔParty support | AI1: Bar Model | AJ1: Energy Mode | AK1: Energy Pool | AL1: Sequence Mode | AM1: Opponent Count | AN1: Question Pool | AO1: Reputation Affects Start | AP1: Reveal In Briefing | AQ1: Loss Ends Level | AR1: Show Transition | AS1: Transition Speaker Count | AT1: Own Party Only | AU1: Threshold Rise Min | AV1: Threshold Rise Max | AW1: Threshold Cap | AX1: Background ID | AY1: Time Units | AZ1: Win ΔDistrict Awareness | BA1: Win ΔNational Awareness
A2: ST01 | B2: Special Committee | C2: 特別委員会 | D2: Tokubetsu Iinkai | E2: Combat | F2: Members | G2: Numerical | H2: 35 | I2: 20 | J2: =IF(AND(ISNUMBER(H2),ISNUMBER(I2)),IF(H2=0,"",I2/H2),"varies") -> 0.57142857 | K2: 7 | L2: 3 | M2: 5 | N2: 5 | O2: 1 | P2: 10 | Q2: 0.1 | R2: 0.4 | S2: 0 | T2: 0 | U2: 0.5 | V2: 0 | W2: =SUM(Q2:V2) -> 1 | X2: =IF(E2<>"Combat","—",IFERROR(INDEX(Affinity!$A$2:$A$7,MATCH(MAX(INDEX(Affinity!$B$2:$V$7,0,MATCH(A2,Affinity!$B$1:$V$1,0))),INDEX(Affinity!$B$2:$V$7,0,MATCH(A2,Affinity!$B$1:$V$1,0)),0)),"—")) -> Earnest | Y2: 0 | Z2: 20000 | AA2: 0 | AB2: 70 | AC2: 0 | AD2: 0 | AE2: 1000 | AF2: 0 | AG2: 1 | AH2: 0 | AI2: Shared_pool | AJ2: per_turn | AL2: reset | AM2: 2 | AO2: No | AR2: Yes | AY2: 4 | BA2: 1
A3: ST02 | B3: Floor Debate | C3: 本会議 | D3: Honkaigi | E3: Combat | F3: Seats | G3: Numerical | H3: 101 | I3: 51 | J3: =IF(AND(ISNUMBER(H3),ISNUMBER(I3)),IF(H3=0,"",I3/H3),"varies") -> 0.5049505 | K3: 10 | L3: 3 | M3: 5 | N3: 4 | O3: 25 | P3: 40 | Q3: 0.2 | R3: 0.35 | S3: 0.05 | T3: 0.15 | U3: 0.15 | V3: 0.1 | W3: =SUM(Q3:V3) -> 1 | X3: =IF(E3<>"Combat","—",IFERROR(INDEX(Affinity!$A$2:$A$7,MATCH(MAX(INDEX(Affinity!$B$2:$V$7,0,MATCH(A3,Affinity!$B$1:$V$1,0))),INDEX(Affinity!$B$2:$V$7,0,MATCH(A3,Affinity!$B$1:$V$1,0)),0)),"—")) -> Appeal | Y3: 0 | Z3: 30000 | AA3: 0 | AB3: 80 | AC3: 0 | AD3: 0 | AE3: 0 | AF3: 0 | AG3: 5 | AH3: 0 | AI3: Shared_pool | AJ3: per_turn | AL3: continuous | AM3: 2 | AO3: No | AR3: Yes | AY3: 4 | BA3: 1
A4: ST03 | B4: Party Caucus | C4: 議員総会 | D4: Giin Sōkai | E4: Combat | F4: Support | G4: Percentage | H4: 100 | I4: 49 | J4: =IF(AND(ISNUMBER(H4),ISNUMBER(I4)),IF(H4=0,"",I4/H4),"varies") -> 0.49 | K4: 10 | L4: 3 | M4: 5 | N4: 5 | O4: 20 | P4: 40 | Q4: 0 | R4: 0.55 | S4: 0 | T4: 0 | U4: 0 | V4: 0.45 | W4: =SUM(Q4:V4) -> 1 | X4: =IF(E4<>"Combat","—",IFERROR(INDEX(Affinity!$A$2:$A$7,MATCH(MAX(INDEX(Affinity!$B$2:$V$7,0,MATCH(A4,Affinity!$B$1:$V$1,0))),INDEX(Affinity!$B$2:$V$7,0,MATCH(A4,Affinity!$B$1:$V$1,0)),0)),"—")) -> Divisive | Y4: 0 | Z4: 20000 | AA4: 1 | AB4: 90 | AC4: 2 | AD4: 0 | AE4: 0 | AF4: -1 | AG4: 1 | AH4: -2 | AI4: Shared_pool | AJ4: per_turn | AL4: continuous | AM4: 2 | AO4: No | AR4: Yes | AT4: Yes | AY4: 4
A5: ST04 | B5: Press Conference | C5: 記者会見 | D5: Kisha Kaiken | E5: Combat | F5: Press tone | G5: Numerical | H5: 100 | I5: 55 | J5: =IF(AND(ISNUMBER(H5),ISNUMBER(I5)),IF(H5=0,"",I5/H5),"varies") -> 0.55 | K5: 6 | L5: 3 | M5: 5 | N5: 4 | O5: 20 | P5: 45 | Q5: 0.9 | R5: 0 | S5: 0 | T5: 0 | U5: 0.05 | V5: 0.05 | W5: =SUM(Q5:V5) -> 1 | X5: =IF(E5<>"Combat","—",IFERROR(INDEX(Affinity!$A$2:$A$7,MATCH(MAX(INDEX(Affinity!$B$2:$V$7,0,MATCH(A5,Affinity!$B$1:$V$1,0))),INDEX(Affinity!$B$2:$V$7,0,MATCH(A5,Affinity!$B$1:$V$1,0)),0)),"—")) -> Appeal | Y5: 1 | Z5: 30000 | AA5: 1 | AB5: 60 | AC5: 1 | AD5: 0 | AE5: 0 | AF5: -2 | AG5: 5 | AH5: -2 | AI5: Single | AJ5: per_turn | AL5: single | AM5: 1 | AN5: press_conference | AO5: Yes | AQ5: No | AR5: Yes | AY5: 2 | BA5: 2
A6: ST05 | B6: Town Hall | C6: 住民集会 | D6: Jūmin Shūkai | E6: Combat | F6: Appeasement | G6: Percentage | H6: 100 | I6: 53 | J6: =IF(AND(ISNUMBER(H6),ISNUMBER(I6)),IF(H6=0,"",I6/H6),"varies") -> 0.53 | K6: 17 | L6: 3 | M6: 5 | N6: 6 | O6: 15 | P6: 20 | Q6: 0.1 | R6: 0.1 | S6: 0.7 | T6: 0.1 | U6: 0 | V6: 0 | W6: =SUM(Q6:V6) -> 1 | X6: =IF(E6<>"Combat","—",IFERROR(INDEX(Affinity!$A$2:$A$7,MATCH(MAX(INDEX(Affinity!$B$2:$V$7,0,MATCH(A6,Affinity!$B$1:$V$1,0))),INDEX(Affinity!$B$2:$V$7,0,MATCH(A6,Affinity!$B$1:$V$1,0)),0)),"—")) -> Earnest | Y6: 5 | Z6: 45000 | AA6: 1 | AB6: 70 | AC6: 0 | AD6: -5 | AE6: 0 | AF6: -3 | AG6: 10 | AH6: 0 | AI6: Shared_pool | AJ6: per_turn | AL6: stream | AM6: 3 | AN6: town_hall | AO6: No | AR6: Yes | AY6: 2 | AZ6: 2
A7: ST06 | B7: TV Debate | C7: 討論番組 | D7: Tōron Bangumi | E7: Combat | F7: Viewer Interest | G7: Numerical | H7: 100 | I7: 65 | J7: =IF(AND(ISNUMBER(H7),ISNUMBER(I7)),IF(H7=0,"",I7/H7),"varies") -> 0.65 | K7: 5 | L7: 5 | M7: 6 | N7: 5 | O7: 60 | P7: 50 | Q7: 0.8 | R7: 0 | S7: 0.2 | T7: 0 | U7: 0 | V7: 0 | W7: =SUM(Q7:V7) -> 1 | X7: =IF(E7<>"Combat","—",IFERROR(INDEX(Affinity!$A$2:$A$7,MATCH(MAX(INDEX(Affinity!$B$2:$V$7,0,MATCH(A7,Affinity!$B$1:$V$1,0))),INDEX(Affinity!$B$2:$V$7,0,MATCH(A7,Affinity!$B$1:$V$1,0)),0)),"—")) -> Appeal | Y7: 3 | Z7: 40000 | AA7: 2 | AB7: 55 | AC7: 2 | AD7: -1 | AE7: 0 | AF7: -3 | AG7: 0 | AH7: -1 | AI7: Survival | AJ7: per_turn | AL7: single | AM7: 1 | AO7: Yes | AR7: Yes | AU7: 0 | AV7: 3 | AY7: 3 | BA7: 3
A8: ST07 | B8: Office Hours | C8: 陳情 | D8: Chinjō | E8: Non-combat | F8: Time slots | G8: Numerical | H8: 10 | I8: 10 | J8: =IF(AND(ISNUMBER(H8),ISNUMBER(I8)),IF(H8=0,"",I8/H8),"varies") -> 1 | K8: 9 | L8: 5 | M8: 5 | N8: 7 | O8: 0 | P8: 0 | Q8: 0 | R8: 0 | S8: 0.7 | T8: 0.3 | U8: 0 | V8: 0 | W8: =SUM(Q8:V8) -> 1 | X8: =IF(E8<>"Combat","—",IFERROR(INDEX(Affinity!$A$2:$A$7,MATCH(MAX(INDEX(Affinity!$B$2:$V$7,0,MATCH(A8,Affinity!$B$1:$V$1,0))),INDEX(Affinity!$B$2:$V$7,0,MATCH(A8,Affinity!$B$1:$V$1,0)),0)),"—")) -> — | Y8: 5 | Z8: 10000 | AA8: 0 | AB8: 50 | AC8: 0 | AD8: 0 | AE8: 0 | AF8: 0 | AG8: 0 | AH8: 0 | AI8: Shared_pool | AJ8: per_turn | AL8: single | AM8: 5 | AO8: No | AQ8: No | AY8: 2 | AZ8: 1
A9: ST08 | B9: Party Steering Committee | C9: 党運営委員会 | D9: Tō Un'ei Iinkai | E9: Combat | F9: Support | G9: Percentage | H9: 100 | I9: 43 | J9: =IF(AND(ISNUMBER(H9),ISNUMBER(I9)),IF(H9=0,"",I9/H9),"varies") -> 0.43 | K9: 5 | L9: 3 | M9: 5 | N9: 5 | O9: 20 | P9: 50 | Q9: 0 | R9: 0.7 | S9: 0 | T9: 0 | U9: 0 | V9: 0.3 | W9: =SUM(Q9:V9) -> 1 | X9: =IF(E9<>"Combat","—",IFERROR(INDEX(Affinity!$A$2:$A$7,MATCH(MAX(INDEX(Affinity!$B$2:$V$7,0,MATCH(A9,Affinity!$B$1:$V$1,0))),INDEX(Affinity!$B$2:$V$7,0,MATCH(A9,Affinity!$B$1:$V$1,0)),0)),"—")) -> Divisive | Y9: 0 | Z9: 20000 | AA9: 2 | AB9: 90 | AC9: 5 | AD9: 0 | AE9: 0 | AF9: -3 | AG9: 5 | AH9: -5 | AI9: Shared_pool | AJ9: pool | AK9: 8 | AL9: single | AM9: 1 | AO9: No | AR9: Yes | AT9: Yes | AY9: 4 | BA9: 1
A10: ST09 | B10: Committee on Ethics and Prosecution | C10: 倫理起訴委員会 | D10: Rinri Kiso Iinkai | E10: Combat | F10: Favorability | G10: Percentage | H10: 100 | I10: 78 | J10: =IF(AND(ISNUMBER(H10),ISNUMBER(I10)),IF(H10=0,"",I10/H10),"varies") -> 0.78 | K10: 10 | L10: 5 | M10: 5 | N10: 5 | O10: 20 | P10: 30 | Q10: 0.35 | R10: 0.4 | S10: 0 | T10: 0 | U10: 0.1 | V10: 0.15 | W10: =SUM(Q10:V10) -> 1 | X10: =IF(E10<>"Combat","—",IFERROR(INDEX(Affinity!$A$2:$A$7,MATCH(MAX(INDEX(Affinity!$B$2:$V$7,0,MATCH(A10,Affinity!$B$1:$V$1,0))),INDEX(Affinity!$B$2:$V$7,0,MATCH(A10,Affinity!$B$1:$V$1,0)),0)),"—")) -> Emotional | Y10: 2 | Z10: 20000 | AA10: 2 | AB10: 40 | AC10: 2 | AD10: 0 | AE10: 0 | AF10: 0 | AG10: 0 | AH10: 0 | AI10: Shared_pool | AJ10: per_turn | AL10: reset | AM10: 4 | AO10: No | AR10: Yes | AY10: 4 | BA10: 1
A11: ST10 | B11: Committee on the Environment | C11: 環境委員会 | D11: Kankyō Iinkai | E11: Combat | F11: Favorability | G11: Percentage | H11: 100 | I11: 66 | J11: =IF(AND(ISNUMBER(H11),ISNUMBER(I11)),IF(H11=0,"",I11/H11),"varies") -> 0.66 | K11: 10 | L11: 5 | M11: 5 | N11: 7 | O11: 30 | P11: 30 | Q11: 0 | R11: 0.1 | S11: 0.65 | T11: 0 | U11: 0.2 | V11: 0.05 | W11: =SUM(Q11:V11) -> 1 | X11: =IF(E11<>"Combat","—",IFERROR(INDEX(Affinity!$A$2:$A$7,MATCH(MAX(INDEX(Affinity!$B$2:$V$7,0,MATCH(A11,Affinity!$B$1:$V$1,0))),INDEX(Affinity!$B$2:$V$7,0,MATCH(A11,Affinity!$B$1:$V$1,0)),0)),"—")) -> Earnest | Y11: 2 | Z11: 10000 | AA11: 1 | AB11: 40 | AC11: 0 | AD11: -1 | AE11: 1000 | AF11: 0 | AG11: 1 | AH11: 0 | AI11: Shared_pool | AJ11: per_turn | AL11: reset | AM11: 2 | AO11: No | AR11: Yes | AY11: 4 | BA11: 1
A12: ST11 | B12: Committee on War | C12: 戦争委員会 | D12: Sensō Iinkai | E12: Combat | F12: Favorability | G12: Percentage | H12: 100 | I12: 72 | J12: =IF(AND(ISNUMBER(H12),ISNUMBER(I12)),IF(H12=0,"",I12/H12),"varies") -> 0.72 | K12: 10 | L12: 3 | M12: 5 | N12: 5 | O12: 25 | P12: 25 | Q12: 0.55 | R12: 0 | S12: 0.05 | T12: 0.25 | U12: 0.15 | V12: 0 | W12: =SUM(Q12:V12) -> 1 | X12: =IF(E12<>"Combat","—",IFERROR(INDEX(Affinity!$A$2:$A$7,MATCH(MAX(INDEX(Affinity!$B$2:$V$7,0,MATCH(A12,Affinity!$B$1:$V$1,0))),INDEX(Affinity!$B$2:$V$7,0,MATCH(A12,Affinity!$B$1:$V$1,0)),0)),"—")) -> Divisive | Y12: 0 | Z12: 10000 | AA12: 1 | AB12: 20 | AC12: 2 | AD12: 0 | AE12: 0 | AF12: 0 | AG12: 1 | AH12: 0 | AI12: Shared_pool | AJ12: per_turn | AL12: reset | AM12: 2 | AO12: No | AR12: Yes | AY12: 4 | BA12: 1
A13: ST12 | B13: Committee on the National Assembly | C13: 国会管理委員会 | D13: Kokkai Kanri Iinkai | E13: Combat | F13: Favorability | G13: Percentage | H13: 100 | I13: 90 | J13: =IF(AND(ISNUMBER(H13),ISNUMBER(I13)),IF(H13=0,"",I13/H13),"varies") -> 0.9 | K13: 10 | L13: 4 | M13: 5 | N13: 7 | O13: 35 | P13: 30 | Q13: 0 | R13: 0.5 | S13: 0 | T13: 0 | U13: 0.5 | V13: 0 | W13: =SUM(Q13:V13) -> 1 | X13: =IF(E13<>"Combat","—",IFERROR(INDEX(Affinity!$A$2:$A$7,MATCH(MAX(INDEX(Affinity!$B$2:$V$7,0,MATCH(A13,Affinity!$B$1:$V$1,0))),INDEX(Affinity!$B$2:$V$7,0,MATCH(A13,Affinity!$B$1:$V$1,0)),0)),"—")) -> Data Driven | Y13: 0 | Z13: 10000 | AA13: 1 | AB13: 15 | AC13: 3 | AD13: 0 | AE13: 0 | AF13: 0 | AG13: 1 | AH13: 0 | AI13: Shared_pool | AJ13: per_turn | AL13: reset | AM13: 3 | AO13: No | AR13: Yes | AY13: 4 | BA13: 1
A14: ST13 | B14: Committee on Agriculture | C14: 農林水産委員会 | D14: Nōrin Suisan Iinkai | E14: Combat | F14: Favorability | G14: Percentage | H14: 100 | I14: 66 | J14: =IF(AND(ISNUMBER(H14),ISNUMBER(I14)),IF(H14=0,"",I14/H14),"varies") -> 0.66 | K14: 10 | L14: 5 | M14: 5 | N14: 7 | O14: 30 | P14: 30 | Q14: 0 | R14: 0.2 | S14: 0.6 | T14: 0 | U14: 0 | V14: 0.2 | W14: =SUM(Q14:V14) -> 1 | X14: =IF(E14<>"Combat","—",IFERROR(INDEX(Affinity!$A$2:$A$7,MATCH(MAX(INDEX(Affinity!$B$2:$V$7,0,MATCH(A14,Affinity!$B$1:$V$1,0))),INDEX(Affinity!$B$2:$V$7,0,MATCH(A14,Affinity!$B$1:$V$1,0)),0)),"—")) -> Emotional | Y14: 1 | Z14: 10000 | AA14: 1 | AB14: 40 | AC14: 0 | AD14: -1 | AE14: 1000 | AF14: 0 | AG14: 1 | AH14: 0 | AI14: Shared_pool | AJ14: per_turn | AL14: reset | AM14: 2 | AO14: No | AR14: Yes | AY14: 4 | BA14: 1
A15: ST14 | B15: Committee on Foreign Affairs | C15: 外務委員会 | D15: Gaimu Iinkai | E15: Combat | F15: Favorability | G15: Percentage | H15: 100 | I15: 78 | J15: =IF(AND(ISNUMBER(H15),ISNUMBER(I15)),IF(H15=0,"",I15/H15),"varies") -> 0.78 | K15: 10 | L15: 4 | M15: 5 | N15: 5 | O15: 25 | P15: 30 | Q15: 0.4 | R15: 0.2 | S15: 0 | T15: 0.2 | U15: 0.2 | V15: 0 | W15: =SUM(Q15:V15) -> 1 | X15: =IF(E15<>"Combat","—",IFERROR(INDEX(Affinity!$A$2:$A$7,MATCH(MAX(INDEX(Affinity!$B$2:$V$7,0,MATCH(A15,Affinity!$B$1:$V$1,0))),INDEX(Affinity!$B$2:$V$7,0,MATCH(A15,Affinity!$B$1:$V$1,0)),0)),"—")) -> Appeal | Y15: 0 | Z15: 20000 | AA15: 2 | AB15: 40 | AC15: 2 | AD15: 0 | AE15: 0 | AF15: 0 | AG15: 1 | AH15: 0 | AI15: Shared_pool | AJ15: per_turn | AL15: reset | AM15: 3 | AO15: No | AR15: Yes | AY15: 4 | BA15: 1
A16: ST15 | B16: Committee on Construction and Development | C16: 建設成長委員会 | D16: Kensetsu Seichō Iinkai | E16: Combat | F16: Favorability | G16: Percentage | H16: 100 | I16: 72 | J16: =IF(AND(ISNUMBER(H16),ISNUMBER(I16)),IF(H16=0,"",I16/H16),"varies") -> 0.72 | K16: 10 | L16: 3 | M16: 5 | N16: 5 | O16: 30 | P16: 35 | Q16: 0.2 | R16: 0 | S16: 0.2 | T16: 0.2 | U16: 0.2 | V16: 0.2 | W16: =SUM(Q16:V16) -> 1 | X16: =IF(E16<>"Combat","—",IFERROR(INDEX(Affinity!$A$2:$A$7,MATCH(MAX(INDEX(Affinity!$B$2:$V$7,0,MATCH(A16,Affinity!$B$1:$V$1,0))),INDEX(Affinity!$B$2:$V$7,0,MATCH(A16,Affinity!$B$1:$V$1,0)),0)),"—")) -> Duplicitous | Y16: 3 | Z16: 40000 | AA16: 3 | AB16: 75 | AC16: 3 | AD16: -2 | AE16: 0 | AF16: 0 | AG16: 2 | AH16: 0 | AI16: Shared_pool | AJ16: per_turn | AL16: reset | AM16: 2 | AO16: No | AR16: Yes | AY16: 4 | BA16: 1
A17: ST16 | B17: Committee on Finance | C17: 財務委員会 | D17: Zaimu Iinkai | E17: Combat | F17: Favorability | G17: Percentage | H17: 100 | I17: 84 | J17: =IF(AND(ISNUMBER(H17),ISNUMBER(I17)),IF(H17=0,"",I17/H17),"varies") -> 0.84 | K17: 10 | L17: 4 | M17: 5 | N17: 3 | O17: 35 | P17: 40 | Q17: 0.25 | R17: 0 | S17: 0 | T17: 0.35 | U17: 0.4 | V17: 0 | W17: =SUM(Q17:V17) -> 1 | X17: =IF(E17<>"Combat","—",IFERROR(INDEX(Affinity!$A$2:$A$7,MATCH(MAX(INDEX(Affinity!$B$2:$V$7,0,MATCH(A17,Affinity!$B$1:$V$1,0))),INDEX(Affinity!$B$2:$V$7,0,MATCH(A17,Affinity!$B$1:$V$1,0)),0)),"—")) -> Data Driven | Y17: 1 | Z17: 50000 | AA17: 5 | AB17: 75 | AC17: 5 | AD17: 0 | AE17: 0 | AF17: 0 | AG17: 2 | AH17: 0 | AI17: Shared_pool | AJ17: per_turn | AL17: reset | AM17: 3 | AO17: No | AR17: Yes | AY17: 4 | BA17: 1
A18: ST17 | B18: Committee on Government Administration | C18: 政府行政委員会 | D18: Seifu Gyōsei Iinkai | E18: Combat | F18: Favorability | G18: Percentage | H18: 100 | I18: 78 | J18: =IF(AND(ISNUMBER(H18),ISNUMBER(I18)),IF(H18=0,"",I18/H18),"varies") -> 0.78 | K18: 10 | L18: 5 | M18: 5 | N18: 5 | O18: 30 | P18: 40 | Q18: 0.15 | R18: 0 | S18: 0.1 | T18: 0.1 | U18: 0.65 | V18: 0 | W18: =SUM(Q18:V18) -> 1 | X18: =IF(E18<>"Combat","—",IFERROR(INDEX(Affinity!$A$2:$A$7,MATCH(MAX(INDEX(Affinity!$B$2:$V$7,0,MATCH(A18,Affinity!$B$1:$V$1,0))),INDEX(Affinity!$B$2:$V$7,0,MATCH(A18,Affinity!$B$1:$V$1,0)),0)),"—")) -> Data Driven | Y18: 1 | Z18: 50000 | AA18: 5 | AB18: 40 | AC18: 5 | AD18: 0 | AE18: 0 | AF18: 0 | AG18: 2 | AH18: 0 | AI18: Shared_pool | AJ18: per_turn | AL18: reset | AM18: 4 | AO18: No | AR18: Yes | AY18: 4 | BA18: 1
A19: ST18 | B19: Committee of the Cabinet | C19: 内閣員会 | D19: Naikaku Iinkai | E19: Combat | F19: Consensus | G19: Percentage | H19: 100 | I19: 60 | J19: =IF(AND(ISNUMBER(H19),ISNUMBER(I19)),IF(H19=0,"",I19/H19),"varies") -> 0.6 | K19: 10 | L19: 26 | M19: 6 | N19: 3 | O19: 30 | P19: 55 | Q19: 0 | R19: 0.1 | S19: 0 | T19: 0 | U19: 0 | V19: 0.9 | W19: =SUM(Q19:V19) -> 1 | X19: =IF(E19<>"Combat","—",IFERROR(INDEX(Affinity!$A$2:$A$7,MATCH(MAX(INDEX(Affinity!$B$2:$V$7,0,MATCH(A19,Affinity!$B$1:$V$1,0))),INDEX(Affinity!$B$2:$V$7,0,MATCH(A19,Affinity!$B$1:$V$1,0)),0)),"—")) -> Data Driven | Y19: 0 | Z19: 100000 | AA19: 15 | AB19: 120 | AC19: 15 | AD19: 0 | AE19: 0 | AF19: -1 | AG19: 20 | AH19: -10 | AI19: Shared_pool | AJ19: pool | AK19: 26 | AL19: reset | AM19: 2 | AO19: No | AR19: Yes | AY19: 4 | BA19: 1
A20: ST19 | B20: Media Ambush | C20: ぶら下がり取材 | D20: Burasagari Shuzai | E20: Combat | F20: Press tone | G20: Percentage | H20: 50 | I20: 30 | J20: =IF(AND(ISNUMBER(H20),ISNUMBER(I20)),IF(H20=0,"",I20/H20),"varies") -> 0.6 | K20: 11 | L20: 3 | M20: 3 | N20: 2 | O20: 5 | P20: 15 | Q20: 1 | R20: 0 | S20: 0 | T20: 0 | U20: 0 | V20: 0 | W20: =SUM(Q20:V20) -> 1 | X20: =IF(E20<>"Combat","—",IFERROR(INDEX(Affinity!$A$2:$A$7,MATCH(MAX(INDEX(Affinity!$B$2:$V$7,0,MATCH(A20,Affinity!$B$1:$V$1,0))),INDEX(Affinity!$B$2:$V$7,0,MATCH(A20,Affinity!$B$1:$V$1,0)),0)),"—")) -> Emotional | Y20: 2 | Z20: 15000 | AA20: 3 | AB20: 70 | AC20: 1 | AD20: -1 | AE20: 0 | AF20: -1 | AG20: 5 | AH20: -5 | AI20: Shared_pool | AJ20: pool | AK20: 15 | AL20: continuous | AM20: 2 | AN20: media_ambush | AO20: No | AP20: No | AQ20: No | AR20: No | AY20: 1 | BA20: 1
A21: ST20 | B21: Lobbyist Meeting | C21: ロビー活動 | D21: Robī Katsudō | E21: Combat | F21: Appeasement | G21: Percentage | H21: 50 | I21: 25 | J21: =IF(AND(ISNUMBER(H21),ISNUMBER(I21)),IF(H21=0,"",I21/H21),"varies") -> 0.5 | K21: 7 | L21: 3 | M21: 5 | N21: 6 | O21: 5 | P21: 15 | Q21: 0 | R21: 0 | S21: 0 | T21: 1 | U21: 0 | V21: 0 | W21: =SUM(Q21:V21) -> 1 | X21: =IF(E21<>"Combat","—",IFERROR(INDEX(Affinity!$A$2:$A$7,MATCH(MAX(INDEX(Affinity!$B$2:$V$7,0,MATCH(A21,Affinity!$B$1:$V$1,0))),INDEX(Affinity!$B$2:$V$7,0,MATCH(A21,Affinity!$B$1:$V$1,0)),0)),"—")) -> Appeal | Y21: 0 | Z21: 50000 | AA21: 0 | AB21: 75 | AC21: 0 | AD21: 0 | AE21: 0 | AF21: 0 | AG21: 0 | AH21: -1 | AI21: Shared_pool | AJ21: pool | AK21: 12 | AL21: single | AM21: 1 | AN21: lobbyist_meeting | AO21: No | AR21: Yes | AY21: 2
A22: ST21 | B22: Policy Study Session | C22: 政策検討会 | D22: Seisaku Kentōkai | E22: Combat | F22: Consensus | G22: Percentage | H22: 50 | I22: 35 | J22: =IF(AND(ISNUMBER(H22),ISNUMBER(I22)),IF(H22=0,"",I22/H22),"varies") -> 0.7 | K22: 10 | L22: 5 | M22: 5 | N22: 10 | O22: 1 | P22: 10 | Q22: 0 | R22: 0 | S22: 0 | T22: 0 | U22: 0.8 | V22: 0.2 | W22: =SUM(Q22:V22) -> 1 | X22: =IF(E22<>"Combat","—",IFERROR(INDEX(Affinity!$A$2:$A$7,MATCH(MAX(INDEX(Affinity!$B$2:$V$7,0,MATCH(A22,Affinity!$B$1:$V$1,0))),INDEX(Affinity!$B$2:$V$7,0,MATCH(A22,Affinity!$B$1:$V$1,0)),0)),"—")) -> Earnest | Y22: 1 | Z22: 15000 | AA22: 1 | AB22: 55 | AC22: 1 | AD22: 0 | AE22: 0 | AF22: 0 | AG22: 5 | AH22: 0 | AI22: Shared_pool | AJ22: per_turn | AL22: stream | AM22: 2 | AN22: policy_study | AO22: No | AQ22: No | AR22: Yes | AY22: 2
A23: ST22 | B23: Party Steering Committee Check-In | C23: 党運営委員会面談 | D23: Tō Un'ei Iinkai Mendan | E23: Non-combat | F23: Time slots | G23: Numerical | H23: 10 | I23: 10 | J23: 1 | K23: 10 | L23: 5 | M23: 5 | N23: 7 | O23: 0 | P23: 0 | Q23: 0 | R23: 0.7 | S23: 0 | T23: 0.3 | U23: 0 | V23: 0 | W23: 1 | X23: — | Y23: 0 | Z23: 0 | AA23: 0 | AB23: 30 | AC23: 5 | AD23: 0 | AE23: 0 | AF23: 0 | AG23: 0 | AH23: 0 | AI23: Shared_pool | AJ23: per_turn | AL23: single | AM23: 1 | AO23: No | AY23: 2 | BA23: 1
A24: ST23 | B24: National Assembly Floor Voting | C24: 本会議採決 | D24: Honkaigi Saiketsu | E24: Vote | AQ24: No | AY24: 1
A25: ST24 | B25: Town Hall on Commuter Fares | C25: 運賃を巡る住民集会 | D25: Unchin o Meguru Jūmin Shūkai | E25: Combat | F25: Appeasement | G25: Percentage | H25: 100 | I25: 53 | J25: =IF(AND(ISNUMBER(H25),ISNUMBER(I25)),IF(H25=0,"",I25/H25),"varies") -> 0.53 | K25: 17 | L25: 3 | M25: 5 | N25: 6 | O25: 15 | P25: 15 | Q25: 0.1 | R25: 0.1 | S25: 0.6 | T25: 0.1 | U25: 0 | V25: 0.1 | W25: =SUM(Q25:V25) -> 1 | X25: =IF(E25<>"Combat","—",IFERROR(INDEX(Affinity!$A$2:$A$7,MATCH(MAX(INDEX(Affinity!$B$2:$AD$7,0,MATCH(A25,Affinity!$B$1:$AD$1,0))),INDEX(Affinity!$B$2:$AD$7,0,MATCH(A25,Affinity!$B$1:$AD$1,0)),0)),"—")) -> Emotional | Y25: 5 | Z25: 45000 | AA25: 1 | AB25: 70 | AC25: 0 | AD25: -5 | AE25: 0 | AF25: -3 | AG25: 10 | AH25: 0 | AI25: Shared_pool | AJ25: per_turn | AL25: stream | AM25: 3 | AN25: town_hall | AO25: No | AR25: Yes | AX25: ST05 | AY25: 2 | AZ25: 2
A26: ST25 | B26: Policy Study on Rail Timetables | C26: 鉄道ダイヤ政策検討会 | D26: Tetsudō Daiya Seisaku Kentōkai | E26: Combat | F26: Consensus | G26: Percentage | H26: 50 | I26: 43 | J26: =IF(AND(ISNUMBER(H26),ISNUMBER(I26)),IF(H26=0,"",I26/H26),"varies") -> 0.86 | K26: 10 | L26: 5 | M26: 5 | N26: 10 | O26: 2 | P26: 12 | Q26: 0 | R26: 0 | S26: 0.1 | T26: 0 | U26: 0.7 | V26: 0.2 | W26: =SUM(Q26:V26) -> 1 | X26: =IF(E26<>"Combat","—",IFERROR(INDEX(Affinity!$A$2:$A$7,MATCH(MAX(INDEX(Affinity!$B$2:$AD$7,0,MATCH(A26,Affinity!$B$1:$AD$1,0))),INDEX(Affinity!$B$2:$AD$7,0,MATCH(A26,Affinity!$B$1:$AD$1,0)),0)),"—")) -> Data Driven | Y26: 1 | Z26: 15000 | AA26: 1 | AB26: 55 | AC26: 1 | AD26: 0 | AE26: 0 | AF26: 0 | AG26: 5 | AH26: 0 | AI26: Shared_pool | AJ26: per_turn | AL26: stream | AM26: 2 | AN26: policy_study | AO26: No | AQ26: No | AR26: Yes | AX26: ST21 | AY26: 2
A27: ST26 | B27: Press Conference on Raising Train Fares | C27: 運賃改定記者会見 | D27: Unchin Kaitei Kisha Kaiken | E27: Combat | F27: Press tone | G27: Numerical | H27: 100 | I27: 58 | J27: =IF(AND(ISNUMBER(H27),ISNUMBER(I27)),IF(H27=0,"",I27/H27),"varies") -> 0.58 | K27: 6 | L27: 3 | M27: 5 | N27: 4 | O27: 20 | P27: 45 | Q27: 0.85 | R27: 0 | S27: 0.1 | T27: 0 | U27: 0 | V27: 0.05 | W27: =SUM(Q27:V27) -> 1 | X27: =IF(E27<>"Combat","—",IFERROR(INDEX(Affinity!$A$2:$A$7,MATCH(MAX(INDEX(Affinity!$B$2:$AD$7,0,MATCH(A27,Affinity!$B$1:$AD$1,0))),INDEX(Affinity!$B$2:$AD$7,0,MATCH(A27,Affinity!$B$1:$AD$1,0)),0)),"—")) -> Appeal | Y27: 1 | Z27: 30000 | AA27: 1 | AB27: 60 | AC27: 1 | AD27: 0 | AE27: 0 | AF27: -2 | AG27: 5 | AH27: -2 | AI27: Single | AJ27: per_turn | AL27: single | AM27: 1 | AO27: Yes | AQ27: No | AR27: Yes | AX27: ST04 | AY27: 2 | BA27: 2
A28: ST27 | B28: Hearing on Rail Safety | C28: 鉄道安全に関する公聴会 | D28: Tetsudō Anzen ni Kansuru Kōchōkai | E28: Combat | F28: Favorability | G28: Percentage | H28: 100 | I28: 78 | J28: =IF(AND(ISNUMBER(H28),ISNUMBER(I28)),IF(H28=0,"",I28/H28),"varies") -> 0.78 | K28: 10 | L28: 4 | M28: 5 | N28: 6 | O28: 30 | P28: 32 | Q28: 0 | R28: 0.2 | S28: 0.4 | T28: 0 | U28: 0.3 | V28: 0.1 | W28: =SUM(Q28:V28) -> 1 | X28: =IF(E28<>"Combat","—",IFERROR(INDEX(Affinity!$A$2:$A$7,MATCH(MAX(INDEX(Affinity!$B$2:$AD$7,0,MATCH(A28,Affinity!$B$1:$AD$1,0))),INDEX(Affinity!$B$2:$AD$7,0,MATCH(A28,Affinity!$B$1:$AD$1,0)),0)),"—")) -> Data Driven | Y28: 3 | Z28: 20000 | AA28: 3 | AB28: 45 | AC28: 3 | AD28: -2 | AE28: 0 | AF28: 0 | AG28: 2 | AH28: 0 | AI28: Shared_pool | AJ28: per_turn | AL28: reset | AM28: 2 | AO28: No | AR28: Yes | AX28: ST15 | AY28: 4 | BA28: 1
A29: ST28 | B29: Lobbyist Meeting on Fishing Quotas | C29: 漁獲枠に関するロビー活動 | D29: Gyokaku-waku ni Kansuru Robī Katsudō | E29: Combat | F29: Appeasement | G29: Percentage | H29: 50 | I29: 25 | J29: =IF(AND(ISNUMBER(H29),ISNUMBER(I29)),IF(H29=0,"",I29/H29),"varies") -> 0.5 | K29: 7 | L29: 3 | M29: 5 | N29: 6 | O29: 5 | P29: 15 | Q29: 0 | R29: 0 | S29: 0 | T29: 1 | U29: 0 | V29: 0 | W29: =SUM(Q29:V29) -> 1 | X29: =IF(E29<>"Combat","—",IFERROR(INDEX(Affinity!$A$2:$A$7,MATCH(MAX(INDEX(Affinity!$B$2:$AD$7,0,MATCH(A29,Affinity!$B$1:$AD$1,0))),INDEX(Affinity!$B$2:$AD$7,0,MATCH(A29,Affinity!$B$1:$AD$1,0)),0)),"—")) -> Data Driven | Y29: 0 | Z29: 50000 | AA29: 0 | AB29: 75 | AC29: 0 | AD29: 0 | AE29: 0 | AF29: 0 | AG29: 0 | AH29: -1 | AI29: Shared_pool | AJ29: pool | AK29: 12 | AL29: single | AM29: 1 | AN29: lobbyist_meeting | AO29: No | AR29: Yes | AX29: ST20 | AY29: 2
A30: ST29 | B30: Town Hall at the Harbor | C30: 漁港の住民集会 | D30: Gyokō no Jūmin Shūkai | E30: Combat | F30: Appeasement | G30: Percentage | H30: 100 | I30: 53 | J30: =IF(AND(ISNUMBER(H30),ISNUMBER(I30)),IF(H30=0,"",I30/H30),"varies") -> 0.53 | K30: 17 | L30: 3 | M30: 5 | N30: 6 | O30: 15 | P30: 20 | Q30: 0.05 | R30: 0.05 | S30: 0.7 | T30: 0.1 | U30: 0 | V30: 0.1 | W30: =SUM(Q30:V30) -> 1 | X30: =IF(E30<>"Combat","—",IFERROR(INDEX(Affinity!$A$2:$A$7,MATCH(MAX(INDEX(Affinity!$B$2:$AD$7,0,MATCH(A30,Affinity!$B$1:$AD$1,0))),INDEX(Affinity!$B$2:$AD$7,0,MATCH(A30,Affinity!$B$1:$AD$1,0)),0)),"—")) -> Emotional | Y30: 5 | Z30: 45000 | AA30: 1 | AB30: 70 | AC30: 0 | AD30: -5 | AE30: 0 | AF30: -3 | AG30: 10 | AH30: 0 | AI30: Shared_pool | AJ30: per_turn | AL30: stream | AM30: 3 | AN30: town_hall | AO30: No | AR30: Yes | AX30: OUT_HARBOR_1; OUT_HARBOR_2 | AY30: 2 | AZ30: 2
A31: ST30 | B31: Media Ambush on Seafood Labeling | C31: 水産物表示を巡るぶら下がり取材 | D31: Suisanbutsu Hyōji o Meguru Burasagari Shuzai | E31: Combat | F31: Press tone | G31: Percentage | H31: 50 | I31: 30 | J31: =IF(AND(ISNUMBER(H31),ISNUMBER(I31)),IF(H31=0,"",I31/H31),"varies") -> 0.6 | K31: 11 | L31: 3 | M31: 3 | N31: 2 | O31: 5 | P31: 15 | Q31: 1 | R31: 0 | S31: 0 | T31: 0 | U31: 0 | V31: 0 | W31: =SUM(Q31:V31) -> 1 | X31: =IF(E31<>"Combat","—",IFERROR(INDEX(Affinity!$A$2:$A$7,MATCH(MAX(INDEX(Affinity!$B$2:$AD$7,0,MATCH(A31,Affinity!$B$1:$AD$1,0))),INDEX(Affinity!$B$2:$AD$7,0,MATCH(A31,Affinity!$B$1:$AD$1,0)),0)),"—")) -> Appeal | Y31: 2 | Z31: 15000 | AA31: 3 | AB31: 70 | AC31: 1 | AD31: -1 | AE31: 0 | AF31: -1 | AG31: 5 | AH31: -5 | AI31: Shared_pool | AJ31: pool | AK31: 15 | AL31: continuous | AM31: 2 | AN31: media_ambush | AO31: No | AP31: No | AQ31: No | AR31: No | AX31: ST19 | AY31: 1 | BA31: 1
A32: ST31 | B32: Hearing on Fishery Quotas | C32: 漁獲枠に関する公聴会 | D32: Gyokaku-waku ni Kansuru Kōchōkai | E32: Combat | F32: Favorability | G32: Percentage | H32: 100 | I32: 72 | J32: =IF(AND(ISNUMBER(H32),ISNUMBER(I32)),IF(H32=0,"",I32/H32),"varies") -> 0.72 | K32: 10 | L32: 4 | M32: 5 | N32: 6 | O32: 30 | P32: 30 | Q32: 0 | R32: 0.2 | S32: 0.5 | T32: 0 | U32: 0.1 | V32: 0.2 | W32: =SUM(Q32:V32) -> 1 | X32: =IF(E32<>"Combat","—",IFERROR(INDEX(Affinity!$A$2:$A$7,MATCH(MAX(INDEX(Affinity!$B$2:$AD$7,0,MATCH(A32,Affinity!$B$1:$AD$1,0))),INDEX(Affinity!$B$2:$AD$7,0,MATCH(A32,Affinity!$B$1:$AD$1,0)),0)),"—")) -> Earnest | Y32: 1 | Z32: 10000 | AA32: 1 | AB32: 40 | AC32: 0 | AD32: -1 | AE32: 1000 | AF32: 0 | AG32: 1 | AH32: 0 | AI32: Shared_pool | AJ32: per_turn | AL32: reset | AM32: 2 | AO32: No | AR32: Yes | AX32: ST13 | AY32: 4 | BA32: 1
A33: ST32 | B33: Press Conference on Wilderness Protection | C33: 原生自然の保護記者会見 | D33: Gensei Shizen no Hogo Kisha Kaiken | E33: Combat | F33: Press tone | G33: Numerical | H33: 100 | I33: 55 | J33: =IF(AND(ISNUMBER(H33),ISNUMBER(I33)),IF(H33=0,"",I33/H33),"varies") -> 0.55 | K33: 6 | L33: 3 | M33: 5 | N33: 4 | O33: 20 | P33: 45 | Q33: 0.9 | R33: 0 | S33: 0 | T33: 0 | U33: 0.05 | V33: 0.05 | W33: =SUM(Q33:V33) -> 1 | X33: =IF(E33<>"Combat","—",IFERROR(INDEX(Affinity!$A$2:$A$7,MATCH(MAX(INDEX(Affinity!$B$2:$CU$7,0,MATCH(A33,Affinity!$B$1:$CU$1,0))),INDEX(Affinity!$B$2:$CU$7,0,MATCH(A33,Affinity!$B$1:$CU$1,0)),0)),"—")) -> Earnest | Y33: 1 | Z33: 30000 | AA33: 1 | AB33: 60 | AC33: 1 | AD33: 0 | AE33: 0 | AF33: -2 | AG33: 5 | AH33: -2 | AI33: Single | AJ33: per_turn | AL33: single | AM33: 1 | AN33: press_conference | AO33: Yes | AQ33: No | AR33: Yes | AX33: ST04 | AY33: 2 | BA33: 2
A34: ST33 | B34: Hearing on Wilderness Protection | C34: 原生自然の保護に関する公聴会 | D34: Gensei Shizen no Hogo ni Kansuru Kōchōkai | E34: Combat | F34: Favorability | G34: Percentage | H34: 100 | I34: 66 | J34: =IF(AND(ISNUMBER(H34),ISNUMBER(I34)),IF(H34=0,"",I34/H34),"varies") -> 0.66 | K34: 10 | L34: 5 | M34: 5 | N34: 7 | O34: 30 | P34: 30 | Q34: 0 | R34: 0.1 | S34: 0.65 | T34: 0 | U34: 0.2 | V34: 0.05 | W34: =SUM(Q34:V34) -> 1 | X34: =IF(E34<>"Combat","—",IFERROR(INDEX(Affinity!$A$2:$A$7,MATCH(MAX(INDEX(Affinity!$B$2:$CU$7,0,MATCH(A34,Affinity!$B$1:$CU$1,0))),INDEX(Affinity!$B$2:$CU$7,0,MATCH(A34,Affinity!$B$1:$CU$1,0)),0)),"—")) -> Earnest | Y34: 2 | Z34: 10000 | AA34: 1 | AB34: 40 | AC34: 0 | AD34: -1 | AE34: 1000 | AF34: 0 | AG34: 1 | AH34: 0 | AI34: Shared_pool | AJ34: per_turn | AL34: reset | AM34: 2 | AO34: No | AR34: Yes | AX34: ST10 | AY34: 4 | BA34: 1
A35: ST34 | B35: Town Hall on Wilderness Protection | C35: 原生自然の保護を巡る住民集会 | D35: Gensei Shizen no Hogo o Meguru Jūmin Shūkai | E35: Combat | F35: Appeasement | G35: Percentage | H35: 100 | I35: 53 | J35: =IF(AND(ISNUMBER(H35),ISNUMBER(I35)),IF(H35=0,"",I35/H35),"varies") -> 0.53 | K35: 17 | L35: 3 | M35: 5 | N35: 6 | O35: 15 | P35: 20 | Q35: 0.1 | R35: 0.1 | S35: 0.7 | T35: 0.1 | U35: 0 | V35: 0 | W35: =SUM(Q35:V35) -> 1 | X35: =IF(E35<>"Combat","—",IFERROR(INDEX(Affinity!$A$2:$A$7,MATCH(MAX(INDEX(Affinity!$B$2:$CU$7,0,MATCH(A35,Affinity!$B$1:$CU$1,0))),INDEX(Affinity!$B$2:$CU$7,0,MATCH(A35,Affinity!$B$1:$CU$1,0)),0)),"—")) -> Emotional | Y35: 5 | Z35: 45000 | AA35: 1 | AB35: 70 | AC35: 0 | AD35: -5 | AE35: 0 | AF35: -3 | AG35: 10 | AH35: 0 | AI35: Shared_pool | AJ35: per_turn | AL35: stream | AM35: 3 | AN35: town_hall | AO35: No | AR35: Yes | AX35: ST05 | AY35: 2 | AZ35: 2
A36: ST35 | B36: Party Caucus on Wilderness Protection | C36: 原生自然の保護党内会合 | D36: Gensei Shizen no Hogo Tōnai Kaigō | E36: Combat | F36: Support | G36: Percentage | H36: 100 | I36: 49 | J36: =IF(AND(ISNUMBER(H36),ISNUMBER(I36)),IF(H36=0,"",I36/H36),"varies") -> 0.49 | K36: 10 | L36: 3 | M36: 5 | N36: 5 | O36: 20 | P36: 40 | Q36: 0 | R36: 0.55 | S36: 0 | T36: 0 | U36: 0 | V36: 0.45 | W36: =SUM(Q36:V36) -> 1 | X36: =IF(E36<>"Combat","—",IFERROR(INDEX(Affinity!$A$2:$A$7,MATCH(MAX(INDEX(Affinity!$B$2:$CU$7,0,MATCH(A36,Affinity!$B$1:$CU$1,0))),INDEX(Affinity!$B$2:$CU$7,0,MATCH(A36,Affinity!$B$1:$CU$1,0)),0)),"—")) -> Earnest | Y36: 0 | Z36: 20000 | AA36: 1 | AB36: 90 | AC36: 2 | AD36: 0 | AE36: 0 | AF36: -1 | AG36: 1 | AH36: -2 | AI36: Shared_pool | AJ36: per_turn | AL36: continuous | AM36: 2 | AO36: No | AR36: Yes | AT36: Yes | AX36: ST03 | AY36: 4
A37: ST36 | B37: Town Hall on Rural Hospitals | C37: 地方病院網を巡る住民集会 | D37: Chihō Byōin-mō o Meguru Jūmin Shūkai | E37: Combat | F37: Appeasement | G37: Percentage | H37: 100 | I37: 53 | J37: =IF(AND(ISNUMBER(H37),ISNUMBER(I37)),IF(H37=0,"",I37/H37),"varies") -> 0.53 | K37: 17 | L37: 3 | M37: 5 | N37: 6 | O37: 15 | P37: 20 | Q37: 0.1 | R37: 0.1 | S37: 0.7 | T37: 0.1 | U37: 0 | V37: 0 | W37: =SUM(Q37:V37) -> 1 | X37: =IF(E37<>"Combat","—",IFERROR(INDEX(Affinity!$A$2:$A$7,MATCH(MAX(INDEX(Affinity!$B$2:$CU$7,0,MATCH(A37,Affinity!$B$1:$CU$1,0))),INDEX(Affinity!$B$2:$CU$7,0,MATCH(A37,Affinity!$B$1:$CU$1,0)),0)),"—")) -> Emotional | Y37: 5 | Z37: 45000 | AA37: 1 | AB37: 70 | AC37: 0 | AD37: -5 | AE37: 0 | AF37: -3 | AG37: 10 | AH37: 0 | AI37: Shared_pool | AJ37: per_turn | AL37: stream | AM37: 3 | AN37: town_hall | AO37: No | AR37: Yes | AX37: ST05 | AY37: 2 | AZ37: 2
A38: ST37 | B38: Hearing on Rural Hospitals | C38: 地方病院網に関する公聴会 | D38: Chihō Byōin-mō ni Kansuru Kōchōkai | E38: Combat | F38: Favorability | G38: Percentage | H38: 100 | I38: 81 | J38: =IF(AND(ISNUMBER(H38),ISNUMBER(I38)),IF(H38=0,"",I38/H38),"varies") -> 0.81 | K38: 10 | L38: 5 | M38: 5 | N38: 5 | O38: 30 | P38: 40 | Q38: 0.15 | R38: 0 | S38: 0.1 | T38: 0.1 | U38: 0.65 | V38: 0 | W38: =SUM(Q38:V38) -> 1 | X38: =IF(E38<>"Combat","—",IFERROR(INDEX(Affinity!$A$2:$A$7,MATCH(MAX(INDEX(Affinity!$B$2:$CU$7,0,MATCH(A38,Affinity!$B$1:$CU$1,0))),INDEX(Affinity!$B$2:$CU$7,0,MATCH(A38,Affinity!$B$1:$CU$1,0)),0)),"—")) -> Emotional | Y38: 1 | Z38: 50000 | AA38: 5 | AB38: 40 | AC38: 5 | AD38: 0 | AE38: 0 | AF38: 0 | AG38: 2 | AH38: 0 | AI38: Shared_pool | AJ38: per_turn | AL38: reset | AM38: 4 | AO38: No | AR38: Yes | AX38: ST17 | AY38: 4 | BA38: 1
A39: ST38 | B39: Policy Study on Rural Hospitals | C39: 地方病院網政策検討会 | D39: Chihō Byōin-mō Seisaku Kentōkai | E39: Combat | F39: Consensus | G39: Percentage | H39: 50 | I39: 44 | J39: =IF(AND(ISNUMBER(H39),ISNUMBER(I39)),IF(H39=0,"",I39/H39),"varies") -> 0.88 | K39: 10 | L39: 5 | M39: 5 | N39: 10 | O39: 1 | P39: 10 | Q39: 0 | R39: 0 | S39: 0 | T39: 0 | U39: 0.8 | V39: 0.2 | W39: =SUM(Q39:V39) -> 1 | X39: =IF(E39<>"Combat","—",IFERROR(INDEX(Affinity!$A$2:$A$7,MATCH(MAX(INDEX(Affinity!$B$2:$CU$7,0,MATCH(A39,Affinity!$B$1:$CU$1,0))),INDEX(Affinity!$B$2:$CU$7,0,MATCH(A39,Affinity!$B$1:$CU$1,0)),0)),"—")) -> Earnest | Y39: 1 | Z39: 15000 | AA39: 1 | AB39: 55 | AC39: 1 | AD39: 0 | AE39: 0 | AF39: 0 | AG39: 5 | AH39: 0 | AI39: Shared_pool | AJ39: per_turn | AL39: stream | AM39: 2 | AN39: policy_study | AO39: No | AQ39: No | AR39: Yes | AX39: ST21 | AY39: 2
A40: ST39 | B40: Party Caucus on Rural Hospitals | C40: 地方病院網党内会合 | D40: Chihō Byōin-mō Tōnai Kaigō | E40: Combat | F40: Support | G40: Percentage | H40: 100 | I40: 49 | J40: =IF(AND(ISNUMBER(H40),ISNUMBER(I40)),IF(H40=0,"",I40/H40),"varies") -> 0.49 | K40: 10 | L40: 3 | M40: 5 | N40: 5 | O40: 20 | P40: 40 | Q40: 0 | R40: 0.55 | S40: 0 | T40: 0 | U40: 0 | V40: 0.45 | W40: =SUM(Q40:V40) -> 1 | X40: =IF(E40<>"Combat","—",IFERROR(INDEX(Affinity!$A$2:$A$7,MATCH(MAX(INDEX(Affinity!$B$2:$CU$7,0,MATCH(A40,Affinity!$B$1:$CU$1,0))),INDEX(Affinity!$B$2:$CU$7,0,MATCH(A40,Affinity!$B$1:$CU$1,0)),0)),"—")) -> Emotional | Y40: 0 | Z40: 20000 | AA40: 1 | AB40: 90 | AC40: 2 | AD40: 0 | AE40: 0 | AF40: -1 | AG40: 1 | AH40: -2 | AI40: Shared_pool | AJ40: per_turn | AL40: continuous | AM40: 2 | AO40: No | AR40: Yes | AT40: Yes | AX40: ST03 | AY40: 4
A41: ST40 | B41: Policy Study on Digital Identity Cards | C41: デジタル身分証政策検討会 | D41: Dejitaru Mibun-shō Seisaku Kentōkai | E41: Combat | F41: Consensus | G41: Percentage | H41: 50 | I41: 44 | J41: =IF(AND(ISNUMBER(H41),ISNUMBER(I41)),IF(H41=0,"",I41/H41),"varies") -> 0.88 | K41: 10 | L41: 5 | M41: 5 | N41: 10 | O41: 1 | P41: 10 | Q41: 0 | R41: 0 | S41: 0 | T41: 0 | U41: 0.8 | V41: 0.2 | W41: =SUM(Q41:V41) -> 1 | X41: =IF(E41<>"Combat","—",IFERROR(INDEX(Affinity!$A$2:$A$7,MATCH(MAX(INDEX(Affinity!$B$2:$CU$7,0,MATCH(A41,Affinity!$B$1:$CU$1,0))),INDEX(Affinity!$B$2:$CU$7,0,MATCH(A41,Affinity!$B$1:$CU$1,0)),0)),"—")) -> Data Driven | Y41: 1 | Z41: 15000 | AA41: 1 | AB41: 55 | AC41: 1 | AD41: 0 | AE41: 0 | AF41: 0 | AG41: 5 | AH41: 0 | AI41: Shared_pool | AJ41: per_turn | AL41: stream | AM41: 2 | AN41: policy_study | AO41: No | AQ41: No | AR41: Yes | AX41: ST21 | AY41: 2
A42: ST41 | B42: TV Debate on Digital Identity Cards | C42: デジタル身分証テレビ討論 | D42: Dejitaru Mibun-shō Terebi Tōron | E42: Combat | F42: Viewer Interest | G42: Numerical | H42: 100 | I42: 65 | J42: =IF(AND(ISNUMBER(H42),ISNUMBER(I42)),IF(H42=0,"",I42/H42),"varies") -> 0.65 | K42: 5 | L42: 5 | M42: 6 | N42: 5 | O42: 60 | P42: 50 | Q42: 0.8 | R42: 0 | S42: 0.2 | T42: 0 | U42: 0 | V42: 0 | W42: =SUM(Q42:V42) -> 1 | X42: =IF(E42<>"Combat","—",IFERROR(INDEX(Affinity!$A$2:$A$7,MATCH(MAX(INDEX(Affinity!$B$2:$CU$7,0,MATCH(A42,Affinity!$B$1:$CU$1,0))),INDEX(Affinity!$B$2:$CU$7,0,MATCH(A42,Affinity!$B$1:$CU$1,0)),0)),"—")) -> Data Driven | Y42: 3 | Z42: 40000 | AA42: 2 | AB42: 55 | AC42: 2 | AD42: -1 | AE42: 0 | AF42: -3 | AG42: 0 | AH42: -1 | AI42: Survival | AJ42: per_turn | AL42: single | AM42: 1 | AO42: Yes | AR42: Yes | AU42: 0 | AV42: 3 | AX42: ST06 | AY42: 3 | BA42: 3
A43: ST42 | B43: Party Caucus on Digital Identity Cards | C43: デジタル身分証党内会合 | D43: Dejitaru Mibun-shō Tōnai Kaigō | E43: Combat | F43: Support | G43: Percentage | H43: 100 | I43: 49 | J43: =IF(AND(ISNUMBER(H43),ISNUMBER(I43)),IF(H43=0,"",I43/H43),"varies") -> 0.49 | K43: 10 | L43: 3 | M43: 5 | N43: 5 | O43: 20 | P43: 40 | Q43: 0 | R43: 0.55 | S43: 0 | T43: 0 | U43: 0 | V43: 0.45 | W43: =SUM(Q43:V43) -> 1 | X43: =IF(E43<>"Combat","—",IFERROR(INDEX(Affinity!$A$2:$A$7,MATCH(MAX(INDEX(Affinity!$B$2:$CU$7,0,MATCH(A43,Affinity!$B$1:$CU$1,0))),INDEX(Affinity!$B$2:$CU$7,0,MATCH(A43,Affinity!$B$1:$CU$1,0)),0)),"—")) -> Earnest | Y43: 0 | Z43: 20000 | AA43: 1 | AB43: 90 | AC43: 2 | AD43: 0 | AE43: 0 | AF43: -1 | AG43: 1 | AH43: -2 | AI43: Shared_pool | AJ43: per_turn | AL43: continuous | AM43: 2 | AO43: No | AR43: Yes | AT43: Yes | AX43: ST03 | AY43: 4
A44: ST43 | B44: Press Conference on Broadcaster Independence | C44: 公共放送の独立記者会見 | D44: Kōkyō Hōsō no Dokuritsu Kisha Kaiken | E44: Combat | F44: Press tone | G44: Numerical | H44: 100 | I44: 55 | J44: =IF(AND(ISNUMBER(H44),ISNUMBER(I44)),IF(H44=0,"",I44/H44),"varies") -> 0.55 | K44: 6 | L44: 3 | M44: 5 | N44: 4 | O44: 20 | P44: 45 | Q44: 0.9 | R44: 0 | S44: 0 | T44: 0 | U44: 0.05 | V44: 0.05 | W44: =SUM(Q44:V44) -> 1 | X44: =IF(E44<>"Combat","—",IFERROR(INDEX(Affinity!$A$2:$A$7,MATCH(MAX(INDEX(Affinity!$B$2:$CU$7,0,MATCH(A44,Affinity!$B$1:$CU$1,0))),INDEX(Affinity!$B$2:$CU$7,0,MATCH(A44,Affinity!$B$1:$CU$1,0)),0)),"—")) -> Earnest | Y44: 1 | Z44: 30000 | AA44: 1 | AB44: 60 | AC44: 1 | AD44: 0 | AE44: 0 | AF44: -2 | AG44: 5 | AH44: -2 | AI44: Single | AJ44: per_turn | AL44: single | AM44: 1 | AN44: press_conference | AO44: Yes | AQ44: No | AR44: Yes | AX44: ST04 | AY44: 2 | BA44: 2
A45: ST44 | B45: TV Debate on Broadcaster Independence | C45: 公共放送の独立テレビ討論 | D45: Kōkyō Hōsō no Dokuritsu Terebi Tōron | E45: Combat | F45: Viewer Interest | G45: Numerical | H45: 100 | I45: 65 | J45: =IF(AND(ISNUMBER(H45),ISNUMBER(I45)),IF(H45=0,"",I45/H45),"varies") -> 0.65 | K45: 5 | L45: 5 | M45: 6 | N45: 5 | O45: 60 | P45: 50 | Q45: 0.8 | R45: 0 | S45: 0.2 | T45: 0 | U45: 0 | V45: 0 | W45: =SUM(Q45:V45) -> 1 | X45: =IF(E45<>"Combat","—",IFERROR(INDEX(Affinity!$A$2:$A$7,MATCH(MAX(INDEX(Affinity!$B$2:$CU$7,0,MATCH(A45,Affinity!$B$1:$CU$1,0))),INDEX(Affinity!$B$2:$CU$7,0,MATCH(A45,Affinity!$B$1:$CU$1,0)),0)),"—")) -> Earnest | Y45: 3 | Z45: 40000 | AA45: 2 | AB45: 55 | AC45: 2 | AD45: -1 | AE45: 0 | AF45: -3 | AG45: 0 | AH45: -1 | AI45: Survival | AJ45: per_turn | AL45: single | AM45: 1 | AO45: Yes | AR45: Yes | AU45: 0 | AV45: 3 | AX45: ST06 | AY45: 3 | BA45: 3
A46: ST45 | B46: Party Caucus on Broadcaster Independence | C46: 公共放送の独立党内会合 | D46: Kōkyō Hōsō no Dokuritsu Tōnai Kaigō | E46: Combat | F46: Support | G46: Percentage | H46: 100 | I46: 49 | J46: =IF(AND(ISNUMBER(H46),ISNUMBER(I46)),IF(H46=0,"",I46/H46),"varies") -> 0.49 | K46: 10 | L46: 3 | M46: 5 | N46: 5 | O46: 20 | P46: 40 | Q46: 0 | R46: 0.55 | S46: 0 | T46: 0 | U46: 0 | V46: 0.45 | W46: =SUM(Q46:V46) -> 1 | X46: =IF(E46<>"Combat","—",IFERROR(INDEX(Affinity!$A$2:$A$7,MATCH(MAX(INDEX(Affinity!$B$2:$CU$7,0,MATCH(A46,Affinity!$B$1:$CU$1,0))),INDEX(Affinity!$B$2:$CU$7,0,MATCH(A46,Affinity!$B$1:$CU$1,0)),0)),"—")) -> Data Driven | Y46: 0 | Z46: 20000 | AA46: 1 | AB46: 90 | AC46: 2 | AD46: 0 | AE46: 0 | AF46: -1 | AG46: 1 | AH46: -2 | AI46: Shared_pool | AJ46: per_turn | AL46: continuous | AM46: 2 | AO46: No | AR46: Yes | AT46: Yes | AX46: ST03 | AY46: 4
A47: ST46 | B47: Press Conference on Donation Transparency | C47: 政治献金の透明化記者会見 | D47: Seiji Kenkin no Tōmeika Kisha Kaiken | E47: Combat | F47: Press tone | G47: Numerical | H47: 100 | I47: 57 | J47: =IF(AND(ISNUMBER(H47),ISNUMBER(I47)),IF(H47=0,"",I47/H47),"varies") -> 0.57 | K47: 6 | L47: 3 | M47: 5 | N47: 4 | O47: 20 | P47: 45 | Q47: 0.9 | R47: 0 | S47: 0 | T47: 0 | U47: 0.05 | V47: 0.05 | W47: =SUM(Q47:V47) -> 1 | X47: =IF(E47<>"Combat","—",IFERROR(INDEX(Affinity!$A$2:$A$7,MATCH(MAX(INDEX(Affinity!$B$2:$CU$7,0,MATCH(A47,Affinity!$B$1:$CU$1,0))),INDEX(Affinity!$B$2:$CU$7,0,MATCH(A47,Affinity!$B$1:$CU$1,0)),0)),"—")) -> Data Driven | Y47: 1 | Z47: 30000 | AA47: 1 | AB47: 60 | AC47: 1 | AD47: 0 | AE47: 0 | AF47: -2 | AG47: 5 | AH47: -2 | AI47: Single | AJ47: per_turn | AL47: single | AM47: 1 | AN47: press_conference | AO47: Yes | AQ47: No | AR47: Yes | AX47: ST04 | AY47: 2 | BA47: 2
A48: ST47 | B48: Hearing on Donation Transparency | C48: 政治献金の透明化に関する公聴会 | D48: Seiji Kenkin no Tōmeika ni Kansuru Kōchōkai | E48: Combat | F48: Favorability | G48: Percentage | H48: 100 | I48: 81 | J48: =IF(AND(ISNUMBER(H48),ISNUMBER(I48)),IF(H48=0,"",I48/H48),"varies") -> 0.81 | K48: 10 | L48: 5 | M48: 5 | N48: 5 | O48: 30 | P48: 40 | Q48: 0.15 | R48: 0 | S48: 0.1 | T48: 0.1 | U48: 0.65 | V48: 0 | W48: =SUM(Q48:V48) -> 1 | X48: =IF(E48<>"Combat","—",IFERROR(INDEX(Affinity!$A$2:$A$7,MATCH(MAX(INDEX(Affinity!$B$2:$CU$7,0,MATCH(A48,Affinity!$B$1:$CU$1,0))),INDEX(Affinity!$B$2:$CU$7,0,MATCH(A48,Affinity!$B$1:$CU$1,0)),0)),"—")) -> Data Driven | Y48: 1 | Z48: 50000 | AA48: 5 | AB48: 40 | AC48: 5 | AD48: 0 | AE48: 0 | AF48: 0 | AG48: 2 | AH48: 0 | AI48: Shared_pool | AJ48: per_turn | AL48: reset | AM48: 4 | AO48: No | AR48: Yes | AX48: ST17 | AY48: 4 | BA48: 1
A49: ST48 | B49: Lobbyist Meeting on Donation Transparency | C49: 政治献金の透明化に関するロビー活動 | D49: Seiji Kenkin no Tōmeika ni Kansuru Robī Katsudō | E49: Combat | F49: Appeasement | G49: Percentage | H49: 50 | I49: 25 | J49: =IF(AND(ISNUMBER(H49),ISNUMBER(I49)),IF(H49=0,"",I49/H49),"varies") -> 0.5 | K49: 7 | L49: 3 | M49: 5 | N49: 6 | O49: 5 | P49: 15 | Q49: 0 | R49: 0 | S49: 0 | T49: 1 | U49: 0 | V49: 0 | W49: =SUM(Q49:V49) -> 1 | X49: =IF(E49<>"Combat","—",IFERROR(INDEX(Affinity!$A$2:$A$7,MATCH(MAX(INDEX(Affinity!$B$2:$CU$7,0,MATCH(A49,Affinity!$B$1:$CU$1,0))),INDEX(Affinity!$B$2:$CU$7,0,MATCH(A49,Affinity!$B$1:$CU$1,0)),0)),"—")) -> Earnest | Y49: 0 | Z49: 50000 | AA49: 0 | AB49: 75 | AC49: 0 | AD49: 0 | AE49: 0 | AF49: 0 | AG49: 0 | AH49: -1 | AI49: Shared_pool | AJ49: pool | AK49: 12 | AL49: single | AM49: 1 | AN49: lobbyist_meeting | AO49: No | AR49: Yes | AX49: ST20 | AY49: 2
A50: ST49 | B50: Party Caucus on Donation Transparency | C50: 政治献金の透明化党内会合 | D50: Seiji Kenkin no Tōmeika Tōnai Kaigō | E50: Combat | F50: Support | G50: Percentage | H50: 100 | I50: 49 | J50: =IF(AND(ISNUMBER(H50),ISNUMBER(I50)),IF(H50=0,"",I50/H50),"varies") -> 0.49 | K50: 10 | L50: 3 | M50: 5 | N50: 5 | O50: 20 | P50: 40 | Q50: 0 | R50: 0.55 | S50: 0 | T50: 0 | U50: 0 | V50: 0.45 | W50: =SUM(Q50:V50) -> 1 | X50: =IF(E50<>"Combat","—",IFERROR(INDEX(Affinity!$A$2:$A$7,MATCH(MAX(INDEX(Affinity!$B$2:$CU$7,0,MATCH(A50,Affinity!$B$1:$CU$1,0))),INDEX(Affinity!$B$2:$CU$7,0,MATCH(A50,Affinity!$B$1:$CU$1,0)),0)),"—")) -> Data Driven | Y50: 0 | Z50: 20000 | AA50: 1 | AB50: 90 | AC50: 2 | AD50: 0 | AE50: 0 | AF50: -1 | AG50: 1 | AH50: -2 | AI50: Shared_pool | AJ50: per_turn | AL50: continuous | AM50: 2 | AO50: No | AR50: Yes | AT50: Yes | AX50: ST03 | AY50: 4
A51: ST50 | B51: Policy Study on Corporate Tax Cuts | C51: 法人税の引き下げ政策検討会 | D51: Hōjinzei no Hikisage Seisaku Kentōkai | E51: Combat | F51: Consensus | G51: Percentage | H51: 50 | I51: 44 | J51: =IF(AND(ISNUMBER(H51),ISNUMBER(I51)),IF(H51=0,"",I51/H51),"varies") -> 0.88 | K51: 10 | L51: 5 | M51: 5 | N51: 10 | O51: 1 | P51: 10 | Q51: 0 | R51: 0 | S51: 0 | T51: 0 | U51: 0.8 | V51: 0.2 | W51: =SUM(Q51:V51) -> 1 | X51: =IF(E51<>"Combat","—",IFERROR(INDEX(Affinity!$A$2:$A$7,MATCH(MAX(INDEX(Affinity!$B$2:$CU$7,0,MATCH(A51,Affinity!$B$1:$CU$1,0))),INDEX(Affinity!$B$2:$CU$7,0,MATCH(A51,Affinity!$B$1:$CU$1,0)),0)),"—")) -> Data Driven | Y51: 1 | Z51: 15000 | AA51: 1 | AB51: 55 | AC51: 1 | AD51: 0 | AE51: 0 | AF51: 0 | AG51: 5 | AH51: 0 | AI51: Shared_pool | AJ51: per_turn | AL51: stream | AM51: 2 | AN51: policy_study | AO51: No | AQ51: No | AR51: Yes | AX51: ST21 | AY51: 2
A52: ST51 | B52: Hearing on Corporate Tax Cuts | C52: 法人税の引き下げに関する公聴会 | D52: Hōjinzei no Hikisage ni Kansuru Kōchōkai | E52: Combat | F52: Favorability | G52: Percentage | H52: 100 | I52: 87 | J52: =IF(AND(ISNUMBER(H52),ISNUMBER(I52)),IF(H52=0,"",I52/H52),"varies") -> 0.87 | K52: 10 | L52: 4 | M52: 5 | N52: 3 | O52: 35 | P52: 40 | Q52: 0.25 | R52: 0 | S52: 0 | T52: 0.35 | U52: 0.4 | V52: 0 | W52: =SUM(Q52:V52) -> 1 | X52: =IF(E52<>"Combat","—",IFERROR(INDEX(Affinity!$A$2:$A$7,MATCH(MAX(INDEX(Affinity!$B$2:$CU$7,0,MATCH(A52,Affinity!$B$1:$CU$1,0))),INDEX(Affinity!$B$2:$CU$7,0,MATCH(A52,Affinity!$B$1:$CU$1,0)),0)),"—")) -> Data Driven | Y52: 1 | Z52: 50000 | AA52: 5 | AB52: 75 | AC52: 5 | AD52: 0 | AE52: 0 | AF52: 0 | AG52: 2 | AH52: 0 | AI52: Shared_pool | AJ52: per_turn | AL52: reset | AM52: 3 | AO52: No | AR52: Yes | AX52: ST16 | AY52: 4 | BA52: 1
A53: ST52 | B53: Party Caucus on Corporate Tax Cuts | C53: 法人税の引き下げ党内会合 | D53: Hōjinzei no Hikisage Tōnai Kaigō | E53: Combat | F53: Support | G53: Percentage | H53: 100 | I53: 49 | J53: =IF(AND(ISNUMBER(H53),ISNUMBER(I53)),IF(H53=0,"",I53/H53),"varies") -> 0.49 | K53: 10 | L53: 3 | M53: 5 | N53: 5 | O53: 20 | P53: 40 | Q53: 0 | R53: 0.55 | S53: 0 | T53: 0 | U53: 0 | V53: 0.45 | W53: =SUM(Q53:V53) -> 1 | X53: =IF(E53<>"Combat","—",IFERROR(INDEX(Affinity!$A$2:$A$7,MATCH(MAX(INDEX(Affinity!$B$2:$CU$7,0,MATCH(A53,Affinity!$B$1:$CU$1,0))),INDEX(Affinity!$B$2:$CU$7,0,MATCH(A53,Affinity!$B$1:$CU$1,0)),0)),"—")) -> Appeal | Y53: 0 | Z53: 20000 | AA53: 1 | AB53: 90 | AC53: 2 | AD53: 0 | AE53: 0 | AF53: -1 | AG53: 1 | AH53: -2 | AI53: Shared_pool | AJ53: per_turn | AL53: continuous | AM53: 2 | AO53: No | AR53: Yes | AT53: Yes | AX53: ST03 | AY53: 4
A54: ST53 | B54: Town Hall on the Carbon Levy | C54: 炭素課徴金を巡る住民集会 | D54: Tanso Kachōkin o Meguru Jūmin Shūkai | E54: Combat | F54: Appeasement | G54: Percentage | H54: 100 | I54: 53 | J54: =IF(AND(ISNUMBER(H54),ISNUMBER(I54)),IF(H54=0,"",I54/H54),"varies") -> 0.53 | K54: 17 | L54: 3 | M54: 5 | N54: 6 | O54: 15 | P54: 20 | Q54: 0.1 | R54: 0.1 | S54: 0.7 | T54: 0.1 | U54: 0 | V54: 0 | W54: =SUM(Q54:V54) -> 1 | X54: =IF(E54<>"Combat","—",IFERROR(INDEX(Affinity!$A$2:$A$7,MATCH(MAX(INDEX(Affinity!$B$2:$CU$7,0,MATCH(A54,Affinity!$B$1:$CU$1,0))),INDEX(Affinity!$B$2:$CU$7,0,MATCH(A54,Affinity!$B$1:$CU$1,0)),0)),"—")) -> Data Driven | Y54: 5 | Z54: 45000 | AA54: 1 | AB54: 70 | AC54: 0 | AD54: -5 | AE54: 0 | AF54: -3 | AG54: 10 | AH54: 0 | AI54: Shared_pool | AJ54: per_turn | AL54: stream | AM54: 3 | AN54: town_hall | AO54: No | AR54: Yes | AX54: ST05 | AY54: 2 | AZ54: 2
A55: ST54 | B55: Hearing on the Carbon Levy | C55: 炭素課徴金に関する公聴会 | D55: Tanso Kachōkin ni Kansuru Kōchōkai | E55: Combat | F55: Favorability | G55: Percentage | H55: 100 | I55: 69 | J55: =IF(AND(ISNUMBER(H55),ISNUMBER(I55)),IF(H55=0,"",I55/H55),"varies") -> 0.69 | K55: 10 | L55: 5 | M55: 5 | N55: 7 | O55: 30 | P55: 30 | Q55: 0 | R55: 0.1 | S55: 0.65 | T55: 0 | U55: 0.2 | V55: 0.05 | W55: =SUM(Q55:V55) -> 1 | X55: =IF(E55<>"Combat","—",IFERROR(INDEX(Affinity!$A$2:$A$7,MATCH(MAX(INDEX(Affinity!$B$2:$CU$7,0,MATCH(A55,Affinity!$B$1:$CU$1,0))),INDEX(Affinity!$B$2:$CU$7,0,MATCH(A55,Affinity!$B$1:$CU$1,0)),0)),"—")) -> Data Driven | Y55: 2 | Z55: 10000 | AA55: 1 | AB55: 40 | AC55: 0 | AD55: -1 | AE55: 1000 | AF55: 0 | AG55: 1 | AH55: 0 | AI55: Shared_pool | AJ55: per_turn | AL55: reset | AM55: 2 | AO55: No | AR55: Yes | AX55: ST10 | AY55: 4 | BA55: 1
A56: ST55 | B56: Press Conference on the Carbon Levy | C56: 炭素課徴金記者会見 | D56: Tanso Kachōkin Kisha Kaiken | E56: Combat | F56: Press tone | G56: Numerical | H56: 100 | I56: 57 | J56: =IF(AND(ISNUMBER(H56),ISNUMBER(I56)),IF(H56=0,"",I56/H56),"varies") -> 0.57 | K56: 6 | L56: 3 | M56: 5 | N56: 4 | O56: 20 | P56: 45 | Q56: 0.9 | R56: 0 | S56: 0 | T56: 0 | U56: 0.05 | V56: 0.05 | W56: =SUM(Q56:V56) -> 1 | X56: =IF(E56<>"Combat","—",IFERROR(INDEX(Affinity!$A$2:$A$7,MATCH(MAX(INDEX(Affinity!$B$2:$CU$7,0,MATCH(A56,Affinity!$B$1:$CU$1,0))),INDEX(Affinity!$B$2:$CU$7,0,MATCH(A56,Affinity!$B$1:$CU$1,0)),0)),"—")) -> Earnest | Y56: 1 | Z56: 30000 | AA56: 1 | AB56: 60 | AC56: 1 | AD56: 0 | AE56: 0 | AF56: -2 | AG56: 5 | AH56: -2 | AI56: Single | AJ56: per_turn | AL56: single | AM56: 1 | AN56: press_conference | AO56: Yes | AQ56: No | AR56: Yes | AX56: ST04 | AY56: 2 | BA56: 2
A57: ST56 | B57: Party Caucus on the Carbon Levy | C57: 炭素課徴金党内会合 | D57: Tanso Kachōkin Tōnai Kaigō | E57: Combat | F57: Support | G57: Percentage | H57: 100 | I57: 49 | J57: =IF(AND(ISNUMBER(H57),ISNUMBER(I57)),IF(H57=0,"",I57/H57),"varies") -> 0.49 | K57: 10 | L57: 3 | M57: 5 | N57: 5 | O57: 20 | P57: 40 | Q57: 0 | R57: 0.55 | S57: 0 | T57: 0 | U57: 0 | V57: 0.45 | W57: =SUM(Q57:V57) -> 1 | X57: =IF(E57<>"Combat","—",IFERROR(INDEX(Affinity!$A$2:$A$7,MATCH(MAX(INDEX(Affinity!$B$2:$CU$7,0,MATCH(A57,Affinity!$B$1:$CU$1,0))),INDEX(Affinity!$B$2:$CU$7,0,MATCH(A57,Affinity!$B$1:$CU$1,0)),0)),"—")) -> Data Driven | Y57: 0 | Z57: 20000 | AA57: 1 | AB57: 90 | AC57: 2 | AD57: 0 | AE57: 0 | AF57: -1 | AG57: 1 | AH57: -2 | AI57: Shared_pool | AJ57: per_turn | AL57: continuous | AM57: 2 | AO57: No | AR57: Yes | AT57: Yes | AX57: ST03 | AY57: 4
A58: ST57 | B58: Hearing on Fishing Quota Reform | C58: 漁獲枠改革に関する公聴会 | D58: Gyokaku-waku Kaikaku ni Kansuru Kōchōkai | E58: Combat | F58: Favorability | G58: Percentage | H58: 100 | I58: 66 | J58: =IF(AND(ISNUMBER(H58),ISNUMBER(I58)),IF(H58=0,"",I58/H58),"varies") -> 0.66 | K58: 10 | L58: 5 | M58: 5 | N58: 7 | O58: 30 | P58: 30 | Q58: 0 | R58: 0.2 | S58: 0.6 | T58: 0 | U58: 0 | V58: 0.2 | W58: =SUM(Q58:V58) -> 1 | X58: =IF(E58<>"Combat","—",IFERROR(INDEX(Affinity!$A$2:$A$7,MATCH(MAX(INDEX(Affinity!$B$2:$CU$7,0,MATCH(A58,Affinity!$B$1:$CU$1,0))),INDEX(Affinity!$B$2:$CU$7,0,MATCH(A58,Affinity!$B$1:$CU$1,0)),0)),"—")) -> Data Driven | Y58: 1 | Z58: 10000 | AA58: 1 | AB58: 40 | AC58: 0 | AD58: -1 | AE58: 1000 | AF58: 0 | AG58: 1 | AH58: 0 | AI58: Shared_pool | AJ58: per_turn | AL58: reset | AM58: 2 | AO58: No | AR58: Yes | AX58: ST13 | AY58: 4 | BA58: 1
A59: ST58 | B59: Town Hall on Fishing Quota Reform | C59: 漁獲枠改革を巡る住民集会 | D59: Gyokaku-waku Kaikaku o Meguru Jūmin Shūkai | E59: Combat | F59: Appeasement | G59: Percentage | H59: 100 | I59: 53 | J59: =IF(AND(ISNUMBER(H59),ISNUMBER(I59)),IF(H59=0,"",I59/H59),"varies") -> 0.53 | K59: 17 | L59: 3 | M59: 5 | N59: 6 | O59: 15 | P59: 20 | Q59: 0.1 | R59: 0.1 | S59: 0.7 | T59: 0.1 | U59: 0 | V59: 0 | W59: =SUM(Q59:V59) -> 1 | X59: =IF(E59<>"Combat","—",IFERROR(INDEX(Affinity!$A$2:$A$7,MATCH(MAX(INDEX(Affinity!$B$2:$CU$7,0,MATCH(A59,Affinity!$B$1:$CU$1,0))),INDEX(Affinity!$B$2:$CU$7,0,MATCH(A59,Affinity!$B$1:$CU$1,0)),0)),"—")) -> Data Driven | Y59: 5 | Z59: 45000 | AA59: 1 | AB59: 70 | AC59: 0 | AD59: -5 | AE59: 0 | AF59: -3 | AG59: 10 | AH59: 0 | AI59: Shared_pool | AJ59: per_turn | AL59: stream | AM59: 3 | AN59: town_hall | AO59: No | AR59: Yes | AX59: ST05 | AY59: 2 | AZ59: 2
A60: ST59 | B60: Party Caucus on Fishing Quota Reform | C60: 漁獲枠改革党内会合 | D60: Gyokaku-waku Kaikaku Tōnai Kaigō | E60: Combat | F60: Support | G60: Percentage | H60: 100 | I60: 49 | J60: =IF(AND(ISNUMBER(H60),ISNUMBER(I60)),IF(H60=0,"",I60/H60),"varies") -> 0.49 | K60: 10 | L60: 3 | M60: 5 | N60: 5 | O60: 20 | P60: 40 | Q60: 0 | R60: 0.55 | S60: 0 | T60: 0 | U60: 0 | V60: 0.45 | W60: =SUM(Q60:V60) -> 1 | X60: =IF(E60<>"Combat","—",IFERROR(INDEX(Affinity!$A$2:$A$7,MATCH(MAX(INDEX(Affinity!$B$2:$CU$7,0,MATCH(A60,Affinity!$B$1:$CU$1,0))),INDEX(Affinity!$B$2:$CU$7,0,MATCH(A60,Affinity!$B$1:$CU$1,0)),0)),"—")) -> Earnest | Y60: 0 | Z60: 20000 | AA60: 1 | AB60: 90 | AC60: 2 | AD60: 0 | AE60: 0 | AF60: -1 | AG60: 1 | AH60: -2 | AI60: Shared_pool | AJ60: per_turn | AL60: continuous | AM60: 2 | AO60: No | AR60: Yes | AT60: Yes | AX60: ST03 | AY60: 4
A61: ST60 | B61: Hearing on Shipbuilding Support | C61: 造船・防衛産業支援に関する公聴会 | D61: Zōsen Bōei Sangyō Shien ni Kansuru Kōchōkai | E61: Combat | F61: Favorability | G61: Percentage | H61: 100 | I61: 74 | J61: =IF(AND(ISNUMBER(H61),ISNUMBER(I61)),IF(H61=0,"",I61/H61),"varies") -> 0.74 | K61: 10 | L61: 3 | M61: 5 | N61: 5 | O61: 25 | P61: 25 | Q61: 0.55 | R61: 0 | S61: 0.05 | T61: 0.25 | U61: 0.15 | V61: 0 | W61: =SUM(Q61:V61) -> 1 | X61: =IF(E61<>"Combat","—",IFERROR(INDEX(Affinity!$A$2:$A$7,MATCH(MAX(INDEX(Affinity!$B$2:$CU$7,0,MATCH(A61,Affinity!$B$1:$CU$1,0))),INDEX(Affinity!$B$2:$CU$7,0,MATCH(A61,Affinity!$B$1:$CU$1,0)),0)),"—")) -> Appeal | Y61: 0 | Z61: 10000 | AA61: 1 | AB61: 20 | AC61: 2 | AD61: 0 | AE61: 0 | AF61: 0 | AG61: 1 | AH61: 0 | AI61: Shared_pool | AJ61: per_turn | AL61: reset | AM61: 2 | AO61: No | AR61: Yes | AX61: ST11 | AY61: 4 | BA61: 1
A62: ST61 | B62: Town Hall on Shipbuilding Support | C62: 造船・防衛産業支援を巡る住民集会 | D62: Zōsen Bōei Sangyō Shien o Meguru Jūmin Shūkai | E62: Combat | F62: Appeasement | G62: Percentage | H62: 100 | I62: 53 | J62: =IF(AND(ISNUMBER(H62),ISNUMBER(I62)),IF(H62=0,"",I62/H62),"varies") -> 0.53 | K62: 17 | L62: 3 | M62: 5 | N62: 6 | O62: 15 | P62: 20 | Q62: 0.1 | R62: 0.1 | S62: 0.7 | T62: 0.1 | U62: 0 | V62: 0 | W62: =SUM(Q62:V62) -> 1 | X62: =IF(E62<>"Combat","—",IFERROR(INDEX(Affinity!$A$2:$A$7,MATCH(MAX(INDEX(Affinity!$B$2:$CU$7,0,MATCH(A62,Affinity!$B$1:$CU$1,0))),INDEX(Affinity!$B$2:$CU$7,0,MATCH(A62,Affinity!$B$1:$CU$1,0)),0)),"—")) -> Appeal | Y62: 5 | Z62: 45000 | AA62: 1 | AB62: 70 | AC62: 0 | AD62: -5 | AE62: 0 | AF62: -3 | AG62: 10 | AH62: 0 | AI62: Shared_pool | AJ62: per_turn | AL62: stream | AM62: 3 | AN62: town_hall | AO62: No | AR62: Yes | AX62: ST05 | AY62: 2 | AZ62: 2
A63: ST62 | B63: Party Caucus on Shipbuilding Support | C63: 造船・防衛産業支援党内会合 | D63: Zōsen Bōei Sangyō Shien Tōnai Kaigō | E63: Combat | F63: Support | G63: Percentage | H63: 100 | I63: 49 | J63: =IF(AND(ISNUMBER(H63),ISNUMBER(I63)),IF(H63=0,"",I63/H63),"varies") -> 0.49 | K63: 10 | L63: 3 | M63: 5 | N63: 5 | O63: 20 | P63: 40 | Q63: 0 | R63: 0.55 | S63: 0 | T63: 0 | U63: 0 | V63: 0.45 | W63: =SUM(Q63:V63) -> 1 | X63: =IF(E63<>"Combat","—",IFERROR(INDEX(Affinity!$A$2:$A$7,MATCH(MAX(INDEX(Affinity!$B$2:$CU$7,0,MATCH(A63,Affinity!$B$1:$CU$1,0))),INDEX(Affinity!$B$2:$CU$7,0,MATCH(A63,Affinity!$B$1:$CU$1,0)),0)),"—")) -> Earnest | Y63: 0 | Z63: 20000 | AA63: 1 | AB63: 90 | AC63: 2 | AD63: 0 | AE63: 0 | AF63: -1 | AG63: 1 | AH63: -2 | AI63: Shared_pool | AJ63: per_turn | AL63: continuous | AM63: 2 | AO63: No | AR63: Yes | AT63: Yes | AX63: ST03 | AY63: 4
A64: ST63 | B64: Hearing on the Constitutional Review | C64: 憲法見直し委員会に関する公聴会 | D64: Kenpō Minaoshi Iinkai ni Kansuru Kōchōkai | E64: Combat | F64: Favorability | G64: Percentage | H64: 100 | I64: 90 | J64: =IF(AND(ISNUMBER(H64),ISNUMBER(I64)),IF(H64=0,"",I64/H64),"varies") -> 0.9 | K64: 10 | L64: 4 | M64: 5 | N64: 7 | O64: 35 | P64: 30 | Q64: 0 | R64: 0.5 | S64: 0 | T64: 0 | U64: 0.5 | V64: 0 | W64: =SUM(Q64:V64) -> 1 | X64: =IF(E64<>"Combat","—",IFERROR(INDEX(Affinity!$A$2:$A$7,MATCH(MAX(INDEX(Affinity!$B$2:$CU$7,0,MATCH(A64,Affinity!$B$1:$CU$1,0))),INDEX(Affinity!$B$2:$CU$7,0,MATCH(A64,Affinity!$B$1:$CU$1,0)),0)),"—")) -> Earnest | Y64: 0 | Z64: 10000 | AA64: 1 | AB64: 15 | AC64: 3 | AD64: 0 | AE64: 0 | AF64: 0 | AG64: 1 | AH64: 0 | AI64: Shared_pool | AJ64: per_turn | AL64: reset | AM64: 3 | AO64: No | AR64: Yes | AX64: ST12 | AY64: 4 | BA64: 1
A65: ST64 | B65: Press Conference on the Constitutional Review | C65: 憲法見直し委員会記者会見 | D65: Kenpō Minaoshi Iinkai Kisha Kaiken | E65: Combat | F65: Press tone | G65: Numerical | H65: 100 | I65: 55 | J65: =IF(AND(ISNUMBER(H65),ISNUMBER(I65)),IF(H65=0,"",I65/H65),"varies") -> 0.55 | K65: 6 | L65: 3 | M65: 5 | N65: 4 | O65: 20 | P65: 45 | Q65: 0.9 | R65: 0 | S65: 0 | T65: 0 | U65: 0.05 | V65: 0.05 | W65: =SUM(Q65:V65) -> 1 | X65: =IF(E65<>"Combat","—",IFERROR(INDEX(Affinity!$A$2:$A$7,MATCH(MAX(INDEX(Affinity!$B$2:$CU$7,0,MATCH(A65,Affinity!$B$1:$CU$1,0))),INDEX(Affinity!$B$2:$CU$7,0,MATCH(A65,Affinity!$B$1:$CU$1,0)),0)),"—")) -> Earnest | Y65: 1 | Z65: 30000 | AA65: 1 | AB65: 60 | AC65: 1 | AD65: 0 | AE65: 0 | AF65: -2 | AG65: 5 | AH65: -2 | AI65: Single | AJ65: per_turn | AL65: single | AM65: 1 | AN65: press_conference | AO65: Yes | AQ65: No | AR65: Yes | AX65: ST04 | AY65: 2 | BA65: 2
A66: ST65 | B66: Party Caucus on the Constitutional Review | C66: 憲法見直し委員会党内会合 | D66: Kenpō Minaoshi Iinkai Tōnai Kaigō | E66: Combat | F66: Support | G66: Percentage | H66: 100 | I66: 49 | J66: =IF(AND(ISNUMBER(H66),ISNUMBER(I66)),IF(H66=0,"",I66/H66),"varies") -> 0.49 | K66: 10 | L66: 3 | M66: 5 | N66: 5 | O66: 20 | P66: 40 | Q66: 0 | R66: 0.55 | S66: 0 | T66: 0 | U66: 0 | V66: 0.45 | W66: =SUM(Q66:V66) -> 1 | X66: =IF(E66<>"Combat","—",IFERROR(INDEX(Affinity!$A$2:$A$7,MATCH(MAX(INDEX(Affinity!$B$2:$CU$7,0,MATCH(A66,Affinity!$B$1:$CU$1,0))),INDEX(Affinity!$B$2:$CU$7,0,MATCH(A66,Affinity!$B$1:$CU$1,0)),0)),"—")) -> Data Driven | Y66: 0 | Z66: 20000 | AA66: 1 | AB66: 90 | AC66: 2 | AD66: 0 | AE66: 0 | AF66: -1 | AG66: 1 | AH66: -2 | AI66: Shared_pool | AJ66: per_turn | AL66: continuous | AM66: 2 | AO66: No | AR66: Yes | AT66: Yes | AX66: ST03 | AY66: 4
A67: ST66 | B67: Hearing on Border Cooperation | C67: 税関・国境協力に関する公聴会 | D67: Zeikan Kokkyō Kyōryoku ni Kansuru Kōchōkai | E67: Combat | F67: Favorability | G67: Percentage | H67: 100 | I67: 78 | J67: =IF(AND(ISNUMBER(H67),ISNUMBER(I67)),IF(H67=0,"",I67/H67),"varies") -> 0.78 | K67: 10 | L67: 4 | M67: 5 | N67: 5 | O67: 25 | P67: 30 | Q67: 0.4 | R67: 0.2 | S67: 0 | T67: 0.2 | U67: 0.2 | V67: 0 | W67: =SUM(Q67:V67) -> 1 | X67: =IF(E67<>"Combat","—",IFERROR(INDEX(Affinity!$A$2:$A$7,MATCH(MAX(INDEX(Affinity!$B$2:$CU$7,0,MATCH(A67,Affinity!$B$1:$CU$1,0))),INDEX(Affinity!$B$2:$CU$7,0,MATCH(A67,Affinity!$B$1:$CU$1,0)),0)),"—")) -> Data Driven | Y67: 0 | Z67: 20000 | AA67: 2 | AB67: 40 | AC67: 2 | AD67: 0 | AE67: 0 | AF67: 0 | AG67: 1 | AH67: 0 | AI67: Shared_pool | AJ67: per_turn | AL67: reset | AM67: 3 | AO67: No | AR67: Yes | AX67: ST14 | AY67: 4 | BA67: 1
A68: ST67 | B68: Lobbyist Meeting on Border Cooperation | C68: 税関・国境協力に関するロビー活動 | D68: Zeikan Kokkyō Kyōryoku ni Kansuru Robī Katsudō | E68: Combat | F68: Appeasement | G68: Percentage | H68: 50 | I68: 25 | J68: =IF(AND(ISNUMBER(H68),ISNUMBER(I68)),IF(H68=0,"",I68/H68),"varies") -> 0.5 | K68: 7 | L68: 3 | M68: 5 | N68: 6 | O68: 5 | P68: 15 | Q68: 0 | R68: 0 | S68: 0 | T68: 1 | U68: 0 | V68: 0 | W68: =SUM(Q68:V68) -> 1 | X68: =IF(E68<>"Combat","—",IFERROR(INDEX(Affinity!$A$2:$A$7,MATCH(MAX(INDEX(Affinity!$B$2:$CU$7,0,MATCH(A68,Affinity!$B$1:$CU$1,0))),INDEX(Affinity!$B$2:$CU$7,0,MATCH(A68,Affinity!$B$1:$CU$1,0)),0)),"—")) -> Data Driven | Y68: 0 | Z68: 50000 | AA68: 0 | AB68: 75 | AC68: 0 | AD68: 0 | AE68: 0 | AF68: 0 | AG68: 0 | AH68: -1 | AI68: Shared_pool | AJ68: pool | AK68: 12 | AL68: single | AM68: 1 | AN68: lobbyist_meeting | AO68: No | AR68: Yes | AX68: ST20 | AY68: 2
A69: ST68 | B69: Party Caucus on Border Cooperation | C69: 税関・国境協力党内会合 | D69: Zeikan Kokkyō Kyōryoku Tōnai Kaigō | E69: Combat | F69: Support | G69: Percentage | H69: 100 | I69: 49 | J69: =IF(AND(ISNUMBER(H69),ISNUMBER(I69)),IF(H69=0,"",I69/H69),"varies") -> 0.49 | K69: 10 | L69: 3 | M69: 5 | N69: 5 | O69: 20 | P69: 40 | Q69: 0 | R69: 0.55 | S69: 0 | T69: 0 | U69: 0 | V69: 0.45 | W69: =SUM(Q69:V69) -> 1 | X69: =IF(E69<>"Combat","—",IFERROR(INDEX(Affinity!$A$2:$A$7,MATCH(MAX(INDEX(Affinity!$B$2:$CU$7,0,MATCH(A69,Affinity!$B$1:$CU$1,0))),INDEX(Affinity!$B$2:$CU$7,0,MATCH(A69,Affinity!$B$1:$CU$1,0)),0)),"—")) -> Appeal | Y69: 0 | Z69: 20000 | AA69: 1 | AB69: 90 | AC69: 2 | AD69: 0 | AE69: 0 | AF69: -1 | AG69: 1 | AH69: -2 | AI69: Shared_pool | AJ69: per_turn | AL69: continuous | AM69: 2 | AO69: No | AR69: Yes | AT69: Yes | AX69: ST03 | AY69: 4
A70: ST69 | B70: Hearing on Chishima Development | C70: 千島資源開発に関する公聴会 | D70: Chishima Shigen Kaihatsu ni Kansuru Kōchōkai | E70: Combat | F70: Favorability | G70: Percentage | H70: 100 | I70: 78 | J70: =IF(AND(ISNUMBER(H70),ISNUMBER(I70)),IF(H70=0,"",I70/H70),"varies") -> 0.78 | K70: 10 | L70: 4 | M70: 5 | N70: 5 | O70: 25 | P70: 30 | Q70: 0.4 | R70: 0.2 | S70: 0 | T70: 0.2 | U70: 0.2 | V70: 0 | W70: =SUM(Q70:V70) -> 1 | X70: =IF(E70<>"Combat","—",IFERROR(INDEX(Affinity!$A$2:$A$7,MATCH(MAX(INDEX(Affinity!$B$2:$CU$7,0,MATCH(A70,Affinity!$B$1:$CU$1,0))),INDEX(Affinity!$B$2:$CU$7,0,MATCH(A70,Affinity!$B$1:$CU$1,0)),0)),"—")) -> Appeal | Y70: 0 | Z70: 20000 | AA70: 2 | AB70: 40 | AC70: 2 | AD70: 0 | AE70: 0 | AF70: 0 | AG70: 1 | AH70: 0 | AI70: Shared_pool | AJ70: per_turn | AL70: reset | AM70: 3 | AO70: No | AR70: Yes | AX70: ST14 | AY70: 4 | BA70: 1
A71: ST70 | B71: Press Conference on Chishima Development | C71: 千島資源開発記者会見 | D71: Chishima Shigen Kaihatsu Kisha Kaiken | E71: Combat | F71: Press tone | G71: Numerical | H71: 100 | I71: 55 | J71: =IF(AND(ISNUMBER(H71),ISNUMBER(I71)),IF(H71=0,"",I71/H71),"varies") -> 0.55 | K71: 6 | L71: 3 | M71: 5 | N71: 4 | O71: 20 | P71: 45 | Q71: 0.9 | R71: 0 | S71: 0 | T71: 0 | U71: 0.05 | V71: 0.05 | W71: =SUM(Q71:V71) -> 1 | X71: =IF(E71<>"Combat","—",IFERROR(INDEX(Affinity!$A$2:$A$7,MATCH(MAX(INDEX(Affinity!$B$2:$CU$7,0,MATCH(A71,Affinity!$B$1:$CU$1,0))),INDEX(Affinity!$B$2:$CU$7,0,MATCH(A71,Affinity!$B$1:$CU$1,0)),0)),"—")) -> Appeal | Y71: 1 | Z71: 30000 | AA71: 1 | AB71: 60 | AC71: 1 | AD71: 0 | AE71: 0 | AF71: -2 | AG71: 5 | AH71: -2 | AI71: Single | AJ71: per_turn | AL71: single | AM71: 1 | AN71: press_conference | AO71: Yes | AQ71: No | AR71: Yes | AX71: ST04 | AY71: 2 | BA71: 2
A72: ST71 | B72: Lobbyist Meeting on Chishima Development | C72: 千島資源開発に関するロビー活動 | D72: Chishima Shigen Kaihatsu ni Kansuru Robī Katsudō | E72: Combat | F72: Appeasement | G72: Percentage | H72: 50 | I72: 25 | J72: =IF(AND(ISNUMBER(H72),ISNUMBER(I72)),IF(H72=0,"",I72/H72),"varies") -> 0.5 | K72: 7 | L72: 3 | M72: 5 | N72: 6 | O72: 5 | P72: 15 | Q72: 0 | R72: 0 | S72: 0 | T72: 1 | U72: 0 | V72: 0 | W72: =SUM(Q72:V72) -> 1 | X72: =IF(E72<>"Combat","—",IFERROR(INDEX(Affinity!$A$2:$A$7,MATCH(MAX(INDEX(Affinity!$B$2:$CU$7,0,MATCH(A72,Affinity!$B$1:$CU$1,0))),INDEX(Affinity!$B$2:$CU$7,0,MATCH(A72,Affinity!$B$1:$CU$1,0)),0)),"—")) -> Data Driven | Y72: 0 | Z72: 50000 | AA72: 0 | AB72: 75 | AC72: 0 | AD72: 0 | AE72: 0 | AF72: 0 | AG72: 0 | AH72: -1 | AI72: Shared_pool | AJ72: pool | AK72: 12 | AL72: single | AM72: 1 | AN72: lobbyist_meeting | AO72: No | AR72: Yes | AX72: ST20 | AY72: 2
A73: ST72 | B73: Party Caucus on Chishima Development | C73: 千島資源開発党内会合 | D73: Chishima Shigen Kaihatsu Tōnai Kaigō | E73: Combat | F73: Support | G73: Percentage | H73: 100 | I73: 49 | J73: =IF(AND(ISNUMBER(H73),ISNUMBER(I73)),IF(H73=0,"",I73/H73),"varies") -> 0.49 | K73: 10 | L73: 3 | M73: 5 | N73: 5 | O73: 20 | P73: 40 | Q73: 0 | R73: 0.55 | S73: 0 | T73: 0 | U73: 0 | V73: 0.45 | W73: =SUM(Q73:V73) -> 1 | X73: =IF(E73<>"Combat","—",IFERROR(INDEX(Affinity!$A$2:$A$7,MATCH(MAX(INDEX(Affinity!$B$2:$CU$7,0,MATCH(A73,Affinity!$B$1:$CU$1,0))),INDEX(Affinity!$B$2:$CU$7,0,MATCH(A73,Affinity!$B$1:$CU$1,0)),0)),"—")) -> Appeal | Y73: 0 | Z73: 20000 | AA73: 1 | AB73: 90 | AC73: 2 | AD73: 0 | AE73: 0 | AF73: -1 | AG73: 1 | AH73: -2 | AI73: Shared_pool | AJ73: per_turn | AL73: continuous | AM73: 2 | AO73: No | AR73: Yes | AT73: Yes | AX73: ST03 | AY73: 4
A74: ST73 | B74: TV Debate on China Trade | C74: 対中貿易正常化テレビ討論 | D74: Taichū Bōeki Seijōka Terebi Tōron | E74: Combat | F74: Viewer Interest | G74: Numerical | H74: 100 | I74: 65 | J74: =IF(AND(ISNUMBER(H74),ISNUMBER(I74)),IF(H74=0,"",I74/H74),"varies") -> 0.65 | K74: 5 | L74: 5 | M74: 6 | N74: 5 | O74: 60 | P74: 50 | Q74: 0.8 | R74: 0 | S74: 0.2 | T74: 0 | U74: 0 | V74: 0 | W74: =SUM(Q74:V74) -> 1 | X74: =IF(E74<>"Combat","—",IFERROR(INDEX(Affinity!$A$2:$A$7,MATCH(MAX(INDEX(Affinity!$B$2:$CU$7,0,MATCH(A74,Affinity!$B$1:$CU$1,0))),INDEX(Affinity!$B$2:$CU$7,0,MATCH(A74,Affinity!$B$1:$CU$1,0)),0)),"—")) -> Data Driven | Y74: 3 | Z74: 40000 | AA74: 2 | AB74: 55 | AC74: 2 | AD74: -1 | AE74: 0 | AF74: -3 | AG74: 0 | AH74: -1 | AI74: Survival | AJ74: per_turn | AL74: single | AM74: 1 | AO74: Yes | AR74: Yes | AU74: 0 | AV74: 3 | AX74: ST06 | AY74: 3 | BA74: 3
A75: ST74 | B75: Hearing on China Trade | C75: 対中貿易正常化に関する公聴会 | D75: Taichū Bōeki Seijōka ni Kansuru Kōchōkai | E75: Combat | F75: Favorability | G75: Percentage | H75: 100 | I75: 81 | J75: =IF(AND(ISNUMBER(H75),ISNUMBER(I75)),IF(H75=0,"",I75/H75),"varies") -> 0.81 | K75: 10 | L75: 4 | M75: 5 | N75: 5 | O75: 25 | P75: 30 | Q75: 0.4 | R75: 0.2 | S75: 0 | T75: 0.2 | U75: 0.2 | V75: 0 | W75: =SUM(Q75:V75) -> 1 | X75: =IF(E75<>"Combat","—",IFERROR(INDEX(Affinity!$A$2:$A$7,MATCH(MAX(INDEX(Affinity!$B$2:$CU$7,0,MATCH(A75,Affinity!$B$1:$CU$1,0))),INDEX(Affinity!$B$2:$CU$7,0,MATCH(A75,Affinity!$B$1:$CU$1,0)),0)),"—")) -> Data Driven | Y75: 0 | Z75: 20000 | AA75: 2 | AB75: 40 | AC75: 2 | AD75: 0 | AE75: 0 | AF75: 0 | AG75: 1 | AH75: 0 | AI75: Shared_pool | AJ75: per_turn | AL75: reset | AM75: 3 | AO75: No | AR75: Yes | AX75: ST14 | AY75: 4 | BA75: 1
A76: ST75 | B76: Party Caucus on China Trade | C76: 対中貿易正常化党内会合 | D76: Taichū Bōeki Seijōka Tōnai Kaigō | E76: Combat | F76: Support | G76: Percentage | H76: 100 | I76: 49 | J76: =IF(AND(ISNUMBER(H76),ISNUMBER(I76)),IF(H76=0,"",I76/H76),"varies") -> 0.49 | K76: 10 | L76: 3 | M76: 5 | N76: 5 | O76: 20 | P76: 40 | Q76: 0 | R76: 0.55 | S76: 0 | T76: 0 | U76: 0 | V76: 0.45 | W76: =SUM(Q76:V76) -> 1 | X76: =IF(E76<>"Combat","—",IFERROR(INDEX(Affinity!$A$2:$A$7,MATCH(MAX(INDEX(Affinity!$B$2:$CU$7,0,MATCH(A76,Affinity!$B$1:$CU$1,0))),INDEX(Affinity!$B$2:$CU$7,0,MATCH(A76,Affinity!$B$1:$CU$1,0)),0)),"—")) -> Appeal | Y76: 0 | Z76: 20000 | AA76: 1 | AB76: 90 | AC76: 2 | AD76: 0 | AE76: 0 | AF76: -1 | AG76: 1 | AH76: -2 | AI76: Shared_pool | AJ76: per_turn | AL76: continuous | AM76: 2 | AO76: No | AR76: Yes | AT76: Yes | AX76: ST03 | AY76: 4
A77: ST76 | B77: Town Hall on Farm Succession | C77: 農地継承支援を巡る住民集会 | D77: Nōchi Keishō Shien o Meguru Jūmin Shūkai | E77: Combat | F77: Appeasement | G77: Percentage | H77: 100 | I77: 53 | J77: =IF(AND(ISNUMBER(H77),ISNUMBER(I77)),IF(H77=0,"",I77/H77),"varies") -> 0.53 | K77: 17 | L77: 3 | M77: 5 | N77: 6 | O77: 15 | P77: 20 | Q77: 0.1 | R77: 0.1 | S77: 0.7 | T77: 0.1 | U77: 0 | V77: 0 | W77: =SUM(Q77:V77) -> 1 | X77: =IF(E77<>"Combat","—",IFERROR(INDEX(Affinity!$A$2:$A$7,MATCH(MAX(INDEX(Affinity!$B$2:$CU$7,0,MATCH(A77,Affinity!$B$1:$CU$1,0))),INDEX(Affinity!$B$2:$CU$7,0,MATCH(A77,Affinity!$B$1:$CU$1,0)),0)),"—")) -> Emotional | Y77: 5 | Z77: 45000 | AA77: 1 | AB77: 70 | AC77: 0 | AD77: -5 | AE77: 0 | AF77: -3 | AG77: 10 | AH77: 0 | AI77: Shared_pool | AJ77: per_turn | AL77: stream | AM77: 3 | AN77: town_hall | AO77: No | AR77: Yes | AX77: ST05 | AY77: 2 | AZ77: 2
A78: ST77 | B78: Hearing on Farm Succession | C78: 農地継承支援に関する公聴会 | D78: Nōchi Keishō Shien ni Kansuru Kōchōkai | E78: Combat | F78: Favorability | G78: Percentage | H78: 100 | I78: 66 | J78: =IF(AND(ISNUMBER(H78),ISNUMBER(I78)),IF(H78=0,"",I78/H78),"varies") -> 0.66 | K78: 10 | L78: 5 | M78: 5 | N78: 7 | O78: 30 | P78: 30 | Q78: 0 | R78: 0.2 | S78: 0.6 | T78: 0 | U78: 0 | V78: 0.2 | W78: =SUM(Q78:V78) -> 1 | X78: =IF(E78<>"Combat","—",IFERROR(INDEX(Affinity!$A$2:$A$7,MATCH(MAX(INDEX(Affinity!$B$2:$CU$7,0,MATCH(A78,Affinity!$B$1:$CU$1,0))),INDEX(Affinity!$B$2:$CU$7,0,MATCH(A78,Affinity!$B$1:$CU$1,0)),0)),"—")) -> Emotional | Y78: 1 | Z78: 10000 | AA78: 1 | AB78: 40 | AC78: 0 | AD78: -1 | AE78: 1000 | AF78: 0 | AG78: 1 | AH78: 0 | AI78: Shared_pool | AJ78: per_turn | AL78: reset | AM78: 2 | AO78: No | AR78: Yes | AX78: ST13 | AY78: 4 | BA78: 1
A79: ST78 | B79: Party Caucus on Farm Succession | C79: 農地継承支援党内会合 | D79: Nōchi Keishō Shien Tōnai Kaigō | E79: Combat | F79: Support | G79: Percentage | H79: 100 | I79: 49 | J79: =IF(AND(ISNUMBER(H79),ISNUMBER(I79)),IF(H79=0,"",I79/H79),"varies") -> 0.49 | K79: 10 | L79: 3 | M79: 5 | N79: 5 | O79: 20 | P79: 40 | Q79: 0 | R79: 0.55 | S79: 0 | T79: 0 | U79: 0 | V79: 0.45 | W79: =SUM(Q79:V79) -> 1 | X79: =IF(E79<>"Combat","—",IFERROR(INDEX(Affinity!$A$2:$A$7,MATCH(MAX(INDEX(Affinity!$B$2:$CU$7,0,MATCH(A79,Affinity!$B$1:$CU$1,0))),INDEX(Affinity!$B$2:$CU$7,0,MATCH(A79,Affinity!$B$1:$CU$1,0)),0)),"—")) -> Earnest | Y79: 0 | Z79: 20000 | AA79: 1 | AB79: 90 | AC79: 2 | AD79: 0 | AE79: 0 | AF79: -1 | AG79: 1 | AH79: -2 | AI79: Shared_pool | AJ79: per_turn | AL79: continuous | AM79: 2 | AO79: No | AR79: Yes | AT79: Yes | AX79: ST03 | AY79: 4
A80: ST79 | B80: Policy Study on University Research Funding | C80: 大学の自治と研究費政策検討会 | D80: Daigaku no Jichi to Kenkyūhi Seisaku Kentōkai | E80: Combat | F80: Consensus | G80: Percentage | H80: 50 | I80: 43 | J80: =IF(AND(ISNUMBER(H80),ISNUMBER(I80)),IF(H80=0,"",I80/H80),"varies") -> 0.86 | K80: 10 | L80: 5 | M80: 5 | N80: 10 | O80: 1 | P80: 10 | Q80: 0 | R80: 0 | S80: 0 | T80: 0 | U80: 0.8 | V80: 0.2 | W80: =SUM(Q80:V80) -> 1 | X80: =IF(E80<>"Combat","—",IFERROR(INDEX(Affinity!$A$2:$A$7,MATCH(MAX(INDEX(Affinity!$B$2:$CU$7,0,MATCH(A80,Affinity!$B$1:$CU$1,0))),INDEX(Affinity!$B$2:$CU$7,0,MATCH(A80,Affinity!$B$1:$CU$1,0)),0)),"—")) -> Data Driven | Y80: 1 | Z80: 15000 | AA80: 1 | AB80: 55 | AC80: 1 | AD80: 0 | AE80: 0 | AF80: 0 | AG80: 5 | AH80: 0 | AI80: Shared_pool | AJ80: per_turn | AL80: stream | AM80: 2 | AN80: policy_study | AO80: No | AQ80: No | AR80: Yes | AX80: ST21 | AY80: 2
A81: ST80 | B81: Hearing on University Research Funding | C81: 大学の自治と研究費に関する公聴会 | D81: Daigaku no Jichi to Kenkyūhi ni Kansuru Kōchōkai | E81: Combat | F81: Favorability | G81: Percentage | H81: 100 | I81: 78 | J81: =IF(AND(ISNUMBER(H81),ISNUMBER(I81)),IF(H81=0,"",I81/H81),"varies") -> 0.78 | K81: 10 | L81: 5 | M81: 5 | N81: 5 | O81: 30 | P81: 40 | Q81: 0.15 | R81: 0 | S81: 0.1 | T81: 0.1 | U81: 0.65 | V81: 0 | W81: =SUM(Q81:V81) -> 1 | X81: =IF(E81<>"Combat","—",IFERROR(INDEX(Affinity!$A$2:$A$7,MATCH(MAX(INDEX(Affinity!$B$2:$CU$7,0,MATCH(A81,Affinity!$B$1:$CU$1,0))),INDEX(Affinity!$B$2:$CU$7,0,MATCH(A81,Affinity!$B$1:$CU$1,0)),0)),"—")) -> Data Driven | Y81: 1 | Z81: 50000 | AA81: 5 | AB81: 40 | AC81: 5 | AD81: 0 | AE81: 0 | AF81: 0 | AG81: 2 | AH81: 0 | AI81: Shared_pool | AJ81: per_turn | AL81: reset | AM81: 4 | AO81: No | AR81: Yes | AX81: ST17 | AY81: 4 | BA81: 1
A82: ST81 | B82: Party Caucus on University Research Funding | C82: 大学の自治と研究費党内会合 | D82: Daigaku no Jichi to Kenkyūhi Tōnai Kaigō | E82: Combat | F82: Support | G82: Percentage | H82: 100 | I82: 49 | J82: =IF(AND(ISNUMBER(H82),ISNUMBER(I82)),IF(H82=0,"",I82/H82),"varies") -> 0.49 | K82: 10 | L82: 3 | M82: 5 | N82: 5 | O82: 20 | P82: 40 | Q82: 0 | R82: 0.55 | S82: 0 | T82: 0 | U82: 0 | V82: 0.45 | W82: =SUM(Q82:V82) -> 1 | X82: =IF(E82<>"Combat","—",IFERROR(INDEX(Affinity!$A$2:$A$7,MATCH(MAX(INDEX(Affinity!$B$2:$CU$7,0,MATCH(A82,Affinity!$B$1:$CU$1,0))),INDEX(Affinity!$B$2:$CU$7,0,MATCH(A82,Affinity!$B$1:$CU$1,0)),0)),"—")) -> Earnest | Y82: 0 | Z82: 20000 | AA82: 1 | AB82: 90 | AC82: 2 | AD82: 0 | AE82: 0 | AF82: -1 | AG82: 1 | AH82: -2 | AI82: Shared_pool | AJ82: per_turn | AL82: continuous | AM82: 2 | AO82: No | AR82: Yes | AT82: Yes | AX82: ST03 | AY82: 4
A83: ST82 | B83: Town Hall on Workplace Equality | C83: 職場の平等を巡る住民集会 | D83: Shokuba no Byōdō o Meguru Jūmin Shūkai | E83: Combat | F83: Appeasement | G83: Percentage | H83: 100 | I83: 53 | J83: =IF(AND(ISNUMBER(H83),ISNUMBER(I83)),IF(H83=0,"",I83/H83),"varies") -> 0.53 | K83: 17 | L83: 3 | M83: 5 | N83: 6 | O83: 15 | P83: 20 | Q83: 0.1 | R83: 0.1 | S83: 0.7 | T83: 0.1 | U83: 0 | V83: 0 | W83: =SUM(Q83:V83) -> 1 | X83: =IF(E83<>"Combat","—",IFERROR(INDEX(Affinity!$A$2:$A$7,MATCH(MAX(INDEX(Affinity!$B$2:$CU$7,0,MATCH(A83,Affinity!$B$1:$CU$1,0))),INDEX(Affinity!$B$2:$CU$7,0,MATCH(A83,Affinity!$B$1:$CU$1,0)),0)),"—")) -> Earnest | Y83: 5 | Z83: 45000 | AA83: 1 | AB83: 70 | AC83: 0 | AD83: -5 | AE83: 0 | AF83: -3 | AG83: 10 | AH83: 0 | AI83: Shared_pool | AJ83: per_turn | AL83: stream | AM83: 3 | AN83: town_hall | AO83: No | AR83: Yes | AX83: ST05 | AY83: 2 | AZ83: 2
A84: ST83 | B84: Press Conference on Workplace Equality | C84: 職場の平等記者会見 | D84: Shokuba no Byōdō Kisha Kaiken | E84: Combat | F84: Press tone | G84: Numerical | H84: 100 | I84: 57 | J84: =IF(AND(ISNUMBER(H84),ISNUMBER(I84)),IF(H84=0,"",I84/H84),"varies") -> 0.57 | K84: 6 | L84: 3 | M84: 5 | N84: 4 | O84: 20 | P84: 45 | Q84: 0.9 | R84: 0 | S84: 0 | T84: 0 | U84: 0.05 | V84: 0.05 | W84: =SUM(Q84:V84) -> 1 | X84: =IF(E84<>"Combat","—",IFERROR(INDEX(Affinity!$A$2:$A$7,MATCH(MAX(INDEX(Affinity!$B$2:$CU$7,0,MATCH(A84,Affinity!$B$1:$CU$1,0))),INDEX(Affinity!$B$2:$CU$7,0,MATCH(A84,Affinity!$B$1:$CU$1,0)),0)),"—")) -> Earnest | Y84: 1 | Z84: 30000 | AA84: 1 | AB84: 60 | AC84: 1 | AD84: 0 | AE84: 0 | AF84: -2 | AG84: 5 | AH84: -2 | AI84: Single | AJ84: per_turn | AL84: single | AM84: 1 | AN84: press_conference | AO84: Yes | AQ84: No | AR84: Yes | AX84: ST04 | AY84: 2 | BA84: 2
A85: ST84 | B85: TV Debate on Workplace Equality | C85: 職場の平等テレビ討論 | D85: Shokuba no Byōdō Terebi Tōron | E85: Combat | F85: Viewer Interest | G85: Numerical | H85: 100 | I85: 65 | J85: =IF(AND(ISNUMBER(H85),ISNUMBER(I85)),IF(H85=0,"",I85/H85),"varies") -> 0.65 | K85: 5 | L85: 5 | M85: 6 | N85: 5 | O85: 60 | P85: 50 | Q85: 0.8 | R85: 0 | S85: 0.2 | T85: 0 | U85: 0 | V85: 0 | W85: =SUM(Q85:V85) -> 1 | X85: =IF(E85<>"Combat","—",IFERROR(INDEX(Affinity!$A$2:$A$7,MATCH(MAX(INDEX(Affinity!$B$2:$CU$7,0,MATCH(A85,Affinity!$B$1:$CU$1,0))),INDEX(Affinity!$B$2:$CU$7,0,MATCH(A85,Affinity!$B$1:$CU$1,0)),0)),"—")) -> Emotional | Y85: 3 | Z85: 40000 | AA85: 2 | AB85: 55 | AC85: 2 | AD85: -1 | AE85: 0 | AF85: -3 | AG85: 0 | AH85: -1 | AI85: Survival | AJ85: per_turn | AL85: single | AM85: 1 | AO85: Yes | AR85: Yes | AU85: 0 | AV85: 3 | AX85: ST06 | AY85: 3 | BA85: 3
A86: ST85 | B86: Party Caucus on Workplace Equality | C86: 職場の平等党内会合 | D86: Shokuba no Byōdō Tōnai Kaigō | E86: Combat | F86: Support | G86: Percentage | H86: 100 | I86: 49 | J86: =IF(AND(ISNUMBER(H86),ISNUMBER(I86)),IF(H86=0,"",I86/H86),"varies") -> 0.49 | K86: 10 | L86: 3 | M86: 5 | N86: 5 | O86: 20 | P86: 40 | Q86: 0 | R86: 0.55 | S86: 0 | T86: 0 | U86: 0 | V86: 0.45 | W86: =SUM(Q86:V86) -> 1 | X86: =IF(E86<>"Combat","—",IFERROR(INDEX(Affinity!$A$2:$A$7,MATCH(MAX(INDEX(Affinity!$B$2:$CU$7,0,MATCH(A86,Affinity!$B$1:$CU$1,0))),INDEX(Affinity!$B$2:$CU$7,0,MATCH(A86,Affinity!$B$1:$CU$1,0)),0)),"—")) -> Earnest | Y86: 0 | Z86: 20000 | AA86: 1 | AB86: 90 | AC86: 2 | AD86: 0 | AE86: 0 | AF86: -1 | AG86: 1 | AH86: -2 | AI86: Shared_pool | AJ86: per_turn | AL86: continuous | AM86: 2 | AO86: No | AR86: Yes | AT86: Yes | AX86: ST03 | AY86: 4
A87: ST86 | B87: Town Hall on Parental Leave | C87: 育児休業と保育を巡る住民集会 | D87: Ikuji Kyūgyō to Hoiku o Meguru Jūmin Shūkai | E87: Combat | F87: Appeasement | G87: Percentage | H87: 100 | I87: 53 | J87: =IF(AND(ISNUMBER(H87),ISNUMBER(I87)),IF(H87=0,"",I87/H87),"varies") -> 0.53 | K87: 17 | L87: 3 | M87: 5 | N87: 6 | O87: 15 | P87: 20 | Q87: 0.1 | R87: 0.1 | S87: 0.7 | T87: 0.1 | U87: 0 | V87: 0 | W87: =SUM(Q87:V87) -> 1 | X87: =IF(E87<>"Combat","—",IFERROR(INDEX(Affinity!$A$2:$A$7,MATCH(MAX(INDEX(Affinity!$B$2:$CU$7,0,MATCH(A87,Affinity!$B$1:$CU$1,0))),INDEX(Affinity!$B$2:$CU$7,0,MATCH(A87,Affinity!$B$1:$CU$1,0)),0)),"—")) -> Emotional | Y87: 5 | Z87: 45000 | AA87: 1 | AB87: 70 | AC87: 0 | AD87: -5 | AE87: 0 | AF87: -3 | AG87: 10 | AH87: 0 | AI87: Shared_pool | AJ87: per_turn | AL87: stream | AM87: 3 | AN87: town_hall | AO87: No | AR87: Yes | AX87: ST05 | AY87: 2 | AZ87: 2
A88: ST87 | B88: Policy Study on Parental Leave | C88: 育児休業と保育政策検討会 | D88: Ikuji Kyūgyō to Hoiku Seisaku Kentōkai | E88: Combat | F88: Consensus | G88: Percentage | H88: 50 | I88: 44 | J88: =IF(AND(ISNUMBER(H88),ISNUMBER(I88)),IF(H88=0,"",I88/H88),"varies") -> 0.88 | K88: 10 | L88: 5 | M88: 5 | N88: 10 | O88: 1 | P88: 10 | Q88: 0 | R88: 0 | S88: 0 | T88: 0 | U88: 0.8 | V88: 0.2 | W88: =SUM(Q88:V88) -> 1 | X88: =IF(E88<>"Combat","—",IFERROR(INDEX(Affinity!$A$2:$A$7,MATCH(MAX(INDEX(Affinity!$B$2:$CU$7,0,MATCH(A88,Affinity!$B$1:$CU$1,0))),INDEX(Affinity!$B$2:$CU$7,0,MATCH(A88,Affinity!$B$1:$CU$1,0)),0)),"—")) -> Emotional | Y88: 1 | Z88: 15000 | AA88: 1 | AB88: 55 | AC88: 1 | AD88: 0 | AE88: 0 | AF88: 0 | AG88: 5 | AH88: 0 | AI88: Shared_pool | AJ88: per_turn | AL88: stream | AM88: 2 | AN88: policy_study | AO88: No | AQ88: No | AR88: Yes | AX88: ST21 | AY88: 2
A89: ST88 | B89: Lobbyist Meeting on Parental Leave | C89: 育児休業と保育に関するロビー活動 | D89: Ikuji Kyūgyō to Hoiku ni Kansuru Robī Katsudō | E89: Combat | F89: Appeasement | G89: Percentage | H89: 50 | I89: 25 | J89: =IF(AND(ISNUMBER(H89),ISNUMBER(I89)),IF(H89=0,"",I89/H89),"varies") -> 0.5 | K89: 7 | L89: 3 | M89: 5 | N89: 6 | O89: 5 | P89: 15 | Q89: 0 | R89: 0 | S89: 0 | T89: 1 | U89: 0 | V89: 0 | W89: =SUM(Q89:V89) -> 1 | X89: =IF(E89<>"Combat","—",IFERROR(INDEX(Affinity!$A$2:$A$7,MATCH(MAX(INDEX(Affinity!$B$2:$CU$7,0,MATCH(A89,Affinity!$B$1:$CU$1,0))),INDEX(Affinity!$B$2:$CU$7,0,MATCH(A89,Affinity!$B$1:$CU$1,0)),0)),"—")) -> Earnest | Y89: 0 | Z89: 50000 | AA89: 0 | AB89: 75 | AC89: 0 | AD89: 0 | AE89: 0 | AF89: 0 | AG89: 0 | AH89: -1 | AI89: Shared_pool | AJ89: pool | AK89: 12 | AL89: single | AM89: 1 | AN89: lobbyist_meeting | AO89: No | AR89: Yes | AX89: ST20 | AY89: 2
A90: ST89 | B90: Party Caucus on Parental Leave | C90: 育児休業と保育党内会合 | D90: Ikuji Kyūgyō to Hoiku Tōnai Kaigō | E90: Combat | F90: Support | G90: Percentage | H90: 100 | I90: 49 | J90: =IF(AND(ISNUMBER(H90),ISNUMBER(I90)),IF(H90=0,"",I90/H90),"varies") -> 0.49 | K90: 10 | L90: 3 | M90: 5 | N90: 5 | O90: 20 | P90: 40 | Q90: 0 | R90: 0.55 | S90: 0 | T90: 0 | U90: 0 | V90: 0.45 | W90: =SUM(Q90:V90) -> 1 | X90: =IF(E90<>"Combat","—",IFERROR(INDEX(Affinity!$A$2:$A$7,MATCH(MAX(INDEX(Affinity!$B$2:$CU$7,0,MATCH(A90,Affinity!$B$1:$CU$1,0))),INDEX(Affinity!$B$2:$CU$7,0,MATCH(A90,Affinity!$B$1:$CU$1,0)),0)),"—")) -> Emotional | Y90: 0 | Z90: 20000 | AA90: 1 | AB90: 90 | AC90: 2 | AD90: 0 | AE90: 0 | AF90: -1 | AG90: 1 | AH90: -2 | AI90: Shared_pool | AJ90: per_turn | AL90: continuous | AM90: 2 | AO90: No | AR90: Yes | AT90: Yes | AX90: ST03 | AY90: 4
A91: ST90 | B91: Hearing on Surveillance Cameras | C91: 監視カメラに関する公聴会 | D91: Kanshi Kamera ni Kansuru Kōchōkai | E91: Combat | F91: Favorability | G91: Percentage | H91: 100 | I91: 81 | J91: =IF(AND(ISNUMBER(H91),ISNUMBER(I91)),IF(H91=0,"",I91/H91),"varies") -> 0.81 | K91: 10 | L91: 5 | M91: 5 | N91: 5 | O91: 30 | P91: 40 | Q91: 0.15 | R91: 0 | S91: 0.1 | T91: 0.1 | U91: 0.65 | V91: 0 | W91: =SUM(Q91:V91) -> 1 | X91: =IF(E91<>"Combat","—",IFERROR(INDEX(Affinity!$A$2:$A$7,MATCH(MAX(INDEX(Affinity!$B$2:$CU$7,0,MATCH(A91,Affinity!$B$1:$CU$1,0))),INDEX(Affinity!$B$2:$CU$7,0,MATCH(A91,Affinity!$B$1:$CU$1,0)),0)),"—")) -> Data Driven | Y91: 1 | Z91: 50000 | AA91: 5 | AB91: 40 | AC91: 5 | AD91: 0 | AE91: 0 | AF91: 0 | AG91: 2 | AH91: 0 | AI91: Shared_pool | AJ91: per_turn | AL91: reset | AM91: 4 | AO91: No | AR91: Yes | AX91: ST17 | AY91: 4 | BA91: 1
A92: ST91 | B92: TV Debate on Surveillance Cameras | C92: 監視カメラテレビ討論 | D92: Kanshi Kamera Terebi Tōron | E92: Combat | F92: Viewer Interest | G92: Numerical | H92: 100 | I92: 65 | J92: =IF(AND(ISNUMBER(H92),ISNUMBER(I92)),IF(H92=0,"",I92/H92),"varies") -> 0.65 | K92: 5 | L92: 5 | M92: 6 | N92: 5 | O92: 60 | P92: 50 | Q92: 0.8 | R92: 0 | S92: 0.2 | T92: 0 | U92: 0 | V92: 0 | W92: =SUM(Q92:V92) -> 1 | X92: =IF(E92<>"Combat","—",IFERROR(INDEX(Affinity!$A$2:$A$7,MATCH(MAX(INDEX(Affinity!$B$2:$CU$7,0,MATCH(A92,Affinity!$B$1:$CU$1,0))),INDEX(Affinity!$B$2:$CU$7,0,MATCH(A92,Affinity!$B$1:$CU$1,0)),0)),"—")) -> Data Driven | Y92: 3 | Z92: 40000 | AA92: 2 | AB92: 55 | AC92: 2 | AD92: -1 | AE92: 0 | AF92: -3 | AG92: 0 | AH92: -1 | AI92: Survival | AJ92: per_turn | AL92: single | AM92: 1 | AO92: Yes | AR92: Yes | AU92: 0 | AV92: 3 | AX92: ST06 | AY92: 3 | BA92: 3
A93: ST92 | B93: Press Conference on Surveillance Cameras | C93: 監視カメラ記者会見 | D93: Kanshi Kamera Kisha Kaiken | E93: Combat | F93: Press tone | G93: Numerical | H93: 100 | I93: 57 | J93: =IF(AND(ISNUMBER(H93),ISNUMBER(I93)),IF(H93=0,"",I93/H93),"varies") -> 0.57 | K93: 6 | L93: 3 | M93: 5 | N93: 4 | O93: 20 | P93: 45 | Q93: 0.9 | R93: 0 | S93: 0 | T93: 0 | U93: 0.05 | V93: 0.05 | W93: =SUM(Q93:V93) -> 1 | X93: =IF(E93<>"Combat","—",IFERROR(INDEX(Affinity!$A$2:$A$7,MATCH(MAX(INDEX(Affinity!$B$2:$CU$7,0,MATCH(A93,Affinity!$B$1:$CU$1,0))),INDEX(Affinity!$B$2:$CU$7,0,MATCH(A93,Affinity!$B$1:$CU$1,0)),0)),"—")) -> Earnest | Y93: 1 | Z93: 30000 | AA93: 1 | AB93: 60 | AC93: 1 | AD93: 0 | AE93: 0 | AF93: -2 | AG93: 5 | AH93: -2 | AI93: Single | AJ93: per_turn | AL93: single | AM93: 1 | AN93: press_conference | AO93: Yes | AQ93: No | AR93: Yes | AX93: ST04 | AY93: 2 | BA93: 2
A94: ST93 | B94: Party Caucus on Surveillance Cameras | C94: 監視カメラ党内会合 | D94: Kanshi Kamera Tōnai Kaigō | E94: Combat | F94: Support | G94: Percentage | H94: 100 | I94: 49 | J94: =IF(AND(ISNUMBER(H94),ISNUMBER(I94)),IF(H94=0,"",I94/H94),"varies") -> 0.49 | K94: 10 | L94: 3 | M94: 5 | N94: 5 | O94: 20 | P94: 40 | Q94: 0 | R94: 0.55 | S94: 0 | T94: 0 | U94: 0 | V94: 0.45 | W94: =SUM(Q94:V94) -> 1 | X94: =IF(E94<>"Combat","—",IFERROR(INDEX(Affinity!$A$2:$A$7,MATCH(MAX(INDEX(Affinity!$B$2:$CU$7,0,MATCH(A94,Affinity!$B$1:$CU$1,0))),INDEX(Affinity!$B$2:$CU$7,0,MATCH(A94,Affinity!$B$1:$CU$1,0)),0)),"—")) -> Data Driven | Y94: 0 | Z94: 20000 | AA94: 1 | AB94: 90 | AC94: 2 | AD94: 0 | AE94: 0 | AF94: -1 | AG94: 1 | AH94: -2 | AI94: Shared_pool | AJ94: per_turn | AL94: continuous | AM94: 2 | AO94: No | AR94: Yes | AT94: Yes | AX94: ST03 | AY94: 4
A95: ST94 | B95: Town Hall on Town Mergers | C95: 自治体合併を巡る住民集会 | D95: Jichitai Gappei o Meguru Jūmin Shūkai | E95: Combat | F95: Appeasement | G95: Percentage | H95: 100 | I95: 53 | J95: =IF(AND(ISNUMBER(H95),ISNUMBER(I95)),IF(H95=0,"",I95/H95),"varies") -> 0.53 | K95: 17 | L95: 3 | M95: 5 | N95: 6 | O95: 15 | P95: 20 | Q95: 0.1 | R95: 0.1 | S95: 0.7 | T95: 0.1 | U95: 0 | V95: 0 | W95: =SUM(Q95:V95) -> 1 | X95: =IF(E95<>"Combat","—",IFERROR(INDEX(Affinity!$A$2:$A$7,MATCH(MAX(INDEX(Affinity!$B$2:$CU$7,0,MATCH(A95,Affinity!$B$1:$CU$1,0))),INDEX(Affinity!$B$2:$CU$7,0,MATCH(A95,Affinity!$B$1:$CU$1,0)),0)),"—")) -> Appeal | Y95: 5 | Z95: 45000 | AA95: 1 | AB95: 70 | AC95: 0 | AD95: -5 | AE95: 0 | AF95: -3 | AG95: 10 | AH95: 0 | AI95: Shared_pool | AJ95: per_turn | AL95: stream | AM95: 3 | AN95: town_hall | AO95: No | AR95: Yes | AX95: ST05 | AY95: 2 | AZ95: 2
A96: ST95 | B96: Hearing on Town Mergers | C96: 自治体合併に関する公聴会 | D96: Jichitai Gappei ni Kansuru Kōchōkai | E96: Combat | F96: Favorability | G96: Percentage | H96: 100 | I96: 78 | J96: =IF(AND(ISNUMBER(H96),ISNUMBER(I96)),IF(H96=0,"",I96/H96),"varies") -> 0.78 | K96: 10 | L96: 5 | M96: 5 | N96: 5 | O96: 30 | P96: 40 | Q96: 0.15 | R96: 0 | S96: 0.1 | T96: 0.1 | U96: 0.65 | V96: 0 | W96: =SUM(Q96:V96) -> 1 | X96: =IF(E96<>"Combat","—",IFERROR(INDEX(Affinity!$A$2:$A$7,MATCH(MAX(INDEX(Affinity!$B$2:$CU$7,0,MATCH(A96,Affinity!$B$1:$CU$1,0))),INDEX(Affinity!$B$2:$CU$7,0,MATCH(A96,Affinity!$B$1:$CU$1,0)),0)),"—")) -> Appeal | Y96: 1 | Z96: 50000 | AA96: 5 | AB96: 40 | AC96: 5 | AD96: 0 | AE96: 0 | AF96: 0 | AG96: 2 | AH96: 0 | AI96: Shared_pool | AJ96: per_turn | AL96: reset | AM96: 4 | AO96: No | AR96: Yes | AX96: ST17 | AY96: 4 | BA96: 1
A97: ST96 | B97: Policy Study on Town Mergers | C97: 自治体合併政策検討会 | D97: Jichitai Gappei Seisaku Kentōkai | E97: Combat | F97: Consensus | G97: Percentage | H97: 50 | I97: 43 | J97: =IF(AND(ISNUMBER(H97),ISNUMBER(I97)),IF(H97=0,"",I97/H97),"varies") -> 0.86 | K97: 10 | L97: 5 | M97: 5 | N97: 10 | O97: 1 | P97: 10 | Q97: 0 | R97: 0 | S97: 0 | T97: 0 | U97: 0.8 | V97: 0.2 | W97: =SUM(Q97:V97) -> 1 | X97: =IF(E97<>"Combat","—",IFERROR(INDEX(Affinity!$A$2:$A$7,MATCH(MAX(INDEX(Affinity!$B$2:$CU$7,0,MATCH(A97,Affinity!$B$1:$CU$1,0))),INDEX(Affinity!$B$2:$CU$7,0,MATCH(A97,Affinity!$B$1:$CU$1,0)),0)),"—")) -> Data Driven | Y97: 1 | Z97: 15000 | AA97: 1 | AB97: 55 | AC97: 1 | AD97: 0 | AE97: 0 | AF97: 0 | AG97: 5 | AH97: 0 | AI97: Shared_pool | AJ97: per_turn | AL97: stream | AM97: 2 | AN97: policy_study | AO97: No | AQ97: No | AR97: Yes | AX97: ST21 | AY97: 2
A98: ST97 | B98: Party Caucus on Town Mergers | C98: 自治体合併党内会合 | D98: Jichitai Gappei Tōnai Kaigō | E98: Combat | F98: Support | G98: Percentage | H98: 100 | I98: 49 | J98: =IF(AND(ISNUMBER(H98),ISNUMBER(I98)),IF(H98=0,"",I98/H98),"varies") -> 0.49 | K98: 10 | L98: 3 | M98: 5 | N98: 5 | O98: 20 | P98: 40 | Q98: 0 | R98: 0.55 | S98: 0 | T98: 0 | U98: 0 | V98: 0.45 | W98: =SUM(Q98:V98) -> 1 | X98: =IF(E98<>"Combat","—",IFERROR(INDEX(Affinity!$A$2:$A$7,MATCH(MAX(INDEX(Affinity!$B$2:$CU$7,0,MATCH(A98,Affinity!$B$1:$CU$1,0))),INDEX(Affinity!$B$2:$CU$7,0,MATCH(A98,Affinity!$B$1:$CU$1,0)),0)),"—")) -> Appeal | Y98: 0 | Z98: 20000 | AA98: 1 | AB98: 90 | AC98: 2 | AD98: 0 | AE98: 0 | AF98: -1 | AG98: 1 | AH98: -2 | AI98: Shared_pool | AJ98: per_turn | AL98: continuous | AM98: 2 | AO98: No | AR98: Yes | AT98: Yes | AX98: ST03 | AY98: 4
A99: ST98 | B99: TV Debate on Party Leadership Ballots | C99: 党首選出方法テレビ討論 | D99: Tōshu Senshutsu Hōhō Terebi Tōron | E99: Combat | F99: Viewer Interest | G99: Numerical | H99: 100 | I99: 65 | J99: =IF(AND(ISNUMBER(H99),ISNUMBER(I99)),IF(H99=0,"",I99/H99),"varies") -> 0.65 | K99: 5 | L99: 5 | M99: 6 | N99: 5 | O99: 60 | P99: 50 | Q99: 0.8 | R99: 0 | S99: 0.2 | T99: 0 | U99: 0 | V99: 0 | W99: =SUM(Q99:V99) -> 1 | X99: =IF(E99<>"Combat","—",IFERROR(INDEX(Affinity!$A$2:$A$7,MATCH(MAX(INDEX(Affinity!$B$2:$CU$7,0,MATCH(A99,Affinity!$B$1:$CU$1,0))),INDEX(Affinity!$B$2:$CU$7,0,MATCH(A99,Affinity!$B$1:$CU$1,0)),0)),"—")) -> Earnest | Y99: 3 | Z99: 40000 | AA99: 2 | AB99: 55 | AC99: 2 | AD99: -1 | AE99: 0 | AF99: -3 | AG99: 0 | AH99: -1 | AI99: Survival | AJ99: per_turn | AL99: single | AM99: 1 | AO99: Yes | AR99: Yes | AU99: 0 | AV99: 3 | AX99: ST06 | AY99: 3 | BA99: 3
A100: ST99 | B100: Press Conference on Party Leadership Ballots | C100: 党首選出方法記者会見 | D100: Tōshu Senshutsu Hōhō Kisha Kaiken | E100: Combat | F100: Press tone | G100: Numerical | H100: 100 | I100: 53 | J100: =IF(AND(ISNUMBER(H100),ISNUMBER(I100)),IF(H100=0,"",I100/H100),"varies") -> 0.53 | K100: 6 | L100: 3 | M100: 5 | N100: 4 | O100: 20 | P100: 45 | Q100: 0.9 | R100: 0 | S100: 0 | T100: 0 | U100: 0.05 | V100: 0.05 | W100: =SUM(Q100:V100) -> 1 | X100: =IF(E100<>"Combat","—",IFERROR(INDEX(Affinity!$A$2:$A$7,MATCH(MAX(INDEX(Affinity!$B$2:$CU$7,0,MATCH(A100,Affinity!$B$1:$CU$1,0))),INDEX(Affinity!$B$2:$CU$7,0,MATCH(A100,Affinity!$B$1:$CU$1,0)),0)),"—")) -> Earnest | Y100: 1 | Z100: 30000 | AA100: 1 | AB100: 60 | AC100: 1 | AD100: 0 | AE100: 0 | AF100: -2 | AG100: 5 | AH100: -2 | AI100: Single | AJ100: per_turn | AL100: single | AM100: 1 | AN100: press_conference | AO100: Yes | AQ100: No | AR100: Yes | AX100: ST04 | AY100: 2 | BA100: 2
...

Sheet Levels
A1: Level ID | B1: Level Description | C1: Cooldown Period (game clock units before this level is available to play again) | D1: Level Tier | E1: Cost in XP to Unlock if Policy Research Assistant is Vacant | F1: Cost in XP to Unlock if Policy Research Assistant is Tier 0 | G1: Cost in XP to Unlock if Policy Research Assistant is Tier 1 | H1: Cost in XP to Unlock if Policy Research Assistant is Tier 2 | I1: Stage ID for Part 1 | J1: Stage ID for Part 2 | K1: Stage ID for Part 3 | L1: Stage ID for Part 4 | M1: Stage ID for Part 5 | N1: Stage ID for Part 6 | O1: Stage ID for Part 7 | P1: Stage ID for Part 8 | Q1: Stage ID for Part 9 | R1: Stage ID for Part 10 | S1: Bonus Win Range ΔJiban | T1: Bonus Win Range ΔYen | U1: Bonus Win Range ΔReputation | V1: Bonus Win Range ΔXP | W1: Bonus Win Range ΔParty support | X1: Win ΔBO01 | Y1: Win ΔBO02 | Z1: Win ΔBO03 | AA1: Win ΔBO04 | AB1: Win ΔBO05 | AC1: Win ΔBO06 | AD1: Win ΔBO07 | AE1: Win ΔBO08 | AF1: Win ΔBO09 | AG1: Win ΔBO10 | AH1: Win ΔBO11 | AI1: Win ΔBO12 | AJ1: Win ΔBO13 | AK1: Win ΔBO14 | AL1: Win ΔBO15 | AM1: Win ΔBO16 | AN1: One-Time (Yes/No) | AO1: Special Trigger | AP1: Win ΔBO17 | AQ1: Win ΔBO18 | AR1: Win ΔBO19 | AS1: Win ΔBO20 | AT1: Win ΔBO21 | AU1: Win ΔBO22 | AV1: Win ΔBO23 | AW1: Win ΔBO24 | AX1: Win ΔBO25 | AY1: Win ΔBO26 | AZ1: Win ΔBO27 | BA1: Win ΔBO28 | BB1: Win ΔBO29 | BC1: Win ΔBO30 | BD1: Win ΔBO31 | BE1: Win ΔBO32 | BF1: Weekend OK (Yes/No) | BG1: Needs Discovery (Yes/No) | BH1: Host Org (BOxx)
A2: LV01 | B2: Talking with Constituents | C2: 36 | D2: 0 | E2: 0 | F2: 0 | G2: 0 | H2: 0 | I2: ST05 | J2: ST07 | K2: N/A | L2: N/A | M2: N/A | N2: N/A | O2: N/A | P2: N/A | Q2: N/A | R2: N/A | S2: 0 | T2: 0 | U2: 0 | V2: 0 | W2: 0% | X2: 0 | Y2: 0 | Z2: 0-1 | AA2: 0-1 | AB2: 0 | AC2: 0-1 | AD2: 0 | AE2: 0 | AF2: 0 | AG2: 0 | AH2: 0 | AI2: 0 | AJ2: 0 | AK2: 0 | AL2: 0 | AM2: 0 | AN2: No
A3: LV02 | B3: Meeting Lobbyists | C3: 18 | D3: 0 | E3: 0 | F3: 0 | G3: 0 | H3: 0 | I3: ST20 | J3: ST19 | K3: N/A | L3: N/A | M3: N/A | N3: N/A | O3: N/A | P3: N/A | Q3: N/A | R3: N/A | S3: 0 | T3: 0 | U3: 0 | V3: 0 | W3: 0% | X3: 0 | Y3: 0 | Z3: 0 | AA3: 0 | AB3: 0 | AC3: 0 | AD3: 0 | AE3: 0 | AF3: 0 | AG3: 0 | AH3: 0 | AI3: 0 | AJ3: 0 | AK3: 0 | AL3: 0 | AM3: 0 | AN3: No
A4: LV03 | B4: Policy Listening and Study | C4: 54 | D4: 0 | E4: 0 | F4: 0 | G4: 0 | H4: 0 | I4: ST05 | J4: ST20 | K4: ST21 | L4: N/A | M4: N/A | N4: N/A | O4: N/A | P4: N/A | Q4: N/A | R4: N/A | S4: 0 | T4: 0 | U4: 0 | V4: 0 | W4: 0% | X4: 0 | Y4: 0-1 | Z4: 0 | AA4: 0 | AB4: 0-2 | AC4: 0 | AD4: 0 | AE4: 0 | AF4: 0-1 | AG4: 0 | AH4: 0 | AI4: 0 | AJ4: 0 | AK4: 0 | AL4: 0 | AM4: 0 | AN4: No
A5: LV04 | B5: Hearing at the Committee on the Environment | C5: 54 | D5: 0 | E5: 0 | F5: 0 | G5: 0 | H5: 0 | I5: ST03 | J5: ST04 | K5: ST10 | L5: N/A | M5: N/A | N5: N/A | O5: N/A | P5: N/A | Q5: N/A | R5: N/A | S5: 0-3 | T5: 0-1100 | U5: 0-5 | V5: 0 | W5: 0% | X5: 0 | Y5: 0 | Z5: 0-1 | AA5: 0-1 | AB5: 0 | AC5: 0-1 | AD5: 0 | AE5: 0 | AF5: 0 | AG5: 1-3 | AH5: 0 | AI5: 0 | AJ5: 0 | AK5: 0 | AL5: 0 | AM5: 0 | AN5: No
A6: LV05 | B6: Media Rounds | C6: 90 | D6: 0 | E6: 0 | F6: 0 | G6: 0 | H6: 0 | I6: ST04 | J6: ST06 | K6: ST03 | L6: ST05 | M6: ST19 | N6: N/A | O6: N/A | P6: N/A | Q6: N/A | R6: N/A | S6: 0 | T6: 0-5000 | U6: 2 | V6: 25 | W6: 0-3% | X6: 0 | Y6: 0-2 | Z6: 0-5 | AA6: 0-1 | AB6: 0-1 | AC6: 0-2 | AD6: 0-1 | AE6: 2-7 | AF6: 0-1 | AG6: 0-2 | AH6: 0 | AI6: 0 | AJ6: 0 | AK6: 0 | AL6: 0 | AM6: 0 | AN6: No
A7: LV06 | B7: Providing the Party Agricultural Policy Support | C7: 126 | D7: 0 | E7: 0 | F7: 0 | G7: 0 | H7: 0 | I7: ST03 | J7: ST04 | K7: ST20 | L7: ST21 | M7: ST03 | N7: ST13 | O7: ST02 | P7: N/A | Q7: N/A | R7: N/A | S7: 0-3 | T7: 0-22000 | U7: 0 | V7: 5 | W7: 2-10% | X7: 0-3 | Y7: 0-3 | Z7: 0-1 | AA7: 0-1 | AB7: 0 | AC7: 0-1 | AD7: 0-2 | AE7: 0-1 | AF7: 0-2 | AG7: 0-2 | AH7: 0 | AI7: 0 | AJ7: 0 | AK7: 0 | AL7: 0 | AM7: 0 | AN7: No
A8: LV07 | B8: Providing the Party Infrastructure Policy Support | C8: 180 | D8: 0 | E8: 25 | F8: 20 | G8: 10 | H8: 0 | I8: ST20 | J8: ST21 | K8: ST03 | L8: ST06 | M8: ST15 | N8: ST02 | O8: ST19 | P8: N/A | Q8: N/A | R8: N/A | S8: 0-2 | T8: 0-25000 | U8: 0 | V8: 5 | W8: 3-12% | X8: 0-3 | Y8: 0-3 | Z8: 0 | AA8: 0-2 | AB8: 0-3 | AC8: 0 | AD8: 0-2 | AE8: 0 | AF8: 0-6 | AG8: 0 | AH8: 0 | AI8: 0 | AJ8: 0 | AK8: 0 | AL8: 0 | AM8: 0 | AN8: No
A9: LV08 | B9: Fighting on the Floor for the Party | C9: 270 | D9: 0 | E9: 50 | F9: 25 | G9: 15 | H9: 10 | I9: ST04 | J9: ST02 | K9: ST04 | L9: ST02 | M9: ST19 | N9: ST02 | O9: N/A | P9: N/A | Q9: N/A | R9: N/A | S9: 0 | T9: 3000-19000 | U9: 7 | V9: 15 | W9: 10-17% | X9: 2-5 | Y9: 2-5 | Z9: 0 | AA9: 0 | AB9: 0 | AC9: 0 | AD9: 0-2 | AE9: 0-4 | AF9: 0 | AG9: 0 | AH9: 0 | AI9: 0 | AJ9: 0 | AK9: 0 | AL9: 0 | AM9: 0 | AN9: No
A10: LV09 | B10: Filling in at Committees | C10: 270 | D10: 0 | E10: 50 | F10: 25 | G10: 15 | H10: 10 | I10: ST01 | J10: ST10 | K10: ST21 | L10: ST17 | M10: ST01 | N10: ST14 | O10: N/A | P10: N/A | Q10: N/A | R10: N/A | S10: 0 | T10: 0-22000 | U10: 3 | V10: 10 | W10: 10-22% | X10: 0-2 | Y10: 1-5 | Z10: 0 | AA10: 0 | AB10: 0 | AC10: 0 | AD10: 0 | AE10: 0 | AF10: 0 | AG10: 0 | AH10: 0 | AI10: 0 | AJ10: 0 | AK10: 0 | AL10: 0 | AM10: 0 | AN10: No
A11: LV10 | B11: Advancing a Bill to Protect Hometown Markets | C11: 360 | D11: 1 | E11: 150 | F11: 100 | G11: 50 | H11: 10 | I11: ST05 | J11: ST04 | K11: ST05 | L11: ST21 | M11: ST20 | N11: ST21 | O11: ST01 | P11: ST06 | Q11: ST15 | R11: ST02 | S11: 4-16 | T11: 5000-25000 | U11: 6-12 | V11: 55-95 | W11: 2-6% | X11: 0 | Y11: 0 | Z11: 5-9 | AA11: 2-4 | AB11: 0-4 | AC11: 1-4 | AD11: 3-6 | AE11: 0 | AF11: 0 | AG11: 2-8 | AH11: 0 | AI11: 0 | AJ11: 0 | AK11: 0 | AL11: 0 | AM11: 0 | AN11: No
A12: LV11 | B12: Meeting with Student Organizers | C12: 90 | D12: 1 | E12: 150 | F12: 100 | G12: 50 | H12: 10 | I12: ST07 | J12: ST05 | K12: ST21 | L12: N/A | M12: N/A | N12: N/A | O12: N/A | P12: N/A | Q12: N/A | R12: N/A | S12: 0-1 | T12: 3000-12000 | U12: 1-2 | V12: 15-30 | W12: 1-4% | X12: 0 | Y12: 0 | Z12: 0-1 | AA12: 0 | AB12: 0 | AC12: 0 | AD12: 0 | AE12: 0 | AF12: 0 | AG12: 0 | AH12: 2-4 | AI12: 0 | AJ12: 0 | AK12: 0 | AL12: 0 | AM12: 0 | AN12: No
A13: LV12 | B13: Family Outreach Tour | C13: 108 | D13: 1 | E13: 150 | F13: 100 | G13: 50 | H13: 10 | I13: ST07 | J13: ST05 | K13: ST10 | L13: ST15 | M13: N/A | N13: N/A | O13: N/A | P13: N/A | Q13: N/A | R13: N/A | S13: 0-2 | T13: 5000-15000 | U13: 1-3 | V13: 20-35 | W13: 2-5% | X13: 0 | Y13: 0 | Z13: 0-1 | AA13: 0 | AB13: 0 | AC13: 1-2 | AD13: 0 | AE13: 0 | AF13: 0 | AG13: 0 | AH13: 0 | AI13: 2-4 | AJ13: 0 | AK13: 0 | AL13: 0 | AM13: 0 | AN13: No
A14: LV13 | B14: Backing the Local Artisans | C14: 108 | D14: 1 | E14: 150 | F14: 100 | G14: 50 | H14: 10 | I14: ST20 | J14: ST02 | K14: ST16 | L14: ST15 | M14: N/A | N14: N/A | O14: N/A | P14: N/A | Q14: N/A | R14: N/A | S14: 0-2 | T14: 5000-18000 | U14: 1-3 | V14: 20-35 | W14: 2-5% | X14: 0 | Y14: 0 | Z14: 0 | AA14: 0 | AB14: 1-2 | AC14: 0 | AD14: 0 | AE14: 0 | AF14: 0 | AG14: 0 | AH14: 0 | AI14: 0 | AJ14: 2-4 | AK14: 0 | AL14: 0 | AM14: 0 | AN14: No
A15: LV14 | B15: Fixing the Daily Commute | C15: 144 | D15: 1 | E15: 150 | F15: 100 | G15: 50 | H15: 10 | I15: ST07 | J15: ST20 | K15: ST15 | L15: ST17 | M15: ST02 | N15: N/A | O15: N/A | P15: N/A | Q15: N/A | R15: N/A | S15: 0-2 | T15: 6000-20000 | U15: 1-3 | V15: 25-40 | W15: 2-6% | X15: 0 | Y15: 0 | Z15: 0 | AA15: 1-2 | AB15: 0 | AC15: 0 | AD15: 0 | AE15: 0 | AF15: 0 | AG15: 0 | AH15: 0 | AI15: 0 | AJ15: 0 | AK15: 2-4 | AL15: 0 | AM15: 0 | AN15: No
A16: LV15 | B16: Courting the Traditionalist Wing | C16: 180 | D16: 1 | E16: 150 | F16: 100 | G16: 50 | H16: 10 | I16: ST03 | J16: ST06 | K16: ST14 | L16: ST18 | M16: ST04 | N16: ST02 | O16: N/A | P16: N/A | Q16: N/A | R16: N/A | S16: 1-3 | T16: 8000-22000 | U16: 2-4 | V16: 25-45 | W16: 3-7% | X16: 1-2 | Y16: 0 | Z16: 0 | AA16: 0 | AB16: 0 | AC16: 0 | AD16: 0 | AE16: 0-1 | AF16: 0 | AG16: 0 | AH16: 0 | AI16: 0 | AJ16: 0 | AK16: 0 | AL16: 2-4 | AM16: 0 | AN16: No
A17: LV16 | B17: Running with the Reform Caucus | C17: 216 | D17: 1 | E17: 150 | F17: 100 | G17: 50 | H17: 10 | I17: ST04 | J17: ST06 | K17: ST12 | L17: ST16 | M17: ST17 | N17: ST21 | O17: ST19 | P17: ST02 | Q17: N/A | R17: N/A | S17: 1-3 | T17: 10000-25000 | U17: 2-5 | V17: 30-55 | W17: 3-8% | X17: 0 | Y17: 0 | Z17: 0 | AA17: 0 | AB17: 0-1 | AC17: 0 | AD17: 0 | AE17: 1-2 | AF17: 0 | AG17: 0 | AH17: 0 | AI17: 0 | AJ17: 0 | AK17: 0 | AL17: 0 | AM17: 2-4 | AN17: No
A18: LV17 | B18: Building the Next-Generation Coalition | C18: 252 | D18: 1 | E18: 150 | F18: 100 | G18: 50 | H18: 10 | I18: ST07 | J18: ST05 | K18: ST21 | L18: ST05 | M18: ST10 | N18: ST15 | O18: ST04 | P18: ST19 | Q18: ST02 | R18: N/A | S18: 1-4 | T18: 12000-28000 | U18: 2-5 | V18: 35-60 | W18: 4-9% | X18: 0 | Y18: 0 | Z18: 0-1 | AA18: 0 | AB18: 0 | AC18: 0-1 | AD18: 0 | AE18: 0 | AF18: 0 | AG18: 0 | AH18: 1-3 | AI18: 1-3 | AJ18: 0 | AK18: 0 | AL18: 0 | AM18: 0 | AN18: No
A19: LV18 | B19: Uniting Main Street and Transit Riders | C19: 270 | D19: 1 | E19: 150 | F19: 100 | G19: 50 | H19: 10 | I19: ST20 | J19: ST02 | K19: ST16 | L19: ST15 | M19: ST17 | N19: ST20 | O19: ST02 | P19: ST19 | Q19: ST04 | R19: ST02 | S19: 2-4 | T19: 15000-30000 | U19: 3-6 | V19: 40-65 | W19: 5-10% | X19: 0 | Y19: 0 | Z19: 0 | AA19: 0-1 | AB19: 0-1 | AC19: 0 | AD19: 0 | AE19: 0 | AF19: 0 | AG19: 0 | AH19: 0 | AI19: 0 | AJ19: 1-3 | AK19: 1-3 | AL19: 0 | AM19: 0 | AN19: No
A20: LV19 | B20: Bridging Old Guard and New Wave | C20: 270 | D20: 1 | E20: 150 | F20: 100 | G20: 50 | H20: 10 | I20: ST03 | J20: ST06 | K20: ST18 | L20: ST14 | M20: ST04 | N20: ST12 | O20: ST16 | P20: ST17 | Q20: ST21 | R20: ST02 | S20: 2-4 | T20: 15000-30000 | U20: 3-6 | V20: 40-65 | W20: 5-10% | X20: 0-1 | Y20: 0 | Z20: 0 | AA20: 0 | AB20: 0 | AC20: 0 | AD20: 0 | AE20: 0-1 | AF20: 0 | AG20: 0 | AH20: 0 | AI20: 0 | AJ20: 0 | AK20: 0 | AL20: 1-3 | AM20: 1-3 | AN20: No
A21: LV20 | B21: Rallying Youth and Labor | C21: 180 | D21: 2 | E21: 300 | F21: 250 | G21: 200 | H21: 100 | I21: ST21 | J21: ST08 | K21: ST03 | L21: ST02 | M21: N/A | N21: N/A | O21: N/A | P21: N/A | Q21: N/A | R21: N/A | S21: 2-5 | T21: 15000-35000 | U21: 3-7 | V21: 40-70 | W21: 5-10% | X21: 0 | Y21: 0-2 | Z21: 0 | AA21: 0 | AB21: 0 | AC21: 0 | AD21: 0 | AE21: 0 | AF21: 2-4 | AG21: 0 | AH21: 2-5 | AI21: 0 | AJ21: 0 | AK21: 0 | AL21: 0 | AM21: 0 | AN21: No
A22: LV21 | B22: A Neighborhood Family Compact | C22: 216 | D22: 2 | E22: 300 | F22: 250 | G22: 200 | H22: 100 | I22: ST05 | J22: ST10 | K22: ST15 | L22: ST08 | M22: ST02 | N22: N/A | O22: N/A | P22: N/A | Q22: N/A | R22: N/A | S22: 2-5 | T22: 18000-38000 | U22: 3-7 | V22: 45-75 | W22: 6-11% | X22: 0 | Y22: 0 | Z22: 0-2 | AA22: 0 | AB22: 0 | AC22: 2-4 | AD22: 0 | AE22: 0 | AF22: 0 | AG22: 0 | AH22: 0 | AI22: 2-5 | AJ22: 0 | AK22: 0 | AL22: 0 | AM22: 0 | AN22: No
A23: LV22 | B23: A Small Business Coalition | C23: 270 | D23: 2 | E23: 300 | F23: 250 | G23: 200 | H23: 100 | I23: ST20 | J23: ST02 | K23: ST16 | L23: ST04 | M23: ST06 | N23: ST15 | O23: ST02 | P23: N/A | Q23: N/A | R23: N/A | S23: 3-6 | T23: 20000-42000 | U23: 4-8 | V23: 50-85 | W23: 7-13% | X23: 0-1 | Y23: 0 | Z23: 0 | AA23: 0 | AB23: 2-4 | AC23: 0 | AD23: 0 | AE23: 0 | AF23: 0 | AG23: 0 | AH23: 0 | AI23: 0 | AJ23: 2-5 | AK23: 0 | AL23: 0 | AM23: 0 | AN23: No
... A31: LV30 | B31: A Grand Bargain | C31: 5994 | D31: 2 | E31: 300 | F31: 250 | G31: 200 | H31: 100 | I31: ST03 | J31: ST18 | K31: ST06 | L31: ST04 | M31: ST12 | N31: ST16 | O31: ST17 | P31: ST08 | Q31: ST02 | R31: N/A | S31: 5-10 | T31: 40000-80000 | U31: 8-15 | V31: 90-150 | W31: 12-25% | X31: 1-3 | Y31: 0 | Z31: 0 | AA31: 0 | AB31: 0 | AC31: 0 | AD31: 0 | AE31: 1-3 | AF31: 0 | AG31: 0 | AH31: 0 | AI31: 0 | AJ31: 0 | AK31: 0 | AL31: 3-6 | AM31: 3-6 | AN31: No
A32: LV31 | B32: Ainu Heritage and Language Act | C32: 5994 | D32: 0 | E32: 50 | F32: 40 | G32: 30 | H32: 0 | I32: ST121 | J32: ST122 | K32: ST123 | L32: ST124 | M32: BI01 | N32: N/A | O32: N/A | P32: N/A | Q32: N/A | R32: N/A | S32: 0 | T32: 0 | U32: 0 | V32: 0 | W32: 0 | X32: 0 | Y32: 0 | Z32: 0 | AA32: 0 | AB32: 0 | AC32: 0 | AD32: 0 | AE32: 0 | AF32: 0 | AG32: 0 | AH32: 0 | AI32: 0 | AJ32: 0 | AK32: 0 | AL32: 0 | AM32: 0 | AN32: Yes | BA32: 0-1 | BB32: 0-1
A33: LV32 | B33: Agricultural Price Stabilization Act | C33: 5994 | D33: 0 | E33: 50 | F33: 40 | G33: 30 | H33: 0 | I33: ST125 | J33: ST126 | K33: ST127 | L33: ST128 | M33: BI02 | N33: N/A | O33: N/A | P33: N/A | Q33: N/A | R33: N/A | S33: 0 | T33: 0 | U33: 0 | V33: 0 | W33: 0 | X33: 0 | Y33: 0 | Z33: 0 | AA33: 0 | AB33: 0 | AC33: 0 | AD33: 0 | AE33: 0 | AF33: 0 | AG33: 0 | AH33: 0 | AI33: 0 | AJ33: 0 | AK33: 0 | AL33: 0 | AM33: 0 | AN33: Yes
A34: LV33 | B34: Special Economic Zones Act | C34: 5994 | D34: 0 | E34: 50 | F34: 40 | G34: 30 | H34: 0 | I34: ST129 | J34: ST130 | K34: ST131 | L34: ST132 | M34: ST133 | N34: ST134 | O34: ST135 | P34: BI03 | Q34: N/A | R34: N/A | S34: 0 | T34: 0 | U34: 0 | V34: 0 | W34: 0 | X34: 0 | Y34: 0 | Z34: 0 | AA34: 0 | AB34: 0 | AC34: 0 | AD34: 0 | AE34: 0 | AF34: 0 | AG34: 0 | AH34: 0 | AI34: 0 | AJ34: 0 | AK34: 0 | AL34: 0 | AM34: 0 | AN34: Yes
A35: LV34 | B35: Hokkaido Shinkansen Acceleration Act | C35: 5994 | D35: 0 | E35: 50 | F35: 40 | G35: 30 | H35: 0 | I35: ST136 | J35: ST137 | K35: ST138 | L35: ST139 | M35: ST140 | N35: ST141 | O35: BI04 | P35: N/A | Q35: N/A | R35: N/A | S35: 0 | T35: 0 | U35: 0 | V35: 0 | W35: 0 | X35: 0 | Y35: 0 | Z35: 0 | AA35: 0 | AB35: 0 | AC35: 0 | AD35: 0 | AE35: 0 | AF35: 0 | AG35: 0 | AH35: 0 | AI35: 0 | AJ35: 0 | AK35: 0 | AL35: 0 | AM35: 0 | AN35: Yes
A36: LV35 | B36: Chishima Coastal Defense Modernization Act | C36: 5994 | D36: 1 | E36: 100 | F36: 80 | G36: 60 | H36: 40 | I36: ST142 | J36: ST143 | K36: ST144 | L36: BI05 | M36: N/A | N36: N/A | O36: N/A | P36: N/A | Q36: N/A | R36: N/A | S36: 0 | T36: 30000-50000 | U36: 0 | V36: 80-120 | W36: 0 | X36: 0 | Y36: 0 | Z36: 0 | AA36: 0 | AB36: 0 | AC36: 0 | AD36: 0 | AE36: 0 | AF36: 0 | AG36: 0 | AH36: 0 | AI36: 0 | AJ36: 0 | AK36: 0 | AL36: 0 | AM36: 0 | AN36: Yes | AU36: 0-1 | BG36: Yes
A37: LV36 | B37: Specified Skilled Worker Visa Act | C37: 5994 | D37: 1 | E37: 100 | F37: 80 | G37: 60 | H37: 40 | I37: ST145 | J37: ST146 | K37: ST147 | L37: ST148 | M37: BI06 | N37: N/A | O37: N/A | P37: N/A | Q37: N/A | R37: N/A | S37: 0 | T37: 30000-50000 | U37: 0 | V37: 80-120 | W37: 0 | X37: 0 | Y37: 0 | Z37: 0 | AA37: 0 | AB37: 0 | AC37: 0 | AD37: 0 | AE37: 0 | AF37: 0 | AG37: 0 | AH37: 0 | AI37: 0 | AJ37: 0 | AK37: 0 | AL37: 0 | AM37: 0 | AN37: Yes
A38: LV37 | B38: Grid Resilience and Renewable Energy Act | C38: 5994 | D38: 1 | E38: 100 | F38: 80 | G38: 60 | H38: 40 | I38: ST149 | J38: ST150 | K38: ST151 | L38: ST152 | M38: BI07 | N38: N/A | O38: N/A | P38: N/A | Q38: N/A | R38: N/A | S38: 0 | T38: 30000-50000 | U38: 0 | V38: 80-120 | W38: 0 | X38: 0 | Y38: 0 | Z38: 0 | AA38: 0 | AB38: 0 | AC38: 0 | AD38: 0 | AE38: 0 | AF38: 0 | AG38: 0 | AH38: 0 | AI38: 0 | AJ38: 0 | AK38: 0 | AL38: 0 | AM38: 0 | AN38: Yes | BG38: Yes | BH38: BO16
A39: LV38 | B39: Consumption Tax Rate Act | C39: 5994 | D39: 1 | E39: 100 | F39: 80 | G39: 60 | H39: 40 | I39: ST153 | J39: ST154 | K39: ST155 | L39: ST156 | M39: BI08 | N39: N/A | O39: N/A | P39: N/A | Q39: N/A | R39: N/A | S39: 0 | T39: 30000-50000 | U39: 0 | V39: 80-120 | W39: 0 | X39: 0 | Y39: 0 | Z39: 0 | AA39: 0 | AB39: 0 | AC39: 0 | AD39: 0 | AE39: 0 | AF39: 0 | AG39: 0 | AH39: 0 | AI39: 0 | AJ39: 0 | AK39: 0 | AL39: 0 | AM39: 0 | AN39: Yes | AT39: 0-1
A40: LV39 | B40: Prefectural Fiscal Devolution Act | C40: 5994 | D40: 1 | E40: 100 | F40: 80 | G40: 60 | H40: 40 | I40: ST157 | J40: ST158 | K40: ST159 | L40: ST160 | M40: BI09 | N40: N/A | O40: N/A | P40: N/A | Q40: N/A | R40: N/A | S40: 0 | T40: 30000-50000 | U40: 0 | V40: 80-120 | W40: 0 | X40: 0 | Y40: 0 | Z40: 0 | AA40: 0 | AB40: 0 | AC40: 0 | AD40: 0 | AE40: 0 | AF40: 0 | AG40: 0 | AH40: 0 | AI40: 0 | AJ40: 0 | AK40: 0 | AL40: 0 | AM40: 0 | AN40: Yes | BG40: Yes
A41: LV40 | B41: Candidate Gender Parity Act | C41: 5994 | D41: 1 | E41: 100 | F41: 80 | G41: 60 | H41: 40 | I41: ST161 | J41: ST162 | K41: ST163 | L41: ST164 | M41: BI10 | N41: N/A | O41: N/A | P41: N/A | Q41: N/A | R41: N/A | S41: 0 | T41: 30000-50000 | U41: 0 | V41: 80-120 | W41: 0 | X41: 0 | Y41: 0 | Z41: 0 | AA41: 0 | AB41: 0 | AC41: 0 | AD41: 0 | AE41: 0 | AF41: 0 | AG41: 0 | AH41: 0 | AI41: 0 | AJ41: 0 | AK41: 0 | AL41: 0 | AM41: 0 | AN41: Yes
A42: LV41 | B42: Tsugaru Strait Joint Commission Act | C42: 5994 | D42: 1 | E42: 100 | F42: 80 | G42: 60 | H42: 40 | I42: ST165 | J42: ST166 | K42: ST167 | L42: ST168 | M42: ST169 | N42: BI11 | O42: N/A | P42: N/A | Q42: N/A | R42: N/A | S42: 0 | T42: 30000-50000 | U42: 0 | V42: 80-120 | W42: 0 | X42: 0 | Y42: 0 | Z42: 0 | AA42: 0 | AB42: 0 | AC42: 0 | AD42: 0 | AE42: 0 | AF42: 0 | AG42: 0 | AH42: 0 | AI42: 0 | AJ42: 0 | AK42: 0 | AL42: 0 | AM42: 0 | AN42: Yes | BG42: Yes | BH42: BO07
A43: LV42 | B43: Judicial Appointments Commission Act | C43: 5994 | D43: 1 | E43: 100 | F43: 80 | G43: 60 | H43: 40 | I43: ST170 | J43: ST171 | K43: ST172 | L43: ST173 | M43: BI12 | N43: N/A | O43: N/A | P43: N/A | Q43: N/A | R43: N/A | S43: 0 | T43: 30000-50000 | U43: 0 | V43: 80-120 | W43: 0 | X43: 0 | Y43: 0 | Z43: 0 | AA43: 0 | AB43: 0 | AC43: 0 | AD43: 0 | AE43: 0 | AF43: 0 | AG43: 0 | AH43: 0 | AI43: 0 | AJ43: 0 | AK43: 0 | AL43: 0 | AM43: 0 | AN43: Yes
A44: LV43 | B44: Temple and Shrine Heritage Act | C44: 5994 | D44: 1 | E44: 100 | F44: 80 | G44: 60 | H44: 40 | I44: ST174 | J44: ST175 | K44: ST176 | L44: ST177 | M44: ST178 | N44: ST179 | O44: BI13 | P44: N/A | Q44: N/A | R44: N/A | S44: 0 | T44: 30000-50000 | U44: 0 | V44: 80-120 | W44: 0 | X44: 0 | Y44: 0 | Z44: 0 | AA44: 0 | AB44: 0 | AC44: 0 | AD44: 0 | AE44: 0 | AF44: 0 | AG44: 0 | AH44: 0 | AI44: 0 | AJ44: 0 | AK44: 0 | AL44: 0 | AM44: 0 | AN44: Yes | AR44: 0-1 | AS44: 0-1 | BG44: Yes
A45: LV44 | B45: Constituency Development Grants Act | C45: 5994 | D45: 1 | E45: 100 | F45: 80 | G45: 60 | H45: 40 | I45: ST180 | J45: ST181 | K45: ST182 | L45: ST183 | M45: ST184 | N45: ST185 | O45: BI14 | P45: N/A | Q45: N/A | R45: N/A | S45: 0 | T45: 30000-50000 | U45: 0 | V45: 80-120 | W45: 0 | X45: 0 | Y45: 0 | Z45: 0 | AA45: 0 | AB45: 0 | AC45: 0 | AD45: 0 | AE45: 0 | AF45: 0 | AG45: 0 | AH45: 0 | AI45: 0 | AJ45: 0 | AK45: 0 | AL45: 0 | AM45: 0 | AN45: Yes | AP45: 0-1 | AQ45: 0-1
A46: LV45 | B46: Digital Economy Promotion Act | C46: 5994 | D46: 1 | E46: 100 | F46: 80 | G46: 60 | H46: 40 | I46: ST186 | J46: ST187 | K46: ST188 | L46: ST189 | M46: ST190 | N46: ST191 | O46: ST192 | P46: BI15 | Q46: N/A | R46: N/A | S46: 0 | T46: 30000-50000 | U46: 0 | V46: 80-120 | W46: 0 | X46: 0 | Y46: 0 | Z46: 0 | AA46: 0 | AB46: 0 | AC46: 0 | AD46: 0 | AE46: 0 | AF46: 0 | AG46: 0 | AH46: 0 | AI46: 0 | AJ46: 0 | AK46: 0 | AL46: 0 | AM46: 0 | AN46: Yes | BG46: Yes
A47: LV46 | B47: Organized Crime Conspiracy Act | C47: 5994 | D47: 1 | E47: 100 | F47: 80 | G47: 60 | H47: 40 | I47: ST193 | J47: ST194 | K47: ST195 | L47: ST196 | M47: ST197 | N47: BI16 | O47: N/A | P47: N/A | Q47: N/A | R47: N/A | S47: 0 | T47: 30000-50000 | U47: 0 | V47: 80-120 | W47: 0 | X47: 0 | Y47: 0 | Z47: 0 | AA47: 0 | AB47: 0 | AC47: 0 | AD47: 0 | AE47: 0 | AF47: 0 | AG47: 0 | AH47: 0 | AI47: 0 | AJ47: 0 | AK47: 0 | AL47: 0 | AM47: 0 | AN47: Yes | AU47: 0-1
A48: LV47 | B48: Partnership Registration Act | C48: 5994 | D48: 1 | E48: 100 | F48: 80 | G48: 60 | H48: 40 | I48: ST198 | J48: ST199 | K48: ST200 | L48: BI17 | M48: N/A | N48: N/A | O48: N/A | P48: N/A | Q48: N/A | R48: N/A | S48: 0 | T48: 30000-50000 | U48: 0 | V48: 80-120 | W48: 0 | X48: 0 | Y48: 0 | Z48: 0 | AA48: 0 | AB48: 0 | AC48: 0 | AD48: 0 | AE48: 0 | AF48: 0 | AG48: 0 | AH48: 0 | AI48: 0 | AJ48: 0 | AK48: 0 | AL48: 0 | AM48: 0 | AN48: Yes | BG48: Yes | BH48: BO27
A49: LV48 | B49: National Emergency Powers Act | C49: 5994 | D49: 1 | E49: 100 | F49: 80 | G49: 60 | H49: 40 | I49: ST201 | J49: ST202 | K49: ST203 | L49: ST204 | M49: ST205 | N49: ST206 | O49: ST207 | P49: BI18 | Q49: N/A | R49: N/A | S49: 0 | T49: 30000-50000 | U49: 0 | V49: 80-120 | W49: 0 | X49: 0 | Y49: 0 | Z49: 0 | AA49: 0 | AB49: 0 | AC49: 0 | AD49: 0 | AE49: 0 | AF49: 0 | AG49: 0 | AH49: 0 | AI49: 0 | AJ49: 0 | AK49: 0 | AL49: 0 | AM49: 0 | AN49: Yes | AU49: 0-1 | AZ49: 0-1
A50: LV49 | B50: Yezo–US Security Consultation Agreement | C50: 5994 | D50: 2 | E50: 200 | F50: 150 | G50: 100 | H50: 50 | I50: ST208 | J50: ST209 | K50: ST210 | L50: ST211 | M50: ST212 | N50: BI19 | O50: N/A | P50: N/A | Q50: N/A | R50: N/A | S50: 0 | T50: 80000-120000 | U50: 0 | V50: 200-300 | W50: 0 | X50: 0 | Y50: 0 | Z50: 0 | AA50: 0 | AB50: 0 | AC50: 0 | AD50: 0 | AE50: 0 | AF50: 0 | AG50: 0 | AH50: 0 | AI50: 0 | AJ50: 0 | AK50: 0 | AL50: 0 | AM50: 0 | AN50: Yes | AU50: 0-1 | BG50: Yes
A51: LV50 | B51: Yezo–EU Economic Partnership Agreement | C51: 5994 | D51: 2 | E51: 200 | F51: 150 | G51: 100 | H51: 50 | I51: ST213 | J51: ST214 | K51: ST215 | L51: ST216 | M51: ST217 | N51: BI20 | O51: N/A | P51: N/A | Q51: N/A | R51: N/A | S51: 0 | T51: 80000-120000 | U51: 0 | V51: 200-300 | W51: 0 | X51: 0 | Y51: 0 | Z51: 0 | AA51: 0 | AB51: 0 | AC51: 0 | AD51: 0 | AE51: 0 | AF51: 0 | AG51: 0 | AH51: 0 | AI51: 0 | AJ51: 0 | AK51: 0 | AL51: 0 | AM51: 0 | AN51: Yes
A52: LV51 | B52: Strategic Land and Port Screening Act | C52: 5994 | D52: 2 | E52: 200 | F52: 150 | G52: 100 | H52: 50 | I52: ST218 | J52: ST219 | K52: ST220 | L52: ST221 | M52: ST222 | N52: BI21 | O52: N/A | P52: N/A | Q52: N/A | R52: N/A | S52: 0 | T52: 80000-120000 | U52: 0 | V52: 200-300 | W52: 0 | X52: 0 | Y52: 0 | Z52: 0 | AA52: 0 | AB52: 0 | AC52: 0 | AD52: 0 | AE52: 0 | AF52: 0 | AG52: 0 | AH52: 0 | AI52: 0 | AJ52: 0 | AK52: 0 | AL52: 0 | AM52: 0 | AN52: Yes | AU52: 0-1
A53: LV52 | B53: Inbound Tourism Visa Waiver Act | C53: 5994 | D53: 2 | E53: 200 | F53: 150 | G53: 100 | H53: 50 | I53: ST223 | J53: ST224 | K53: ST225 | L53: ST226 | M53: BI22 | N53: N/A | O53: N/A | P53: N/A | Q53: N/A | R53: N/A | S53: 0 | T53: 80000-120000 | U53: 0 | V53: 200-300 | W53: 0 | X53: 0 | Y53: 0 | Z53: 0 | AA53: 0 | AB53: 0 | AC53: 0 | AD53: 0 | AE53: 0 | AF53: 0 | AG53: 0 | AH53: 0 | AI53: 0 | AJ53: 0 | AK53: 0 | AL53: 0 | AM53: 0 | AN53: Yes | AX53: 0-1 | BG53: Yes
A54: LV53 | B54: Chishima Joint Economic Activity Act | C54: 5994 | D54: 1 | E54: 100 | F54: 80 | G54: 60 | H54: 40 | I54: ST227 | J54: ST228 | K54: ST229 | L54: BI23 | M54: N/A | N54: N/A | O54: N/A | P54: N/A | Q54: N/A | R54: N/A | S54: 0 | T54: 30000-50000 | U54: 0 | V54: 80-120 | W54: 0 | X54: 0 | Y54: 0 | Z54: 0 | AA54: 0 | AB54: 0 | AC54: 0 | AD54: 0 | AE54: 0 | AF54: 0 | AG54: 0 | AH54: 0 | AI54: 0 | AJ54: 0 | AK54: 0 | AL54: 0 | AM54: 0 | AN54: Yes
A55: LV54 | B55: Tomari Nuclear Restart Act | C55: 5994 | D55: 2 | E55: 200 | F55: 150 | G55: 100 | H55: 50 | I55: ST230 | J55: ST231 | K55: ST232 | L55: BI24 | M55: N/A | N55: N/A | O55: N/A | P55: N/A | Q55: N/A | R55: N/A | S55: 0 | T55: 80000-120000 | U55: 0 | V55: 200-300 | W55: 0 | X55: 0 | Y55: 0 | Z55: 0 | AA55: 0 | AB55: 0 | AC55: 0 | AD55: 0 | AE55: 0 | AF55: 0 | AG55: 0 | AH55: 0 | AI55: 0 | AJ55: 0 | AK55: 0 | AL55: 0 | AM55: 0 | AN55: Yes
A56: LV55 | B56: Integrated Resort Act | C56: 5994 | D56: 2 | E56: 200 | F56: 150 | G56: 100 | H56: 50 | I56: ST233 | J56: ST234 | K56: ST235 | L56: ST236 | M56: ST233 | N56: ST237 | O56: ST238 | P56: BI25 | Q56: N/A | R56: N/A | S56: 0 | T56: 80000-120000 | U56: 0 | V56: 200-300 | W56: 0 | X56: 0 | Y56: 0 | Z56: 0 | AA56: 0 | AB56: 0 | AC56: 0 | AD56: 0 | AE56: 0 | AF56: 0 | AG56: 0 | AH56: 0 | AI56: 0 | AJ56: 0 | AK56: 0 | AL56: 0 | AM56: 0 | AN56: Yes | BG56: Yes | BH56: BO05
A57: LV56 | B57: Civil Service Merit Act | C57: 5994 | D57: 2 | E57: 200 | F57: 150 | G57: 100 | H57: 50 | I57: ST239 | J57: ST240 | K57: ST241 | L57: ST242 | M57: BI26 | N57: N/A | O57: N/A | P57: N/A | Q57: N/A | R57: N/A | S57: 0 | T57: 80000-120000 | U57: 0 | V57: 200-300 | W57: 0 | X57: 0 | Y57: 0 | Z57: 0 | AA57: 0 | AB57: 0 | AC57: 0 | AD57: 0 | AE57: 0 | AF57: 0 | AG57: 0 | AH57: 0 | AI57: 0 | AJ57: 0 | AK57: 0 | AL57: 0 | AM57: 0 | AN57: Yes | AV57: 0-1 | AY57: 0-1
A58: LV57 | B58: Regional Minimum Wage Act | C58: 5994 | D58: 2 | E58: 200 | F58: 150 | G58: 100 | H58: 50 | I58: ST243 | J58: ST244 | K58: ST245 | L58: ST246 | M58: ST247 | N58: ST248 | O58: BI27 | P58: N/A | Q58: N/A | R58: N/A | S58: 0 | T58: 80000-120000 | U58: 0 | V58: 200-300 | W58: 0 | X58: 0 | Y58: 0 | Z58: 0 | AA58: 0 | AB58: 0 | AC58: 0 | AD58: 0 | AE58: 0 | AF58: 0 | AG58: 0 | AH58: 0 | AI58: 0 | AJ58: 0 | AK58: 0 | AL58: 0 | AM58: 0 | AN58: Yes | BG58: Yes
A59: LV58 | B59: Independent Election Commission Act | C59: 5994 | D59: 2 | E59: 200 | F59: 150 | G59: 100 | H59: 50 | I59: ST249 | J59: ST250 | K59: ST251 | L59: ST252 | M59: BI28 | N59: N/A | O59: N/A | P59: N/A | Q59: N/A | R59: N/A | S59: 0 | T59: 80000-120000 | U59: 0 | V59: 200-300 | W59: 0 | X59: 0 | Y59: 0 | Z59: 0 | AA59: 0 | AB59: 0 | AC59: 0 | AD59: 0 | AE59: 0 | AF59: 0 | AG59: 0 | AH59: 0 | AI59: 0 | AJ59: 0 | AK59: 0 | AL59: 0 | AM59: 0 | AN59: Yes | AY59: 0-1
A60: LV59 | B60: Moral Education Curriculum Act | C60: 5994 | D60: 2 | E60: 200 | F60: 150 | G60: 100 | H60: 50 | I60: ST253 | J60: ST254 | K60: ST255 | L60: ST256 | M60: BI29 | N60: N/A | O60: N/A | P60: N/A | Q60: N/A | R60: N/A | S60: 0 | T60: 80000-120000 | U60: 0 | V60: 200-300 | W60: 0 | X60: 0 | Y60: 0 | Z60: 0 | AA60: 0 | AB60: 0 | AC60: 0 | AD60: 0 | AE60: 0 | AF60: 0 | AG60: 0 | AH60: 0 | AI60: 0 | AJ60: 0 | AK60: 0 | AL60: 0 | AM60: 0 | AN60: Yes | BG60: Yes
A61: LV60 | B61: Foreign Resident Local Suffrage Act | C61: 5994 | D61: 2 | E61: 200 | F61: 150 | G61: 100 | H61: 50 | I61: ST257 | J61: ST258 | K61: ST259 | L61: BI30 | M61: N/A | N61: N/A | O61: N/A | P61: N/A | Q61: N/A | R61: N/A | S61: 0 | T61: 80000-120000 | U61: 0 | V61: 200-300 | W61: 0 | X61: 0 | Y61: 0 | Z61: 0 | AA61: 0 | AB61: 0 | AC61: 0 | AD61: 0 | AE61: 0 | AF61: 0 | AG61: 0 | AH61: 0 | AI61: 0 | AJ61: 0 | AK61: 0 | AL61: 0 | AM61: 0 | AN61: Yes | AY61: 0-1 | AZ61: 0-1 | BG61: Yes
A62: LV61 | B62: Rail Fares and Timetables | C62: 144 | D62: 1 | E62: 150 | F62: 100 | G62: 50 | H62: 10 | I62: ST07 | J62: ST24 | K62: ST25 | L62: ST26 | M62: ST27 | N62: N/A | O62: N/A | P62: N/A | Q62: N/A | R62: N/A | S62: 0-2 | T62: 6000-20000 | U62: 1-3 | V62: 25-40 | W62: 2-6% | X62: 0 | Y62: 0 | Z62: 0 | AA62: 0 | AB62: 0 | AC62: 0 | AD62: 0 | AE62: 0 | AF62: 0 | AG62: 0 | AH62: 0 | AI62: 0 | AJ62: 0 | AK62: 1-2 | AL62: 0 | AM62: 0 | AN62: No
A63: LV62 | B63: Fishing Quotas and Harbors | C63: 144 | D63: 1 | E63: 150 | F63: 100 | G63: 50 | H63: 10 | I63: ST07 | J63: ST28 | K63: ST29 | L63: ST30 | M63: ST31 | N63: N/A | O63: N/A | P63: N/A | Q63: N/A | R63: N/A | S63: 0-2 | T63: 6000-20000 | U63: 1-3 | V63: 25-40 | W63: 2-6% | X63: 0 | Y63: 0 | Z63: 0 | AA63: 0 | AB63: 0 | AC63: 0 | AD63: 1-2 | AE63: 0 | AF63: 0 | AG63: 0 | AH63: 0 | AI63: 0 | AJ63: 0 | AK63: 0 | AL63: 0 | AM63: 0 | AN63: No
A64: LV63 | B64: Wilderness and Wildlife Protection Act | C64: 5994 | D64: 1 | E64: 100 | F64: 80 | G64: 60 | H64: 40 | I64: ST101 | J64: ST32 | K64: ST33 | L64: ST34 | M64: ST35 | N64: BI31 | O64: N/A | P64: N/A | Q64: N/A | R64: N/A | S64: 0 | T64: 30000-50000 | U64: 0 | V64: 80-120 | W64: 0 | X64: 0 | Y64: 0 | Z64: 0 | AA64: 0 | AB64: 0 | AC64: 0 | AD64: 0 | AE64: 0 | AF64: 0 | AG64: 0 | AH64: 0 | AI64: 0 | AJ64: 0 | AK64: 0 | AL64: 0 | AM64: 0 | AN64: Yes | AS64: 0-1 | BA64: 0-1
A65: LV64 | B65: Rural Hospital Network Act | C65: 5994 | D65: 2 | E65: 200 | F65: 150 | G65: 100 | H65: 50 | I65: ST102 | J65: ST36 | K65: ST37 | L65: ST38 | M65: ST39 | N65: BI32 | O65: N/A | P65: N/A | Q65: N/A | R65: N/A | S65: 0 | T65: 80000-120000 | U65: 0 | V65: 200-300 | W65: 0 | X65: 0 | Y65: 0 | Z65: 0 | AA65: 0 | AB65: 0 | AC65: 0 | AD65: 0 | AE65: 0 | AF65: 0 | AG65: 0 | AH65: 0 | AI65: 0 | AJ65: 0 | AK65: 0 | AL65: 0 | AM65: 0 | AN65: Yes | AT65: 0-1 | BC65: 0-1 | BG65: Yes
A66: LV65 | B66: Digital Identity Card Act | C66: 5994 | D66: 1 | E66: 100 | F66: 80 | G66: 60 | H66: 40 | I66: ST103 | J66: ST40 | K66: ST41 | L66: ST42 | M66: BI33 | N66: N/A | O66: N/A | P66: N/A | Q66: N/A | R66: N/A | S66: 0 | T66: 30000-50000 | U66: 0 | V66: 80-120 | W66: 0 | X66: 0 | Y66: 0 | Z66: 0 | AA66: 0 | AB66: 0 | AC66: 0 | AD66: 0 | AE66: 0 | AF66: 0 | AG66: 0 | AH66: 0 | AI66: 0 | AJ66: 0 | AK66: 0 | AL66: 0 | AM66: 0 | AN66: Yes | BG66: Yes | BH66: BO24
A67: LV66 | B67: Public Broadcasting Independence Act | C67: 5994 | D67: 1 | E67: 100 | F67: 80 | G67: 60 | H67: 40 | I67: ST104 | J67: ST43 | K67: ST44 | L67: ST45 | M67: BI34 | N67: N/A | O67: N/A | P67: N/A | Q67: N/A | R67: N/A | S67: 0 | T67: 30000-50000 | U67: 0 | V67: 80-120 | W67: 0 | X67: 0 | Y67: 0 | Z67: 0 | AA67: 0 | AB67: 0 | AC67: 0 | AD67: 0 | AE67: 0 | AF67: 0 | AG67: 0 | AH67: 0 | AI67: 0 | AJ67: 0 | AK67: 0 | AL67: 0 | AM67: 0 | AN67: Yes
A68: LV67 | B68: Political Donation Transparency Act | C68: 5994 | D68: 2 | E68: 200 | F68: 150 | G68: 100 | H68: 50 | I68: ST105 | J68: ST46 | K68: ST47 | L68: ST48 | M68: ST49 | N68: BI35 | O68: N/A | P68: N/A | Q68: N/A | R68: N/A | S68: 0 | T68: 80000-120000 | U68: 0 | V68: 200-300 | W68: 0 | X68: 0 | Y68: 0 | Z68: 0 | AA68: 0 | AB68: 0 | AC68: 0 | AD68: 0 | AE68: 0 | AF68: 0 | AG68: 0 | AH68: 0 | AI68: 0 | AJ68: 0 | AK68: 0 | AL68: 0 | AM68: 0 | AN68: Yes | AV68: 0-1 | AY68: 0-1
A69: LV68 | B69: Corporate Tax Reduction Act | C69: 5994 | D69: 2 | E69: 200 | F69: 150 | G69: 100 | H69: 50 | I69: ST106 | J69: ST50 | K69: ST51 | L69: ST52 | M69: BI36 | N69: N/A | O69: N/A | P69: N/A | Q69: N/A | R69: N/A | S69: 0 | T69: 80000-120000 | U69: 0 | V69: 200-300 | W69: 0 | X69: 0 | Y69: 0 | Z69: 0 | AA69: 0 | AB69: 0 | AC69: 0 | AD69: 0 | AE69: 0 | AF69: 0 | AG69: 0 | AH69: 0 | AI69: 0 | AJ69: 0 | AK69: 0 | AL69: 0 | AM69: 0 | AN69: Yes | AV69: 0-1 | AW69: 0-1
A70: LV69 | B70: Carbon Levy Act | C70: 5994 | D70: 2 | E70: 200 | F70: 150 | G70: 100 | H70: 50 | I70: ST107 | J70: ST53 | K70: ST54 | L70: ST55 | M70: ST56 | N70: BI37 | O70: N/A | P70: N/A | Q70: N/A | R70: N/A | S70: 0 | T70: 80000-120000 | U70: 0 | V70: 200-300 | W70: 0 | X70: 0 | Y70: 0 | Z70: 0 | AA70: 0 | AB70: 0 | AC70: 0 | AD70: 0 | AE70: 0 | AF70: 0 | AG70: 0 | AH70: 0 | AI70: 0 | AJ70: 0 | AK70: 0 | AL70: 0 | AM70: 0 | AN70: Yes | BG70: Yes | BH70: BO16
A71: LV70 | B71: Fisheries Quota Modernization Act | C71: 5994 | D71: 1 | E71: 100 | F71: 80 | G71: 60 | H71: 40 | I71: ST108 | J71: ST57 | K71: ST58 | L71: ST59 | M71: BI38 | N71: N/A | O71: N/A | P71: N/A | Q71: N/A | R71: N/A | S71: 0 | T71: 30000-50000 | U71: 0 | V71: 80-120 | W71: 0 | X71: 0 | Y71: 0 | Z71: 0 | AA71: 0 | AB71: 0 | AC71: 0 | AD71: 0 | AE71: 0 | AF71: 0 | AG71: 0 | AH71: 0 | AI71: 0 | AJ71: 0 | AK71: 0 | AL71: 0 | AM71: 0 | AN71: Yes | BG71: Yes | BH71: BO07
A72: LV71 | B72: Shipbuilding and Defense Industry Act | C72: 5994 | D72: 2 | E72: 200 | F72: 150 | G72: 100 | H72: 50 | I72: ST109 | J72: ST60 | K72: ST61 | L72: ST62 | M72: BI39 | N72: N/A | O72: N/A | P72: N/A | Q72: N/A | R72: N/A | S72: 0 | T72: 80000-120000 | U72: 0 | V72: 200-300 | W72: 0 | X72: 0 | Y72: 0 | Z72: 0 | AA72: 0 | AB72: 0 | AC72: 0 | AD72: 0 | AE72: 0 | AF72: 0 | AG72: 0 | AH72: 0 | AI72: 0 | AJ72: 0 | AK72: 0 | AL72: 0 | AM72: 0 | AN72: Yes | AU72: 0-1
A73: LV72 | B73: Constitutional Review Commission Act | C73: 5994 | D73: 1 | E73: 100 | F73: 80 | G73: 60 | H73: 40 | I73: ST110 | J73: ST63 | K73: ST64 | L73: ST65 | M73: BI40 | N73: N/A | O73: N/A | P73: N/A | Q73: N/A | R73: N/A | S73: 0 | T73: 30000-50000 | U73: 0 | V73: 80-120 | W73: 0 | X73: 0 | Y73: 0 | Z73: 0 | AA73: 0 | AB73: 0 | AC73: 0 | AD73: 0 | AE73: 0 | AF73: 0 | AG73: 0 | AH73: 0 | AI73: 0 | AJ73: 0 | AK73: 0 | AL73: 0 | AM73: 0 | AN73: Yes | AP73: 0-1
A74: LV73 | B74: Japan Customs and Border Cooperation Act | C74: 5994 | D74: 1 | E74: 100 | F74: 80 | G74: 60 | H74: 40 | I74: ST111 | J74: ST66 | K74: ST67 | L74: ST68 | M74: BI41 | N74: N/A | O74: N/A | P74: N/A | Q74: N/A | R74: N/A | S74: 0 | T74: 30000-50000 | U74: 0 | V74: 80-120 | W74: 0 | X74: 0 | Y74: 0 | Z74: 0 | AA74: 0 | AB74: 0 | AC74: 0 | AD74: 0 | AE74: 0 | AF74: 0 | AG74: 0 | AH74: 0 | AI74: 0 | AJ74: 0 | AK74: 0 | AL74: 0 | AM74: 0 | AN74: Yes | AX74: 0-1 | BG74: Yes
A75: LV74 | B75: Chishima Resource Development Agreement Act | C75: 5994 | D75: 1 | E75: 100 | F75: 80 | G75: 60 | H75: 40 | I75: ST112 | J75: ST69 | K75: ST70 | L75: ST71 | M75: ST72 | N75: BI42 | O75: N/A | P75: N/A | Q75: N/A | R75: N/A | S75: 0 | T75: 30000-50000 | U75: 0 | V75: 80-120 | W75: 0 | X75: 0 | Y75: 0 | Z75: 0 | AA75: 0 | AB75: 0 | AC75: 0 | AD75: 0 | AE75: 0 | AF75: 0 | AG75: 0 | AH75: 0 | AI75: 0 | AJ75: 0 | AK75: 0 | AL75: 0 | AM75: 0 | AN75: Yes
A76: LV75 | B76: Yezo–China Trade Normalization Act | C76: 5994 | D76: 2 | E76: 200 | F76: 150 | G76: 100 | H76: 50 | I76: ST113 | J76: ST73 | K76: ST74 | L76: ST75 | M76: BI43 | N76: N/A | O76: N/A | P76: N/A | Q76: N/A | R76: N/A | S76: 0 | T76: 80000-120000 | U76: 0 | V76: 200-300 | W76: 0 | X76: 0 | Y76: 0 | Z76: 0 | AA76: 0 | AB76: 0 | AC76: 0 | AD76: 0 | AE76: 0 | AF76: 0 | AG76: 0 | AH76: 0 | AI76: 0 | AJ76: 0 | AK76: 0 | AL76: 0 | AM76: 0 | AN76: Yes | BG76: Yes | BH76: BO05
A77: LV76 | B77: Farm Succession Support Act | C77: 5994 | D77: 1 | E77: 100 | F77: 80 | G77: 60 | H77: 40 | I77: ST114 | J77: ST76 | K77: ST77 | L77: ST78 | M77: BI44 | N77: N/A | O77: N/A | P77: N/A | Q77: N/A | R77: N/A | S77: 0 | T77: 30000-50000 | U77: 0 | V77: 80-120 | W77: 0 | X77: 0 | Y77: 0 | Z77: 0 | AA77: 0 | AB77: 0 | AC77: 0 | AD77: 0 | AE77: 0 | AF77: 0 | AG77: 0 | AH77: 0 | AI77: 0 | AJ77: 0 | AK77: 0 | AL77: 0 | AM77: 0 | AN77: Yes | BG77: Yes | BH77: BO10
A78: LV77 | B78: University Autonomy and Research Funding Act | C78: 5994 | D78: 1 | E78: 100 | F78: 80 | G78: 60 | H78: 40 | I78: ST115 | J78: ST79 | K78: ST80 | L78: ST81 | M78: BI45 | N78: N/A | O78: N/A | P78: N/A | Q78: N/A | R78: N/A | S78: 0 | T78: 30000-50000 | U78: 0 | V78: 80-120 | W78: 0 | X78: 0 | Y78: 0 | Z78: 0 | AA78: 0 | AB78: 0 | AC78: 0 | AD78: 0 | AE78: 0 | AF78: 0 | AG78: 0 | AH78: 0 | AI78: 0 | AJ78: 0 | AK78: 0 | AL78: 0 | AM78: 0 | AN78: Yes
A79: LV78 | B79: Workplace Equality Act | C79: 5994 | D79: 2 | E79: 200 | F79: 150 | G79: 100 | H79: 50 | I79: ST116 | J79: ST82 | K79: ST83 | L79: ST84 | M79: ST85 | N79: BI46 | O79: N/A | P79: N/A | Q79: N/A | R79: N/A | S79: 0 | T79: 80000-120000 | U79: 0 | V79: 200-300 | W79: 0 | X79: 0 | Y79: 0 | Z79: 0 | AA79: 0 | AB79: 0 | AC79: 0 | AD79: 0 | AE79: 0 | AF79: 0 | AG79: 0 | AH79: 0 | AI79: 0 | AJ79: 0 | AK79: 0 | AL79: 0 | AM79: 0 | AN79: Yes
A80: LV79 | B80: Parental Leave and Childcare Act | C80: 5994 | D80: 1 | E80: 100 | F80: 80 | G80: 60 | H80: 40 | I80: ST117 | J80: ST86 | K80: ST87 | L80: ST88 | M80: ST89 | N80: BI47 | O80: N/A | P80: N/A | Q80: N/A | R80: N/A | S80: 0 | T80: 30000-50000 | U80: 0 | V80: 80-120 | W80: 0 | X80: 0 | Y80: 0 | Z80: 0 | AA80: 0 | AB80: 0 | AC80: 0 | AD80: 0 | AE80: 0 | AF80: 0 | AG80: 0 | AH80: 0 | AI80: 0 | AJ80: 0 | AK80: 0 | AL80: 0 | AM80: 0 | AN80: Yes | BG80: Yes | BH80: BO12
A81: LV80 | B81: Public Safety Surveillance Act | C81: 5994 | D81: 2 | E81: 200 | F81: 150 | G81: 100 | H81: 50 | I81: ST118 | J81: ST90 | K81: ST91 | L81: ST92 | M81: ST93 | N81: BI48 | O81: N/A | P81: N/A | Q81: N/A | R81: N/A | S81: 0 | T81: 80000-120000 | U81: 0 | V81: 200-300 | W81: 0 | X81: 0 | Y81: 0 | Z81: 0 | AA81: 0 | AB81: 0 | AC81: 0 | AD81: 0 | AE81: 0 | AF81: 0 | AG81: 0 | AH81: 0 | AI81: 0 | AJ81: 0 | AK81: 0 | AL81: 0 | AM81: 0 | AN81: Yes | AU81: 0-1 | AZ81: 0-1
A82: LV81 | B82: Local Government Mergers Act | C82: 5994 | D82: 1 | E82: 100 | F82: 80 | G82: 60 | H82: 40 | I82: ST119 | J82: ST94 | K82: ST95 | L82: ST96 | M82: ST97 | N82: BI49 | O82: N/A | P82: N/A | Q82: N/A | R82: N/A | S82: 0 | T82: 30000-50000 | U82: 0 | V82: 80-120 | W82: 0 | X82: 0 | Y82: 0 | Z82: 0 | AA82: 0 | AB82: 0 | AC82: 0 | AD82: 0 | AE82: 0 | AF82: 0 | AG82: 0 | AH82: 0 | AI82: 0 | AJ82: 0 | AK82: 0 | AL82: 0 | AM82: 0 | AN82: Yes | AV82: 0-1 | BG82: Yes | BH82: BO23
A83: LV82 | B83: Party Leadership Selection Act | C83: 5994 | D83: 0 | E83: 50 | F83: 40 | G83: 30 | H83: 0 | I83: ST120 | J83: ST98 | K83: ST99 | L83: ST100 | M83: BI50 | N83: N/A | O83: N/A | P83: N/A | Q83: N/A | R83: N/A | S83: 0 | T83: 0 | U83: 0 | V83: 0 | W83: 0 | X83: 0 | Y83: 0 | Z83: 0 | AA83: 0 | AB83: 0 | AC83: 0 | AD83: 0 | AE83: 0 | AF83: 0 | AG83: 0 | AH83: 0 | AI83: 0 | AJ83: 0 | AK83: 0 | AL83: 0 | AM83: 0 | AN83: Yes
A84: LV83 | B84: Constituency Town Hall | C84: 0 | D84: 0 | E84: 0 | F84: 0 | G84: 0 | H84: 0 | I84: ST05 | J84: N/A | K84: N/A | L84: N/A | M84: N/A | N84: N/A | O84: N/A | P84: N/A | Q84: N/A | R84: N/A | S84: 0 | T84: 0 | U84: 0 | V84: 0 | W84: 0 | X84: 0 | Y84: 0 | Z84: 0 | AA84: 0 | AB84: 0 | AC84: 0 | AD84: 0 | AE84: 0 | AF84: 0 | AG84: 0 | AH84: 0 | AI84: 0 | AJ84: 0 | AK84: 0 | AL84: 0 | AM84: 0 | AN84: No | AO84: Town Hall | BF84: Yes
A85: LV84 | B85: Party Steering Committee Check-In | C85: 0 | D85: 0 | E85: 0 | F85: 0 | G85: 0 | H85: 0 | I85: ST22 | J85: N/A | K85: N/A | L85: N/A | M85: N/A | N85: N/A | O85: N/A | P85: N/A | Q85: N/A | R85: N/A | S85: 0 | T85: 0 | U85: 0 | V85: 0 | W85: 0 | X85: 0 | Y85: 0 | Z85: 0 | AA85: 0 | AB85: 0 | AC85: 0 | AD85: 0 | AE85: 0 | AF85: 0 | AG85: 0 | AH85: 0 | AI85: 0 | AJ85: 0 | AK85: 0 | AL85: 0 | AM85: 0 | AN85: No | AO85: Steering Committee | BF85: Yes
A86: LV85 | B86: A Quiet Word with a Lobbyist | C86: 16 | D86: 0 | E86: 0 | F86: 0 | G86: 0 | H86: 0 | I86: ST20 | J86: N/A | K86: N/A | L86: N/A | M86: N/A | N86: N/A | O86: N/A | P86: N/A | Q86: N/A | R86: N/A | S86: 0 | T86: 0 | U86: 0 | V86: 0 | W86: 0% | X86: 0 | Y86: 0 | Z86: 0 | AA86: 0 | AB86: 0 | AC86: 0 | AD86: 0 | AE86: 0 | AF86: 0 | AG86: 0 | AH86: 0 | AI86: 0 | AJ86: 0 | AK86: 0 | AL86: 0 | AM86: 0 | AN86: No | BF86: Yes
A87: LV86 | B87: Office Hours | C87: 8 | D87: 0 | E87: 0 | F87: 0 | G87: 0 | H87: 0 | I87: ST07 | J87: N/A | K87: N/A | L87: N/A | M87: N/A | N87: N/A | O87: N/A | P87: N/A | Q87: N/A | R87: N/A | S87: 0 | T87: 0 | U87: 0 | V87: 0 | W87: 0% | X87: 0 | Y87: 0 | Z87: 0 | AA87: 0 | AB87: 0 | AC87: 0 | AD87: 0 | AE87: 0 | AF87: 0 | AG87: 0 | AH87: 0 | AI87: 0 | AJ87: 0 | AK87: 0 | AL87: 0 | AM87: 0 | AN87: No | BF87: Yes
A88: LV87 | B88: Attend a Local Festival | C88: 24 | D88: 0 | E88: 0 | F88: 0 | G88: 0 | H88: 0 | I88: ST264 | J88: N/A | K88: N/A | L88: N/A | M88: N/A | N88: N/A | O88: N/A | P88: N/A | Q88: N/A | R88: N/A | S88: 0 | T88: 0 | U88: 0 | V88: 0 | W88: 0% | X88: 0 | Y88: 0 | Z88: 0 | AA88: 0 | AB88: 0 | AC88: 0 | AD88: 0 | AE88: 0 | AF88: 0 | AG88: 0 | AH88: 0 | AI88: 0 | AJ88: 0 | AK88: 0 | AL88: 0 | AM88: 0 | AN88: No | BF88: Yes
A89: LV88 | B89: A Press Gaggle | C89: 12 | D89: 0 | E89: 0 | F89: 0 | G89: 0 | H89: 0 | I89: ST04 | J89: N/A | K89: N/A | L89: N/A | M89: N/A | N89: N/A | O89: N/A | P89: N/A | Q89: N/A | R89: N/A | S89: 0 | T89: 0 | U89: 0 | V89: 0 | W89: 0% | X89: 0 | Y89: 0 | Z89: 0 | AA89: 0 | AB89: 0 | AC89: 0 | AD89: 0 | AE89: 0 | AF89: 0 | AG89: 0 | AH89: 0 | AI89: 0 | AJ89: 0 | AK89: 0 | AL89: 0 | AM89: 0 | AN89: No | BF89: Yes
A90: LV89 | B90: A Town Hall on Local Issues | C90: 12 | D90: 0 | E90: 0 | F90: 0 | G90: 0 | H90: 0 | I90: ST05 | J90: N/A | K90: N/A | L90: N/A | M90: N/A | N90: N/A | O90: N/A | P90: N/A | Q90: N/A | R90: N/A | S90: 0 | T90: 0 | U90: 0 | V90: 0 | W90: 0% | X90: 0 | Y90: 0 | Z90: 0 | AA90: 0 | AB90: 0 | AC90: 0 | AD90: 0 | AE90: 0 | AF90: 0 | AG90: 0 | AH90: 0 | AI90: 0 | AJ90: 0 | AK90: 0 | AL90: 0 | AM90: 0 | AN90: No | BF90: Yes
A91: LV90 | B91: A Policy Study Evening | C91: 12 | D91: 0 | E91: 0 | F91: 0 | G91: 0 | H91: 0 | I91: ST21 | J91: N/A | K91: N/A | L91: N/A | M91: N/A | N91: N/A | O91: N/A | P91: N/A | Q91: N/A | R91: N/A | S91: 0 | T91: 0 | U91: 0 | V91: 0 | W91: 0% | X91: 0 | Y91: 0 | Z91: 0 | AA91: 0 | AB91: 0 | AC91: 0 | AD91: 0 | AE91: 0 | AF91: 0 | AG91: 0 | AH91: 0 | AI91: 0 | AJ91: 0 | AK91: 0 | AL91: 0 | AM91: 0 | AN91: No | BF91: Yes
A92: LV91 | B92: A Late TV Interview | C92: 16 | D92: 0 | E92: 0 | F92: 0 | G92: 0 | H92: 0 | I92: ST06 | J92: N/A | K92: N/A | L92: N/A | M92: N/A | N92: N/A | O92: N/A | P92: N/A | Q92: N/A | R92: N/A | S92: 0 | T92: 0 | U92: 0 | V92: 0 | W92: 0% | X92: 0 | Y92: 0 | Z92: 0 | AA92: 0 | AB92: 0 | AC92: 0 | AD92: 0 | AE92: 0 | AF92: 0 | AG92: 0 | AH92: 0 | AI92: 0 | AJ92: 0 | AK92: 0 | AL92: 0 | AM92: 0 | AN92: No | BF92: Yes
A93: LV92 | B93: Attend the Autumn Harvest Festival | C93: 24 | D93: 0 | E93: 0 | F93: 0 | G93: 0 | H93: 0 | I93: ST265 | J93: N/A | K93: N/A | L93: N/A | M93: N/A | N93: N/A | O93: N/A | P93: N/A | Q93: N/A | R93: N/A | S93: 0 | T93: 0 | U93: 0 | V93: 0 | W93: 0% | X93: 0 | Y93: 0 | Z93: 0 | AA93: 0 | AB93: 0 | AC93: 0 | AD93: 0 | AE93: 0 | AF93: 0 | AG93: 0 | AH93: 0 | AI93: 0 | AJ93: 0 | AK93: 0 | AL93: 0 | AM93: 0 | AN93: No | BF93: Yes
A94: LV93 | B94: Attend the Winter Snow Festival | C94: 24 | D94: 0 | E94: 0 | F94: 0 | G94: 0 | H94: 0 | I94: ST266 | J94: N/A | K94: N/A | L94: N/A | M94: N/A | N94: N/A | O94: N/A | P94: N/A | Q94: N/A | R94: N/A | S94: 0 | T94: 0 | U94: 0 | V94: 0 | W94: 0% | X94: 0 | Y94: 0 | Z94: 0 | AA94: 0 | AB94: 0 | AC94: 0 | AD94: 0 | AE94: 0 | AF94: 0 | AG94: 0 | AH94: 0 | AI94: 0 | AJ94: 0 | AK94: 0 | AL94: 0 | AM94: 0 | AN94: No | BF94: Yes
A95: LV94 | B95: Constituency Walkabout | C95: 8 | D95: 0 | E95: 0 | F95: 0 | G95: 0 | H95: 0 | I95: ST267 | J95: N/A | K95: N/A | L95: N/A | M95: N/A | N95: N/A | O95: N/A | P95: N/A | Q95: N/A | R95: N/A | S95: 0 | T95: 0 | U95: 0 | V95: 0 | W95: 0% | X95: 0 | Y95: 0 | Z95: 0 | AA95: 0 | AB95: 0 | AC95: 0 | AD95: 0 | AE95: 0 | AF95: 0 | AG95: 0 | AH95: 0 | AI95: 0 | AJ95: 0 | AK95: 0 | AL95: 0 | AM95: 0 | AN95: No | BF95: Yes
A96: LV95 | B96: Community Clinic Day | C96: 16 | D96: 0 | E96: 0 | F96: 0 | G96: 0 | H96: 0 | I96: ST268 | J96: N/A | K96: N/A | L96: N/A | M96: N/A | N96: N/A | O96: N/A | P96: N/A | Q96: N/A | R96: N/A | S96: 0 | T96: 0 | U96: 0 | V96: 0 | W96: 0% | X96: 0 | Y96: 0 | Z96: 0 | AA96: 0 | AB96: 0 | AC96: 0 | AD96: 0 | AE96: 0 | AF96: 0 | AG96: 0 | AH96: 0 | AI96: 0 | AJ96: 0 | AK96: 0 | AL96: 0 | AM96: 0 | AN96: No | BF96: Yes
A97: LV96 | B97: School Visit | C97: 12 | D97: 0 | E97: 0 | F97: 0 | G97: 0 | H97: 0 | I97: ST269 | J97: N/A | K97: N/A | L97: N/A | M97: N/A | N97: N/A | O97: N/A | P97: N/A | Q97: N/A | R97: N/A | S97: 0 | T97: 0 | U97: 0 | V97: 0 | W97: 0% | X97: 0 | Y97: 0 | Z97: 0 | AA97: 0 | AB97: 0 | AC97: 0 | AD97: 0 | AE97: 0 | AF97: 0 | AG97: 0 | AH97: 0 | AI97: 0 | AJ97: 0 | AK97: 0 | AL97: 0 | AM97: 0 | AN97: No | BF97: Yes
A98: LV97 | B98: Farmers' Market Stall | C98: 24 | D98: 0 | E98: 0 | F98: 0 | G98: 0 | H98: 0 | I98: ST270 | J98: N/A | K98: N/A | L98: N/A | M98: N/A | N98: N/A | O98: N/A | P98: N/A | Q98: N/A | R98: N/A | S98: 0 | T98: 0 | U98: 0 | V98: 0 | W98: 0% | X98: 0 | Y98: 0 | Z98: 0 | AA98: 0 | AB98: 0 | AC98: 0 | AD98: 0 | AE98: 0 | AF98: 0 | AG98: 0 | AH98: 0 | AI98: 0 | AJ98: 0 | AK98: 0 | AL98: 0 | AM98: 0 | AN98: No | BF98: Yes

Sheet Affinity
A1: Element | B1: ST01 | C1: ST02 | D1: ST03 | E1: ST04 | F1: ST05 | G1: ST06 | H1: ST07 | I1: ST08 | J1: ST09 | K1: ST10 | L1: ST11 | M1: ST12 | N1: ST13 | O1: ST14 | P1: ST15 | Q1: ST16 | R1: ST17 | S1: ST18 | T1: ST19 | U1: ST20 | V1: ST21 | W1: ST24 | X1: ST25 | Y1: ST26 | Z1: ST27 | AA1: ST28 | AB1: ST29 | AC1: ST30 | AD1: ST31 | AE1: ST32 | AF1: ST33 | AG1: ST34 | AH1: ST35 | AI1: ST36 | AJ1: ST37 | AK1: ST38 | AL1: ST39 | AM1: ST40 | AN1: ST41 | AO1: ST42 | AP1: ST43 | AQ1: ST44 | AR1: ST45 | AS1: ST46 | AT1: ST47 | AU1: ST48 | AV1: ST49 | AW1: ST50 | AX1: ST51 | AY1: ST52 | AZ1: ST53 | BA1: ST54 | BB1: ST55 | BC1: ST56 | BD1: ST57 | BE1: ST58 | BF1: ST59 | BG1: ST60 | BH1: ST61 | BI1: ST62 | BJ1: ST63 | BK1: ST64 | BL1: ST65 | BM1: ST66 | BN1: ST67 | BO1: ST68 | BP1: ST69 | BQ1: ST70 | BR1: ST71 | BS1: ST72 | BT1: ST73 | BU1: ST74 | BV1: ST75 | BW1: ST76 | BX1: ST77 | BY1: ST78 | BZ1: ST79 | CA1: ST80 | CB1: ST81 | CC1: ST82 | CD1: ST83 | CE1: ST84 | CF1: ST85 | CG1: ST86 | CH1: ST87 | CI1: ST88 | CJ1: ST89 | CK1: ST90 | CL1: ST91 | CM1: ST92 | CN1: ST93 | CO1: ST94 | CP1: ST95 | CQ1: ST96 | CR1: ST97 | CS1: ST98 | CT1: ST99 | CU1: ST100 | CV1: ST101 | CW1: ST102 | CX1: ST103 | CY1: ST104 | CZ1: ST105 | DA1: ST106 | DB1: ST107 | DC1: ST108 | DD1: ST109 | DE1: ST110 | DF1: ST111 | DG1: ST112 | DH1: ST113 | DI1: ST114 | DJ1: ST115 | DK1: ST116 | DL1: ST117 | DM1: ST118 | DN1: ST119 | DO1: ST120 | DP1: ST121 | DQ1: ST122 | DR1: ST123 | DS1: ST124 | DT1: ST125 | DU1: ST126 | DV1: ST127 | DW1: ST128 | DX1: ST129 | DY1: ST130 | DZ1: ST131 | EA1: ST132 | EB1: ST133 | EC1: ST134 | ED1: ST135 | EE1: ST136 | EF1: ST137 | EG1: ST138 | EH1: ST139 | EI1: ST140 | EJ1: ST141 | EK1: ST142 | EL1: ST143 | EM1: ST144 | EN1: ST145 | EO1: ST146 | EP1: ST147 | EQ1: ST148 | ER1: ST149 | ES1: ST150 | ET1: ST151 | EU1: ST152 | EV1: ST153 | EW1: ST154 | EX1: ST155 | EY1: ST156 | EZ1: ST157 | FA1: ST158 | FB1: ST159 | FC1: ST160 | FD1: ST161 | FE1: ST162 | FF1: ST163 | FG1: ST164 | FH1: ST165 | FI1: ST166 | FJ1: ST167 | FK1: ST168 | FL1: ST169 | FM1: ST170 | FN1: ST171 | FO1: ST172 | FP1: ST173 | FQ1: ST174 | FR1: ST175 | FS1: ST176 | FT1: ST177 | FU1: ST178 | FV1: ST179 | FW1: ST180 | FX1: ST181 | FY1: ST182 | FZ1: ST183 | GA1: ST184 | GB1: ST185 | GC1: ST186 | GD1: ST187 | GE1: ST188 | GF1: ST189 | GG1: ST190 | GH1: ST191 | GI1: ST192 | GJ1: ST193 | GK1: ST194 | GL1: ST195 | GM1: ST196 | GN1: ST197 | GO1: ST198 | GP1: ST199 | GQ1: ST200 | GR1: ST201 | GS1: ST202 | GT1: ST203 | GU1: ST204 | GV1: ST205 | GW1: ST206 | GX1: ST207 | GY1: ST208 | GZ1: ST209 | HA1: ST210 | HB1: ST211 | HC1: ST212 | HD1: ST213 | HE1: ST214 | HF1: ST215 | HG1: ST216 | HH1: ST217 | HI1: ST218 | HJ1: ST219 | HK1: ST220 | HL1: ST221 | HM1: ST222 | HN1: ST223 | HO1: ST224 | HP1: ST225 | HQ1: ST226 | HR1: ST227 | HS1: ST228 | HT1: ST229 | HU1: ST230 | HV1: ST231 | HW1: ST232 | HX1: ST233 | HY1: ST234 | HZ1: ST235 | IA1: ST236 | IB1: ST237 | IC1: ST238 | ID1: ST239 | IE1: ST240 | IF1: ST241 | IG1: ST242 | IH1: ST243 | II1: ST244 | IJ1: ST245 | IK1: ST246 | IL1: ST247 | IM1: ST248 | IN1: ST249 | IO1: ST250 | IP1: ST251 | IQ1: ST252 | IR1: ST253 | IS1: ST254 | IT1: ST255 | IU1: ST256 | IV1: ST257 | IW1: ST258 | IX1: ST259 | IY1: ST260 | IZ1: ST261 | JA1: ST262 | JB1: ST263
A2: Earnest | B2: 1.5 | C2: 1 | D2: 1 | E2: 1 | F2: 1.5 | G2: 0.7 | H2: 1.5 | I2: 1 | J2: 1 | K2: 1.5 | L2: 1 | M2: 1.3 | N2: 1 | O2: 1 | P2: 0.5 | Q2: 0.7 | R2: 1.3 | S2: 1 | T2: 0.7 | U2: 0.7 | V2: 1.5 | W2: 1 | X2: 1.3 | Y2: 1.3 | Z2: 1.3 | AA2: 1 | AB2: 1.3 | AC2: 1.3 | AD2: 1.5 | AE2: 1.5 | AF2: 1.5 | AG2: 1 | AH2: 1.5 | AI2: 1.3 | AJ2: 1 | AK2: 1.5 | AL2: 0.7 | AM2: 1.3 | AN2: 1 | AO2: 1.5 | AP2: 1.5 | AQ2: 1.5 | AR2: 1 | AS2: 1.3 | AT2: 1 | AU2: 1.5 | AV2: 0.7 | AW2: 0.5 | AX2: 1 | AY2: 0.5 | AZ2: 1.3 | BA2: 1 | BB2: 1.5 | BC2: 0.7 | BD2: 1.3 | BE2: 1 | BF2: 1.5 | BG2: 1.3 | BH2: 1 | BI2: 1.5 | BJ2: 1.5 | BK2: 1.5 | BL2: 1 | BM2: 1 | BN2: 1.3 | BO2: 1.3 | BP2: 1 | BQ2: 0.7 | BR2: 1 | BS2: 1.3 | BT2: 0.5 | BU2: 1 | BV2: 0.5 | BW2: 1.3 | BX2: 1 | BY2: 1.5 | BZ2: 1.3 | CA2: 1 | CB2: 1.5 | CC2: 1.5 | CD2: 1.5 | CE2: 1 | CF2: 1.5 | CG2: 1.3 | CH2: 1 | CI2: 1.5 | CJ2: 0.7 | CK2: 1.3 | CL2: 1 | CM2: 1.5 | CN2: 0.7 | CO2: 1 | CP2: 0.7 | CQ2: 1 | CR2: 1.3 | CS2: 1.5 | CT2: 1.5 | CU2: 1 | CV2: 1.5 | CW2: 1.5 | CX2: 1.5 | CY2: 1.5 | CZ2: 1.5 | DA2: 1.5 | DB2: 1.5 | DC2: 1.5 | DD2: 1.5 | DE2: 1.5 | DF2: 1.5 | DG2: 1.5 | DH2: 1.5 | DI2: 1.5 | DJ2: 1.5 | DK2: 1.5 | DL2: 1.5 | DM2: 1.5 | DN2: 1.5 | DO2: 1.5 | DP2: 1.5 | DQ2: 1.5 | DR2: 1.3 | DS2: 1 | DT2: 1 | DU2: 1.5 | DV2: 1 | DW2: 1 | DX2: 1 | DY2: 1 | DZ2: 1.5 | EA2: 0.5 | EB2: 0.7 | EC2: 0.7 | ED2: 1 | EE2: 1.5 | EF2: 0.7 | EG2: 0.7 | EH2: 0.5 | EI2: 1 | EJ2: 1 | EK2: 1 | EL2: 1 | EM2: 1 | EN2: 1.5 | EO2: 1.3 | EP2: 1 | EQ2: 1 | ER2: 1.5 | ES2: 1.5 | ET2: 0.5 | EU2: 1 | EV2: 1.5 | EW2: 0.7 | EX2: 0.7 | EY2: 1 | EZ2: 1 | FA2: 1.3 | FB2: 0.7 | FC2: 1 | FD2: 1 | FE2: 1.3 | FF2: 1.3 | FG2: 1 | FH2: 0.7 | FI2: 1 | FJ2: 1 | FK2: 0.7 | FL2: 1 | FM2: 1.5 | FN2: 1 | FO2: 1 | FP2: 1 | FQ2: 1.5 | FR2: 0.7 | FS2: 1.5 | FT2: 1.5 | FU2: 0.7 | FV2: 1 | FW2: 1.5 | FX2: 1.5 | FY2: 1 | FZ2: 0.5 | GA2: 0.7 | GB2: 1 | GC2: 0.7 | GD2: 1.5 | GE2: 0.7 | GF2: 0.7 | GG2: 1 | GH2: 0.5 | GI2: 1 | GJ2: 1.5 | GK2: 0.7 | GL2: 1 | GM2: 1 | GN2: 1 | GO2: 1.5 | GP2: 1.3 | GQ2: 1 | GR2: 1.5 | GS2: 1.3 | GT2: 0.7 | GU2: 1.3 | GV2: 0.7 | GW2: 1 | GX2: 1 | GY2: 1.5 | GZ2: 1 | HA2: 1 | HB2: 1 | HC2: 1 | HD2: 1.5 | HE2: 1.5 | HF2: 1 | HG2: 0.7 | HH2: 1 | HI2: 1 | HJ2: 1.5 | HK2: 1 | HL2: 0.5 | HM2: 1 | HN2: 1 | HO2: 0.7 | HP2: 1.3 | HQ2: 1 | HR2: 1.5 | HS2: 1 | HT2: 1 | HU2: 1.5 | HV2: 0.5 | HW2: 1 | HX2: 0.7 | HY2: 0.7 | HZ2: 1.5 | IA2: 0.5 | IB2: 0.7 | IC2: 1 | ID2: 1 | IE2: 1.3 | IF2: 1.3 | IG2: 1 | IH2: 1.5 | II2: 1.5 | IJ2: 0.7 | IK2: 1.3 | IL2: 0.7 | IM2: 1 | IN2: 1 | IO2: 1.3 | IP2: 1 | IQ2: 1 | IR2: 1.5 | IS2: 1.5 | IT2: 1.3 | IU2: 1 | IV2: 1 | IW2: 1.3 | IX2: 1 | IY2: 1.5 | IZ2: 1 | JA2: 1.5 | JB2: 1.5
A3: Emotional | B3: 1 | C3: 1.3 | D3: 0.7 | E3: 1.3 | F3: 1.3 | G3: 1.3 | H3: 1 | I3: 0.7 | J3: 1.5 | K3: 1 | L3: 1.3 | M3: 0.7 | N3: 1.5 | O3: 0.5 | P3: 1 | Q3: 0.5 | R3: 0.5 | S3: 0.7 | T3: 1.5 | U3: 0.5 | V3: 0.5 | W3: 1.5 | X3: 0.5 | Y3: 1 | Z3: 1 | AA3: 0.5 | AB3: 1.5 | AC3: 1 | AD3: 1 | AE3: 1.3 | AF3: 1 | AG3: 1.5 | AH3: 0.7 | AI3: 1.5 | AJ3: 1.5 | AK3: 1 | AL3: 1.5 | AM3: 0.5 | AN3: 1 | AO3: 0.5 | AP3: 1 | AQ3: 0.7 | AR3: 1 | AS3: 0.5 | AT3: 1 | AU3: 0.5 | AV3: 1 | AW3: 0.7 | AX3: 0.5 | AY3: 0.7 | AZ3: 1 | BA3: 1.3 | BB3: 1.3 | BC3: 1 | BD3: 1 | BE3: 0.7 | BF3: 1 | BG3: 0.5 | BH3: 1 | BI3: 0.5 | BJ3: 0.5 | BK3: 1 | BL3: 0.5 | BM3: 0.7 | BN3: 0.5 | BO3: 0.7 | BP3: 0.5 | BQ3: 1 | BR3: 0.5 | BS3: 1 | BT3: 0.7 | BU3: 0.5 | BV3: 0.7 | BW3: 1.5 | BX3: 1.5 | BY3: 1 | BZ3: 1 | CA3: 0.7 | CB3: 1 | CC3: 1.3 | CD3: 1 | CE3: 1.5 | CF3: 0.7 | CG3: 1.5 | CH3: 1.5 | CI3: 1 | CJ3: 1.5 | CK3: 0.7 | CL3: 0.5 | CM3: 0.7 | CN3: 0.5 | CO3: 1 | CP3: 1.3 | CQ3: 1.3 | CR3: 1 | CS3: 0.7 | CT3: 0.5 | CU3: 0.7 | CV3: 1 | CW3: 1 | CX3: 1 | CY3: 1 | CZ3: 1 | DA3: 1 | DB3: 1 | DC3: 1 | DD3: 1 | DE3: 1 | DF3: 1 | DG3: 1 | DH3: 1 | DI3: 1 | DJ3: 1 | DK3: 1 | DL3: 1 | DM3: 1 | DN3: 1 | DO3: 1 | DP3: 1 | DQ3: 1.3 | DR3: 0.5 | DS3: 0.7 | DT3: 1.3 | DU3: 1 | DV3: 1.5 | DW3: 0.7 | DX3: 1.3 | DY3: 0.5 | DZ3: 0.5 | EA3: 1 | EB3: 0.5 | EC3: 0.5 | ED3: 0.7 | EE3: 1.3 | EF3: 0.5 | EG3: 0.5 | EH3: 1 | EI3: 0.5 | EJ3: 0.7 | EK3: 1.3 | EL3: 1.3 | EM3: 0.7 | EN3: 1 | EO3: 0.5 | EP3: 0.5 | EQ3: 0.7 | ER3: 1.3 | ES3: 1 | ET3: 1 | EU3: 0.7 | EV3: 1 | EW3: 0.5 | EX3: 0.5 | EY3: 0.7 | EZ3: 1.3 | FA3: 0.5 | FB3: 0.5 | FC3: 0.7 | FD3: 1.3 | FE3: 0.5 | FF3: 0.7 | FG3: 0.7 | FH3: 0.5 | FI3: 0.5 | FJ3: 1.3 | FK3: 0.5 | FL3: 0.7 | FM3: 1 | FN3: 1.3 | FO3: 1.5 | FP3: 0.7 | FQ3: 1.3 | FR3: 0.5 | FS3: 1 | FT3: 1 | FU3: 0.5 | FV3: 0.7 | FW3: 1.3 | FX3: 1 | FY3: 1.3 | FZ3: 1 | GA3: 0.5 | GB3: 0.7 | GC3: 0.5 | GD3: 0.5 | GE3: 1.5 | GF3: 0.5 | GG3: 1.3 | GH3: 1 | GI3: 0.7 | GJ3: 1 | GK3: 1.5 | GL3: 1.5 | GM3: 1.3 | GN3: 0.7 | GO3: 1.3 | GP3: 0.5 | GQ3: 0.7 | GR3: 0.5 | GS3: 0.7 | GT3: 1.5 | GU3: 0.5 | GV3: 1.3 | GW3: 1.3 | GX3: 0.7 | GY3: 0.5 | GZ3: 0.5 | HA3: 1.3 | HB3: 1.3 | HC3: 0.7 | HD3: 1 | HE3: 0.5 | HF3: 0.5 | HG3: 0.5 | HH3: 0.7 | HI3: 1.3 | HJ3: 1 | HK3: 1.3 | HL3: 1 | HM3: 0.7 | HN3: 0.5 | HO3: 1.3 | HP3: 0.5 | HQ3: 0.7 | HR3: 1 | HS3: 0.5 | HT3: 0.7 | HU3: 1 | HV3: 1 | HW3: 0.7 | HX3: 0.5 | HY3: 1.5 | HZ3: 0.5 | IA3: 1 | IB3: 0.5 | IC3: 0.7 | ID3: 1.3 | IE3: 0.5 | IF3: 0.7 | IG3: 0.7 | IH3: 1 | II3: 1 | IJ3: 1.3 | IK3: 0.5 | IL3: 0.5 | IM3: 0.7 | IN3: 1.3 | IO3: 0.7 | IP3: 1.5 | IQ3: 0.7 | IR3: 1 | IS3: 1 | IT3: 0.5 | IU3: 0.7 | IV3: 1.3 | IW3: 0.5 | IX3: 0.7 | IY3: 1 | IZ3: 0.7 | JA3: 1 | JB3: 1
A4: Appeal | B4: 1.3 | C4: 1.5 | D4: 1.3 | E4: 1.5 | F4: 1 | G4: 1.5 | H4: 1.3 | I4: 1.3 | J4: 0.5 | K4: 1 | L4: 1 | M4: 1 | N4: 0.7 | O4: 1.5 | P4: 0.7 | Q4: 1 | R4: 1 | S4: 1.3 | T4: 1.3 | U4: 1.5 | V4: 1 | W4: 1.3 | X4: 1 | Y4: 1.5 | Z4: 0.7 | AA4: 1 | AB4: 1 | AC4: 1.5 | AD4: 1 | AE4: 1 | AF4: 0.7 | AG4: 1 | AH4: 1.3 | AI4: 1 | AJ4: 1.3 | AK4: 1.3 | AL4: 1 | AM4: 1 | AN4: 0.7 | AO4: 1 | AP4: 1 | AQ4: 1.3 | AR4: 1.3 | AS4: 1 | AT4: 0.7 | AU4: 1 | AV4: 1.3 | AW4: 1.3 | AX4: 1 | AY4: 1.5 | AZ4: 1 | BA4: 0.7 | BB4: 1 | BC4: 1.3 | BD4: 1 | BE4: 1.3 | BF4: 1.3 | BG4: 1.5 | BH4: 1.5 | BI4: 1 | BJ4: 1 | BK4: 1.3 | BL4: 1.3 | BM4: 1.3 | BN4: 1 | BO4: 1.5 | BP4: 1.5 | BQ4: 1.5 | BR4: 1 | BS4: 1.5 | BT4: 1.3 | BU4: 1 | BV4: 1.5 | BW4: 1 | BX4: 1.3 | BY4: 1.3 | BZ4: 1 | CA4: 1.3 | CB4: 1.3 | CC4: 1 | CD4: 0.7 | CE4: 1 | CF4: 1.3 | CG4: 1 | CH4: 0.7 | CI4: 1 | CJ4: 1.3 | CK4: 0.5 | CL4: 1 | CM4: 0.5 | CN4: 1 | CO4: 1.5 | CP4: 1.5 | CQ4: 1 | CR4: 1.5 | CS4: 1.3 | CT4: 1 | CU4: 1.5 | CV4: 1.3 | CW4: 1.3 | CX4: 1.3 | CY4: 1.3 | CZ4: 1.3 | DA4: 1.3 | DB4: 1.3 | DC4: 1.3 | DD4: 1.3 | DE4: 1.3 | DF4: 1.3 | DG4: 1.3 | DH4: 1.3 | DI4: 1.3 | DJ4: 1.3 | DK4: 1.3 | DL4: 1.3 | DM4: 1.3 | DN4: 1.3 | DO4: 1.3 | DP4: 1.3 | DQ4: 1 | DR4: 1 | DS4: 1.3 | DT4: 1.5 | DU4: 1 | DV4: 0.7 | DW4: 1.3 | DX4: 1.5 | DY4: 1.5 | DZ4: 1 | EA4: 0.7 | EB4: 1.5 | EC4: 1 | ED4: 1.3 | EE4: 1 | EF4: 1 | EG4: 1.5 | EH4: 0.7 | EI4: 1.5 | EJ4: 1.3 | EK4: 1.5 | EL4: 1 | EM4: 1.3 | EN4: 1.3 | EO4: 1 | EP4: 1.5 | EQ4: 1.3 | ER4: 1 | ES4: 1 | ET4: 0.7 | EU4: 1.3 | EV4: 1.3 | EW4: 1.5 | EX4: 1 | EY4: 1.3 | EZ4: 1.5 | FA4: 1 | FB4: 1 | FC4: 1.3 | FD4: 1.5 | FE4: 1 | FF4: 1 | FG4: 1.3 | FH4: 1.5 | FI4: 1.5 | FJ4: 1.5 | FK4: 1 | FL4: 1.3 | FM4: 1.3 | FN4: 1.5 | FO4: 0.5 | FP4: 1.3 | FQ4: 1 | FR4: 1.5 | FS4: 1.3 | FT4: 1 | FU4: 1 | FV4: 1.3 | FW4: 1 | FX4: 1.3 | FY4: 1.5 | FZ4: 0.7 | GA4: 1 | GB4: 1.3 | GC4: 1.5 | GD4: 1 | GE4: 1.3 | GF4: 1 | GG4: 1.5 | GH4: 0.7 | GI4: 1.3 | GJ4: 1.3 | GK4: 1.3 | GL4: 0.5 | GM4: 1.5 | GN4: 1.3 | GO4: 1 | GP4: 1 | GQ4: 1.3 | GR4: 1 | GS4: 1 | GT4: 1.3 | GU4: 1 | GV4: 1.5 | GW4: 1 | GX4: 1.3 | GY4: 1 | GZ4: 1.5 | HA4: 1.5 | HB4: 1 | HC4: 1.3 | HD4: 1.3 | HE4: 1 | HF4: 1.5 | HG4: 1 | HH4: 1.3 | HI4: 1.5 | HJ4: 1.3 | HK4: 1 | HL4: 0.7 | HM4: 1.3 | HN4: 1.5 | HO4: 1.5 | HP4: 1 | HQ4: 1.3 | HR4: 1.3 | HS4: 1.5 | HT4: 1.3 | HU4: 1 | HV4: 0.7 | HW4: 1.3 | HX4: 1.5 | HY4: 1.3 | HZ4: 1 | IA4: 0.7 | IB4: 1 | IC4: 1.3 | ID4: 1.5 | IE4: 1 | IF4: 1 | IG4: 1.3 | IH4: 1.3 | II4: 1.3 | IJ4: 1.5 | IK4: 1 | IL4: 1 | IM4: 1.3 | IN4: 1.5 | IO4: 1 | IP4: 0.5 | IQ4: 1.3 | IR4: 1.3 | IS4: 1.3 | IT4: 1 | IU4: 1.3 | IV4: 1.5 | IW4: 1 | IX4: 1.3 | IY4: 1.3 | IZ4: 1.3 | JA4: 1.3 | JB4: 1.3
A5: Data Driven | B5: 1 | C5: 0.7 | D5: 0.5 | E5: 0.5 | F5: 0.7 | G5: 0.5 | H5: 0.7 | I5: 0.5 | J5: 1.3 | K5: 1.3 | L5: 0.5 | M5: 1.5 | N5: 1 | O5: 1.3 | P5: 1.3 | Q5: 1.5 | R5: 1.5 | S5: 1.5 | T5: 0.5 | U5: 1 | V5: 1.3 | W5: 0.7 | X5: 1.5 | Y5: 0.5 | Z5: 1.5 | AA5: 1.5 | AB5: 1 | AC5: 0.7 | AD5: 1.3 | AE5: 1 | AF5: 1.3 | AG5: 1.3 | AH5: 1 | AI5: 1 | AJ5: 0.7 | AK5: 1 | AL5: 1.3 | AM5: 1.5 | AN5: 1.5 | AO5: 1 | AP5: 1.3 | AQ5: 1 | AR5: 1.5 | AS5: 1.5 | AT5: 1.5 | AU5: 1 | AV5: 1.5 | AW5: 1.5 | AX5: 1.5 | AY5: 1 | AZ5: 1.5 | BA5: 1.5 | BB5: 1 | BC5: 1.5 | BD5: 1.5 | BE5: 1.5 | BF5: 1 | BG5: 1 | BH5: 1.3 | BI5: 1.3 | BJ5: 1.3 | BK5: 1 | BL5: 1.5 | BM5: 1.5 | BN5: 1.5 | BO5: 1 | BP5: 1.3 | BQ5: 1 | BR5: 1.5 | BS5: 0.7 | BT5: 1.5 | BU5: 1.5 | BV5: 1 | BW5: 1 | BX5: 0.7 | BY5: 1 | BZ5: 1.5 | CA5: 1.5 | CB5: 1 | CC5: 1 | CD5: 1.3 | CE5: 1.3 | CF5: 1 | CG5: 1 | CH5: 1.3 | CI5: 1.3 | CJ5: 1 | CK5: 1.5 | CL5: 1.5 | CM5: 1 | CN5: 1.5 | CO5: 1.3 | CP5: 1 | CQ5: 1.5 | CR5: 0.7 | CS5: 1 | CT5: 1.3 | CU5: 1.3 | CV5: 0.7 | CW5: 0.7 | CX5: 0.7 | CY5: 0.7 | CZ5: 0.7 | DA5: 0.7 | DB5: 0.7 | DC5: 0.7 | DD5: 0.7 | DE5: 0.7 | DF5: 0.7 | DG5: 0.7 | DH5: 0.7 | DI5: 0.7 | DJ5: 0.7 | DK5: 0.7 | DL5: 0.7 | DM5: 0.7 | DN5: 0.7 | DO5: 0.7 | DP5: 0.7 | DQ5: 0.7 | DR5: 1.5 | DS5: 0.5 | DT5: 0.5 | DU5: 1.3 | DV5: 1 | DW5: 0.5 | DX5: 0.5 | DY5: 1.3 | DZ5: 1.3 | EA5: 1.3 | EB5: 1 | EC5: 1.5 | ED5: 0.5 | EE5: 0.7 | EF5: 1.5 | EG5: 1 | EH5: 1.3 | EI5: 1.3 | EJ5: 0.5 | EK5: 0.5 | EL5: 0.5 | EM5: 0.5 | EN5: 0.7 | EO5: 1.5 | EP5: 1.3 | EQ5: 0.5 | ER5: 0.7 | ES5: 1.3 | ET5: 1.3 | EU5: 0.5 | EV5: 0.7 | EW5: 1 | EX5: 1.5 | EY5: 0.5 | EZ5: 0.5 | FA5: 1.5 | FB5: 1.5 | FC5: 0.5 | FD5: 0.5 | FE5: 1.5 | FF5: 1.5 | FG5: 0.5 | FH5: 1 | FI5: 1.3 | FJ5: 0.5 | FK5: 1.5 | FL5: 0.5 | FM5: 0.7 | FN5: 0.5 | FO5: 1.3 | FP5: 0.5 | FQ5: 0.7 | FR5: 1 | FS5: 0.7 | FT5: 1.3 | FU5: 1.5 | FV5: 0.5 | FW5: 0.7 | FX5: 0.7 | FY5: 0.5 | FZ5: 1.3 | GA5: 1.5 | GB5: 0.5 | GC5: 1 | GD5: 1.3 | GE5: 0.5 | GF5: 1.5 | GG5: 0.5 | GH5: 1.3 | GI5: 0.5 | GJ5: 0.7 | GK5: 0.5 | GL5: 1.3 | GM5: 0.5 | GN5: 0.5 | GO5: 0.7 | GP5: 1.5 | GQ5: 0.5 | GR5: 1.3 | GS5: 1.5 | GT5: 0.5 | GU5: 1.5 | GV5: 0.5 | GW5: 0.5 | GX5: 0.5 | GY5: 1.3 | GZ5: 1.3 | HA5: 0.5 | HB5: 0.5 | HC5: 0.5 | HD5: 0.7 | HE5: 1.3 | HF5: 1.3 | HG5: 1.5 | HH5: 0.5 | HI5: 0.5 | HJ5: 1 | HK5: 0.5 | HL5: 1.3 | HM5: 0.5 | HN5: 1.3 | HO5: 0.5 | HP5: 1.5 | HQ5: 0.5 | HR5: 0.7 | HS5: 1.3 | HT5: 0.5 | HU5: 1.3 | HV5: 1.3 | HW5: 0.5 | HX5: 1 | HY5: 0.5 | HZ5: 1.3 | IA5: 1.3 | IB5: 1.5 | IC5: 0.5 | ID5: 0.5 | IE5: 1.5 | IF5: 1.5 | IG5: 0.5 | IH5: 0.7 | II5: 1 | IJ5: 0.5 | IK5: 1.5 | IL5: 1.5 | IM5: 0.5 | IN5: 0.5 | IO5: 1.5 | IP5: 1.3 | IQ5: 0.5 | IR5: 0.7 | IS5: 1 | IT5: 1.5 | IU5: 0.5 | IV5: 0.5 | IW5: 1.5 | IX5: 0.5 | IY5: 0.7 | IZ5: 0.5 | JA5: 0.7 | JB5: 0.7
A6: Divisive | B6: 0.7 | C6: 1 | D6: 1.5 | E6: 1 | F6: 0.5 | G6: 1 | H6: 0.5 | I6: 1.5 | J6: 0.7 | K6: 0.5 | L6: 1.5 | M6: 0.5 | N6: 1.3 | O6: 0.7 | P6: 1 | Q6: 1 | R6: 0.7 | S6: 0.5 | T6: 1 | U6: 1 | V6: 0.7 | W6: 0.5 | X6: 0.7 | Y6: 1 | Z6: 0.5 | AA6: 0.7 | AB6: 0.5 | AC6: 1 | AD6: 0.5 | AE6: 0.5 | AF6: 1 | AG6: 0.5 | AH6: 1 | AI6: 0.7 | AJ6: 0.5 | AK6: 0.7 | AL6: 0.5 | AM6: 0.7 | AN6: 0.5 | AO6: 0.7 | AP6: 0.7 | AQ6: 0.5 | AR6: 0.7 | AS6: 1 | AT6: 1.3 | AU6: 1.3 | AV6: 1 | AW6: 1 | AX6: 0.7 | AY6: 1 | AZ6: 0.5 | BA6: 1 | BB6: 0.5 | BC6: 1 | BD6: 0.7 | BE6: 0.5 | BF6: 0.7 | BG6: 1 | BH6: 0.7 | BI6: 1 | BJ6: 0.7 | BK6: 0.5 | BL6: 0.7 | BM6: 0.5 | BN6: 1 | BO6: 0.5 | BP6: 0.7 | BQ6: 0.5 | BR6: 0.7 | BS6: 0.5 | BT6: 1 | BU6: 0.7 | BV6: 1 | BW6: 0.7 | BX6: 0.5 | BY6: 0.7 | BZ6: 0.7 | CA6: 0.5 | CB6: 0.7 | CC6: 0.5 | CD6: 1 | CE6: 0.5 | CF6: 1 | CG6: 0.7 | CH6: 0.5 | CI6: 0.7 | CJ6: 0.5 | CK6: 1 | CL6: 1.3 | CM6: 1.3 | CN6: 1 | CO6: 0.7 | CP6: 0.5 | CQ6: 0.7 | CR6: 0.5 | CS6: 1 | CT6: 0.7 | CU6: 1 | CV6: 0.5 | CW6: 0.5 | CX6: 0.5 | CY6: 0.5 | CZ6: 0.5 | DA6: 0.5 | DB6: 0.5 | DC6: 0.5 | DD6: 0.5 | DE6: 0.5 | DF6: 0.5 | DG6: 0.5 | DH6: 0.5 | DI6: 0.5 | DJ6: 0.5 | DK6: 0.5 | DL6: 0.5 | DM6: 0.5 | DN6: 0.5 | DO6: 0.5 | DP6: 0.5 | DQ6: 0.5 | DR6: 0.7 | DS6: 1.5 | DT6: 1 | DU6: 0.5 | DV6: 1.3 | DW6: 1.5 | DX6: 1 | DY6: 0.7 | DZ6: 0.7 | EA6: 1 | EB6: 1 | EC6: 1 | ED6: 1.5 | EE6: 0.5 | EF6: 1 | EG6: 1 | EH6: 1 | EI6: 0.7 | EJ6: 1.5 | EK6: 1 | EL6: 1.5 | EM6: 1.5 | EN6: 0.5 | EO6: 0.7 | EP6: 0.7 | EQ6: 1.5 | ER6: 0.5 | ES6: 0.5 | ET6: 1 | EU6: 1.5 | EV6: 0.5 | EW6: 1 | EX6: 1 | EY6: 1.5 | EZ6: 1 | FA6: 0.7 | FB6: 1 | FC6: 1.5 | FD6: 1 | FE6: 0.7 | FF6: 0.5 | FG6: 1.5 | FH6: 1 | FI6: 0.7 | FJ6: 1 | FK6: 1 | FL6: 1.5 | FM6: 0.5 | FN6: 1 | FO6: 0.7 | FP6: 1.5 | FQ6: 0.5 | FR6: 1 | FS6: 0.5 | FT6: 0.5 | FU6: 1 | FV6: 1.5 | FW6: 0.5 | FX6: 0.5 | FY6: 1 | FZ6: 1 | GA6: 1 | GB6: 1.5 | GC6: 1 | GD6: 0.7 | GE6: 1 | GF6: 1 | GG6: 1 | GH6: 1 | GI6: 1.5 | GJ6: 0.5 | GK6: 1 | GL6: 0.7 | GM6: 1 | GN6: 1.5 | GO6: 0.5 | GP6: 0.7 | GQ6: 1.5 | GR6: 0.7 | GS6: 0.5 | GT6: 1 | GU6: 0.7 | GV6: 1 | GW6: 1.5 | GX6: 1.5 | GY6: 0.7 | GZ6: 0.7 | HA6: 1 | HB6: 1.5 | HC6: 1.5 | HD6: 0.5 | HE6: 0.7 | HF6: 0.7 | HG6: 1 | HH6: 1.5 | HI6: 1 | HJ6: 0.7 | HK6: 1.5 | HL6: 1 | HM6: 1.5 | HN6: 0.7 | HO6: 1 | HP6: 0.7 | HQ6: 1.5 | HR6: 0.5 | HS6: 0.7 | HT6: 1.5 | HU6: 0.5 | HV6: 1 | HW6: 1.5 | HX6: 1 | HY6: 1 | HZ6: 0.7 | IA6: 1 | IB6: 1 | IC6: 1.5 | ID6: 1 | IE6: 0.7 | IF6: 0.5 | IG6: 1.5 | IH6: 0.5 | II6: 0.7 | IJ6: 1 | IK6: 0.7 | IL6: 1 | IM6: 1.5 | IN6: 1 | IO6: 0.5 | IP6: 0.7 | IQ6: 1.5 | IR6: 0.5 | IS6: 0.7 | IT6: 0.7 | IU6: 1.5 | IV6: 1 | IW6: 0.7 | IX6: 1.5 | IY6: 0.5 | IZ6: 1.5 | JA6: 0.5 | JB6: 0.5
A7: Duplicitous | B7: 0.5 | C7: 0.5 | D7: 1 | E7: 0.7 | F7: 1 | G7: 1 | H7: 1 | I7: 1 | J7: 1 | K7: 0.7 | L7: 0.7 | M7: 1 | N7: 0.5 | O7: 1 | P7: 1.5 | Q7: 1.3 | R7: 1 | S7: 1 | T7: 1 | U7: 1.3 | V7: 1 | W7: 1 | X7: 1 | Y7: 0.7 | Z7: 1 | AA7: 1.3 | AB7: 0.7 | AC7: 0.5 | AD7: 0.7 | AE7: 0.7 | AF7: 0.5 | AG7: 0.7 | AH7: 0.5 | AI7: 0.5 | AJ7: 1 | AK7: 0.5 | AL7: 1 | AM7: 1 | AN7: 1.3 | AO7: 1.3 | AP7: 0.5 | AQ7: 1 | AR7: 0.5 | AS7: 0.7 | AT7: 0.5 | AU7: 0.7 | AV7: 0.5 | AW7: 1 | AX7: 1.3 | AY7: 1.3 | AZ7: 0.7 | BA7: 0.5 | BB7: 0.7 | BC7: 0.5 | BD7: 0.5 | BE7: 1 | BF7: 0.5 | BG7: 0.7 | BH7: 0.5 | BI7: 0.7 | BJ7: 1 | BK7: 0.7 | BL7: 1 | BM7: 1 | BN7: 0.7 | BO7: 1 | BP7: 1 | BQ7: 1.3 | BR7: 1.3 | BS7: 1 | BT7: 1 | BU7: 1.3 | BV7: 1.3 | BW7: 0.5 | BX7: 1 | BY7: 0.5 | BZ7: 0.5 | CA7: 1 | CB7: 0.5 | CC7: 0.7 | CD7: 0.5 | CE7: 0.7 | CF7: 0.5 | CG7: 0.5 | CH7: 1 | CI7: 0.5 | CJ7: 1 | CK7: 1 | CL7: 0.7 | CM7: 1 | CN7: 1.3 | CO7: 0.5 | CP7: 1 | CQ7: 0.5 | CR7: 1 | CS7: 0.5 | CT7: 1 | CU7: 0.5 | CV7: 1 | CW7: 1 | CX7: 1 | CY7: 1 | CZ7: 1 | DA7: 1 | DB7: 1 | DC7: 1 | DD7: 1 | DE7: 1 | DF7: 1 | DG7: 1 | DH7: 1 | DI7: 1 | DJ7: 1 | DK7: 1 | DL7: 1 | DM7: 1 | DN7: 1 | DO7: 1 | DP7: 1 | DQ7: 1 | DR7: 1 | DS7: 1 | DT7: 0.7 | DU7: 0.7 | DV7: 0.5 | DW7: 1 | DX7: 0.7 | DY7: 1 | DZ7: 1 | EA7: 1.5 | EB7: 1.3 | EC7: 1.3 | ED7: 1 | EE7: 1 | EF7: 1.3 | EG7: 1.3 | EH7: 1.5 | EI7: 1 | EJ7: 1 | EK7: 0.7 | EL7: 0.7 | EM7: 1 | EN7: 1 | EO7: 1 | EP7: 1 | EQ7: 1 | ER7: 1 | ES7: 0.7 | ET7: 1.5 | EU7: 1 | EV7: 1 | EW7: 1.3 | EX7: 1.3 | EY7: 1 | EZ7: 0.7 | FA7: 1 | FB7: 1.3 | FC7: 1 | FD7: 0.7 | FE7: 1 | FF7: 1 | FG7: 1 | FH7: 1.3 | FI7: 1 | FJ7: 0.7 | FK7: 1.3 | FL7: 1 | FM7: 1 | FN7: 0.7 | FO7: 1 | FP7: 1 | FQ7: 1 | FR7: 1.3 | FS7: 1 | FT7: 0.7 | FU7: 1.3 | FV7: 1 | FW7: 1 | FX7: 1 | FY7: 0.7 | FZ7: 1.5 | GA7: 1.3 | GB7: 1 | GC7: 1.3 | GD7: 1 | GE7: 1 | GF7: 1.3 | GG7: 0.7 | GH7: 1.5 | GI7: 1 | GJ7: 1 | GK7: 1 | GL7: 1 | GM7: 0.7 | GN7: 1 | GO7: 1 | GP7: 1 | GQ7: 1 | GR7: 1 | GS7: 1 | GT7: 1 | GU7: 1 | GV7: 1 | GW7: 0.7 | GX7: 1 | GY7: 1 | GZ7: 1 | HA7: 0.7 | HB7: 0.7 | HC7: 1 | HD7: 1 | HE7: 1 | HF7: 1 | HG7: 1.3 | HH7: 1 | HI7: 0.7 | HJ7: 0.5 | HK7: 0.7 | HL7: 1.5 | HM7: 1 | HN7: 1 | HO7: 1 | HP7: 1 | HQ7: 1 | HR7: 1 | HS7: 1 | HT7: 1 | HU7: 0.7 | HV7: 1.5 | HW7: 1 | HX7: 1.3 | HY7: 1 | HZ7: 1 | IA7: 1.5 | IB7: 1.3 | IC7: 1 | ID7: 0.7 | IE7: 1 | IF7: 1 | IG7: 1 | IH7: 1 | II7: 0.5 | IJ7: 1 | IK7: 1 | IL7: 1.3 | IM7: 1 | IN7: 0.7 | IO7: 1 | IP7: 1 | IQ7: 1 | IR7: 1 | IS7: 0.5 | IT7: 1 | IU7: 1 | IV7: 0.7 | IW7: 1 | IX7: 1 | IY7: 1 | IZ7: 1 | JA7: 1 | JB7: 1
A9: Stage name → | B9: =IFERROR(INDEX(Stages!$B$2:$B$22,MATCH(B$1,Stages!$A$2:$A$9,0)),"") -> Special Committee | C9: =IFERROR(INDEX(Stages!$B$2:$B$22,MATCH(C$1,Stages!$A$2:$A$9,0)),"") -> Floor Debate | D9: =IFERROR(INDEX(Stages!$B$2:$B$22,MATCH(D$1,Stages!$A$2:$A$9,0)),"") -> Party Caucus | E9: =IFERROR(INDEX(Stages!$B$2:$B$22,MATCH(E$1,Stages!$A$2:$A$9,0)),"") -> Press Conference | F9: =IFERROR(INDEX(Stages!$B$2:$B$22,MATCH(F$1,Stages!$A$2:$A$9,0)),"") -> Town Hall | G9: =IFERROR(INDEX(Stages!$B$2:$B$22,MATCH(G$1,Stages!$A$2:$A$9,0)),"") -> TV Debate | H9: =IFERROR(INDEX(Stages!$B$2:$B$22,MATCH(H$1,Stages!$A$2:$A$9,0)),"") -> Office Hours | I9: =IFERROR(INDEX(Stages!$B$2:$B$22,MATCH(I$1,Stages!$A$2:$A$9,0)),"") -> Party Steering Committee | J9: =Stages!B10 -> Committee on Ethics and Prosecution | K9: =Stages!B11 -> Committee on the Environment | L9: =Stages!B12 -> Committee on War | M9: =Stages!B13 -> Committee on the National Assembly | N9: =Stages!B14 -> Committee on Agriculture | O9: =Stages!B15 -> Committee on Foreign Affairs | P9: =Stages!B16 -> Committee on Construction and Development | Q9: =Stages!B17 -> Committee on Finance | R9: =Stages!B18 -> Committee on Government Administration | S9: =Stages!B19 -> Committee of the Cabinet | T9: =Stages!B20 -> Media Ambush | U9: =Stages!B21 -> Lobbyist Meeting | V9: =Stages!B22 -> Policy Study Session | W9: Town Hall on Commuter Fares | X9: Policy Study on Rail Timetables | Y9: Press Conference on Raising Train Fares | Z9: Hearing on Rail Safety | AA9: Lobbyist Meeting on Fishing Quotas | AB9: Town Hall at the Harbor | AC9: Media Ambush on Seafood Labeling | AD9: Hearing on Fishery Quotas | AE9: Press Conference on Wilderness Protection | AF9: Hearing on Wilderness Protection | AG9: Town Hall on Wilderness Protection | AH9: Party Caucus on Wilderness Protection | AI9: Town Hall on Rural Hospitals | AJ9: Hearing on Rural Hospitals | AK9: Policy Study on Rural Hospitals | AL9: Party Caucus on Rural Hospitals | AM9: Policy Study on Digital Identity Cards | AN9: TV Debate on Digital Identity Cards | AO9: Party Caucus on Digital Identity Cards | AP9: Press Conference on Broadcaster Independence | AQ9: TV Debate on Broadcaster Independence | AR9: Party Caucus on Broadcaster Independence | AS9: Press Conference on Donation Transparency | AT9: Hearing on Donation Transparency | AU9: Lobbyist Meeting on Donation Transparency | AV9: Party Caucus on Donation Transparency | AW9: Policy Study on Corporate Tax Cuts | AX9: Hearing on Corporate Tax Cuts | AY9: Party Caucus on Corporate Tax Cuts | AZ9: Town Hall on the Carbon Levy | BA9: Hearing on the Carbon Levy | BB9: Press Conference on the Carbon Levy | BC9: Party Caucus on the Carbon Levy | BD9: Hearing on Fishing Quota Reform | BE9: Town Hall on Fishing Quota Reform | BF9: Party Caucus on Fishing Quota Reform | BG9: Hearing on Shipbuilding Support | BH9: Town Hall on Shipbuilding Support | BI9: Party Caucus on Shipbuilding Support | BJ9: Hearing on the Constitutional Review | BK9: Press Conference on the Constitutional Review | BL9: Party Caucus on the Constitutional Review | BM9: Hearing on Border Cooperation | BN9: Lobbyist Meeting on Border Cooperation | BO9: Party Caucus on Border Cooperation | BP9: Hearing on Chishima Development | BQ9: Press Conference on Chishima Development | BR9: Lobbyist Meeting on Chishima Development | BS9: Party Caucus on Chishima Development | BT9: TV Debate on China Trade | BU9: Hearing on China Trade | BV9: Party Caucus on China Trade | BW9: Town Hall on Farm Succession | BX9: Hearing on Farm Succession | BY9: Party Caucus on Farm Succession | BZ9: Policy Study on University Research Funding | CA9: Hearing on University Research Funding | CB9: Party Caucus on University Research Funding | CC9: Town Hall on Workplace Equality | CD9: Press Conference on Workplace Equality | CE9: TV Debate on Workplace Equality | CF9: Party Caucus on Workplace Equality | CG9: Town Hall on Parental Leave | CH9: Policy Study on Parental Leave | CI9: Lobbyist Meeting on Parental Leave | CJ9: Party Caucus on Parental Leave | CK9: Hearing on Surveillance Cameras | CL9: TV Debate on Surveillance Cameras | CM9: Press Conference on Surveillance Cameras | CN9: Party Caucus on Surveillance Cameras | CO9: Town Hall on Town Mergers | CP9: Hearing on Town Mergers | CQ9: Policy Study on Town Mergers | CR9: Party Caucus on Town Mergers | CS9: TV Debate on Party Leadership Ballots | CT9: Press Conference on Party Leadership Ballots | CU9: Party Caucus on Party Leadership Ballots | CV9: Office Hours: Wilderness Protection | CW9: Office Hours: Rural Hospitals | CX9: Office Hours: Digital Identity Cards | CY9: Office Hours: Broadcaster Independence | CZ9: Office Hours: Donation Transparency | DA9: Office Hours: Corporate Tax Cuts | DB9: Office Hours: the Carbon Levy | DC9: Office Hours: Fishing Quota Reform | DD9: Office Hours: Shipbuilding Support | DE9: Office Hours: the Constitutional Review | DF9: Office Hours: Border Cooperation | DG9: Office Hours: Chishima Development | DH9: Office Hours: China Trade | DI9: Office Hours: Farm Succession | DJ9: Office Hours: University Research Funding | DK9: Office Hours: Workplace Equality | DL9: Office Hours: Parental Leave | DM9: Office Hours: Surveillance Cameras | DN9: Office Hours: Town Mergers | DO9: Office Hours: Party Leadership Ballots | DP9: Office Hours: Ainu Heritage and Language | DQ9: Town Hall on Ainu Heritage and Language | DR9: Committee on Government Administration: Ainu Heritage and Language | DS9: Party Caucus on Ainu Heritage and Language | DT9: Press Conference on Agricultural Price Stabilization | DU9: Committee on the Environment: Agricultural Price Stabilization | DV9: Committee on Agriculture: Agricultural Price Stabilization | DW9: Party Caucus on Agricultural Price Stabilization | DX9: Press Conference on Special Economic Zones | DY9: Committee on Foreign Affairs: Special Economic Zones | DZ9: Policy Study Session on Special Economic Zones | EA9: Committee on Construction and Development: Special Economic Zones | EB9: Lobbyist Meeting on Special Economic Zones | EC9: Committee on Finance: Special Economic Zones | ED9: Party Caucus on Special Economic Zones | EE9: Town Hall on Hokkaido Shinkansen Acceleration | EF9: Committee on Finance: Hokkaido Shinkansen Acceleration | EG9: Lobbyist Meeting on Hokkaido Shinkansen Acceleration | EH9: Committee on Construction and Development: Hokkaido Shinkansen Acceleration | EI9: Committee on Foreign Affairs: Hokkaido Shinkansen Acceleration | EJ9: Party Caucus on Hokkaido Shinkansen Acceleration | EK9: Press Conference on Chishima Coastal Defense Modernization | EL9: Committee on War: Chishima Coastal Defense Modernization | EM9: Party Caucus on Chishima Coastal Defense Modernization | EN9: Office Hours: Specified Skilled Worker Visa | EO9: Committee on Government Administration: Specified Skilled Worker Visa | EP9: Committee on Foreign Affairs: Specified Skilled Worker Visa | EQ9: Party Caucus on Specified Skilled Worker Visa | ER9: Town Hall on Grid Resilience and Renewable Energy | ES9: Committee on the Environment: Grid Resilience and Renewable Energy | ET9: Committee on Construction and Development: Grid Resilience and Renewable Energy | EU9: Party Caucus on Grid Resilience and Renewable Energy | EV9: Office Hours: Consumption Tax Rate | EW9: Lobbyist Meeting on Consumption Tax Rate | EX9: Committee on Finance: Consumption Tax Rate | EY9: Party Caucus on Consumption Tax Rate | EZ9: Press Conference on Prefectural Fiscal Devolution | FA9: Committee on Government Administration: Prefectural Fiscal Devolution | FB9: Committee on Finance: Prefectural Fiscal Devolution | FC9: Party Caucus on Prefectural Fiscal Devolution | FD9: Press Conference on Candidate Gender Parity | FE9: Committee on Government Administration: Candidate Gender Parity | FF9: Committee on the National Assembly: Candidate Gender Parity | FG9: Party Caucus on Candidate Gender Parity | FH9: Lobbyist Meeting on Tsugaru Strait Joint Commission | FI9: Committee on Foreign Affairs: Tsugaru Strait Joint Commission | FJ9: Press Conference on Tsugaru Strait Joint Commission | FK9: Committee on Finance: Tsugaru Strait Joint Commission | FL9: Party Caucus on Tsugaru Strait Joint Commission | FM9: Office Hours: Judicial Appointments Commission | FN9: Press Conference on Judicial Appointments Commission | FO9: Committee on Ethics and Prosecution: Judicial Appointments Commission | FP9: Party Caucus on Judicial Appointments Commission | FQ9: Town Hall on Temple and Shrine Heritage | FR9: Lobbyist Meeting on Temple and Shrine Heritage | FS9: Office Hours: Temple and Shrine Heritage | FT9: Committee on the Environment: Temple and Shrine Heritage | FU9: Committee on Finance: Temple and Shrine Heritage | FV9: Party Caucus on Temple and Shrine Heritage | FW9: Town Hall on Constituency Development Grants | FX9: Office Hours: Constituency Development Grants | FY9: Press Conference on Constituency Development Grants | FZ9: Committee on Construction and Development: Constituency Development Grants | GA9: Committee on Finance: Constituency Development Grants | GB9: Party Caucus on Constituency Development Grants | GC9: Lobbyist Meeting on Digital Economy Promotion | GD9: Policy Study Session on Digital Economy Promotion | GE9: Media Ambush on Digital Economy Promotion | GF9: Committee on Finance: Digital Economy Promotion | GG9: Press Conference on Digital Economy Promotion | GH9: Committee on Construction and Development: Digital Economy Promotion | GI9: Party Caucus on Digital Economy Promotion | GJ9: Office Hours: Organized Crime Conspiracy | GK9: Media Ambush on Organized Crime Conspiracy | GL9: Committee on Ethics and Prosecution: Organized Crime Conspiracy | GM9: Press Conference on Organized Crime Conspiracy | GN9: Party Caucus on Organized Crime Conspiracy | GO9: Town Hall on Partnership Registration | GP9: Committee on Government Administration: Partnership Registration | GQ9: Party Caucus on Partnership Registration | GR9: Policy Study Session on National Emergency Powers | GS9: Committee on the National Assembly: National Emergency Powers | GT9: Media Ambush on National Emergency Powers | GU9: Committee on Government Administration: National Emergency Powers | GV9: TV Debate on National Emergency Powers | GW9: Committee on War: National Emergency Powers | GX9: Party Caucus on National Emergency Powers | GY9: Policy Study Session on Yezo–US Security Consultation Agreement | GZ9: Committee on Foreign Affairs: Yezo–US Security Consultation Agreement | HA9: Press Conference on Yezo–US Security Consultation Agreement | HB9: Committee on War: Yezo–US Security Consultation Agreement | HC9: Party Caucus on Yezo–US Security Consultation Agreement | HD9: Office Hours: Yezo–EU Economic Partnership Agreement | HE9: Policy Study Session on Yezo–EU Economic Partnership Agreement | HF9: Committee on Foreign Affairs: Yezo–EU Economic Partnership Agreement | HG9: Committee on Finance: Yezo–EU Economic Partnership Agreement | HH9: Party Caucus on Yezo–EU Economic Partnership Agreement | HI9: Press Conference on Strategic Land and Port Screening | HJ9: Special Committee: Strategic Land and Port Screening | HK9: Committee on War: Strategic Land and Port Screening | HL9: Committee on Construction and Development: Strategic Land and Port Screening | HM9: Party Caucus on Strategic Land and Port Screening | HN9: Committee on Foreign Affairs: Inbound Tourism Visa Waiver | HO9: TV Debate on Inbound Tourism Visa Waiver | HP9: Committee on Government Administration: Inbound Tourism Visa Waiver | HQ9: Party Caucus on Inbound Tourism Visa Waiver | HR9: Office Hours: Chishima Joint Economic Activity | HS9: Committee on Foreign Affairs: Chishima Joint Economic Activity | HT9: Party Caucus on Chishima Joint Economic Activity | HU9: Committee on the Environment: Tomari Nuclear Restart | HV9: Committee on Construction and Development: Tomari Nuclear Restart | HW9: Party Caucus on Tomari Nuclear Restart | HX9: Lobbyist Meeting on Integrated Resort | HY9: Media Ambush on Integrated Resort | HZ9: Policy Study Session on Integrated Resort | IA9: Committee on Construction and Development: Integrated Resort | IB9: Committee on Finance: Integrated Resort | IC9: Party Caucus on Integrated Resort | ID9: Press Conference on Civil Service Merit | IE9: Committee on Government Administration: Civil Service Merit | IF9: Committee on the National Assembly: Civil Service Merit | IG9: Party Caucus on Civil Service Merit | IH9: Office Hours: Regional Minimum Wage | II9: Special Committee: Regional Minimum Wage | IJ9: TV Debate on Regional Minimum Wage | IK9: Committee on Government Administration: Regional Minimum Wage | IL9: Committee on Finance: Regional Minimum Wage | IM9: Party Caucus on Regional Minimum Wage | IN9: Press Conference on Independent Election Commission | IO9: Committee on the National Assembly: Independent Election Commission | IP9: Committee on Ethics and Prosecution: Independent Election Commission | IQ9: Party Caucus on Independent Election Commission | IR9: Office Hours: Moral Education Curriculum | IS9: Special Committee: Moral Education Curriculum | IT9: Committee on Government Administration: Moral Education Curriculum | IU9: Party Caucus on Moral Education Curriculum | IV9: Press Conference on Foreign Resident Local Suffrage | IW9: Committee on Government Administration: Foreign Resident Local Suffrage | IX9: Party Caucus on Foreign Resident Local Suffrage | IY9: Member Visit | IZ9: Win Over a Member | JA9: Lobbyist Trade | JB9: Patron Visit
A10: Column average | B10: =AVERAGE(B2:B7) -> 1 | C10: =AVERAGE(C2:C7) -> 1 | D10: =AVERAGE(D2:D7) -> 1 | E10: =AVERAGE(E2:E7) -> 1 | F10: =AVERAGE(F2:F7) -> 1 | G10: =AVERAGE(G2:G7) -> 1 | H10: =AVERAGE(H2:H7) -> 1 | I10: =AVERAGE(I2:I7) -> 1 | ... JB10: =AVERAGE(JB2:JB7) -> 1

Sheet Cards
A1: Card ID | B1: Name (EN) | C1: Name (JP) | D1: Romaji | E1: Suit (Element) | F1: Suit (JP) | G1: XP to Unlock | H1: Type | I1: Cost (持ち時間) | J1: Self + | K1: Opp − | L1: Guard | M1: Draw | N1: Gaffe +/− | O1: Target segment | P1: Effect text | Q1: Tier | R1: Special | S1: Special value | T1: Special note | U1: Discard To Play | V1: Discard For Draw
A2: C01 | B2: Record of Service | C2: 実績報告 | D2: Jisseki Hōkoku | E2: Earnest | F2: 誠実 | G2: 10 | H2: Gain | I2: 2 | J2: 4 | K2: 0 | L2: 0 | M2: 0 | N2: 0 | O2: Any | P2: Gain 4. | Q2: 2
A3: C02 | B3: Sincere Answer | C3: 誠意ある答弁 | D3: Seii aru Tōben | E3: Earnest | F3: 誠実 | G3: 5 | H3: Defend | I3: 1 | J3: 1 | K3: 0 | L3: 4 | M3: 0 | N3: 0 | O3: Any | P3: Gain 1. Guard 4. | Q3: 0
A4: C03 | B4: Formal Apology | C4: 深々と頭を下げる | D4: Fukabuka to Atama o Sageru | E4: Earnest | F4: 誠実 | G4: 10 | H4: Gain | I4: 3 | J4: 2 | K4: 0 | L4: 0 | M4: 0 | N4: -2 | O4: Any | P4: Gain 2. Reduce your gaffe meter by 2. | Q4: 2
A5: C04 | B5: Return to First Principles | C5: 初心表明 | D5: Shoshin Hyōmei | E5: Earnest | F5: 誠実 | G5: 15 | H5: Gain | I5: 3 | J5: 6 | K5: 0 | L5: 0 | M5: 0 | N5: 0 | O5: Constituents | P5: Gain 6; +2 more if Constituents ≥ 30%. | Q5: 3 | R5: bonus_if_target_segment_ge_30 | S5: 2 | T5: Gain 6; +2 more if Constituents >= 30
A6: C05 | B6: Impassioned Speech | C6: 熱弁 | D6: Netsuben | E6: Emotional | F6: 情熱 | G6: 5 | H6: Gain | I6: 2 | J6: 5 | K6: 0 | L6: 0 | M6: 0 | N6: 0 | O6: Any | P6: Gain 5. | Q6: 0
A7: C06 | B7: Tearful Appeal | C7: 涙の訴え | D7: Namida no Uttae | E7: Emotional | F7: 情熱 | G7: 10 | H7: Gain | I7: 2 | J7: 4 | K7: 0 | L7: 0 | M7: 0 | N7: 0 | O7: Constituents | P7: Gain 4; doubled if Constituents ≥ 50%. | Q7: 2 | R7: double_if_target_segment_ge_50 | T7: Doubled if Constituents >= 50% (reads Target segment)
A8: C07 | B8: Rousing Applause | C8: 拍手喝采 | D8: Hakushu Kassai | E8: Emotional | F8: 情熱 | G8: 5 | H8: Gain | I8: 0 | J8: 1 | K8: 0 | L8: 0 | M8: 1 | N8: 0 | O8: Any | P8: Gain 1. Draw 1. | Q8: 1
A9: C08 | B9: Speech from the Soul | C9: 魂の演説 | D9: Tamashii no Enzetsu | E9: Emotional | F9: 情熱 | G9: 15 | H9: Gain | I9: 3 | J9: 11 | K9: 0 | L9: 0 | M9: 0 | N9: 2 | O9: Any | P9: Gain 11. Gaffe +2. | Q9: 3
A10: C09 | B10: Call for Unity | C10: 結束を呼びかける | D10: Kessoku o Yobikakeru | E10: Appeal | F10: 求心 | G10: 5 | H10: Gain | I10: 2 | J10: 4 | K10: 0 | L10: 0 | M10: 0 | N10: 0 | O10: Party Members | P10: Gain 4; +2 more if Party Members ≥ 50%. | Q10: 0 | R10: bonus_if_target_segment_ge_50 | S10: 2 | T10: +2 if Party Members >= 50% (reads Target segment)
A11: C10 | B11: Voice of the Hometown | C11: 地元の声 | D11: Jimoto no Koe | E11: Appeal | F11: 求心 | G11: 10 | H11: Gain | I11: 2 | J11: 4 | K11: 0 | L11: 0 | M11: 0 | N11: 0 | O11: Constituents | P11: Gain 4; +1 more for every 20% Constituents (up to +5). | Q11: 2 | R11: scale_per_20_target_segment | S11: 1 | T11: +1 per 20% of the target audience, capped at +5 (reads Target segment)
A12: C11 | B12: Work the Room First | C12: 事前に話を通す | D12: Jizen ni Hanashi o Tōsu | E12: Appeal | F12: 求心 | G12: 10 | H12: Buff | I12: 1 | J12: 0 | K12: 0 | L12: 0 | M12: 0 | N12: 0 | O12: Any | P12: Your next card this turn gets +2. | Q12: 2 | R12: buff_next_card_this_turn | S12: 2 | T12: Your next card this turn gets +2
A13: C12 | B13: Ask Who's With You | C13: 賛否を確かめる | D13: Sanpi o Tashikameru | E13: Appeal | F13: 求心 | G13: 10 | H13: Buff | I13: 1 | J13: 0 | K13: 0 | L13: 0 | M13: 2 | N13: 0 | O13: Any | P13: Draw 2. Reveal the opponent's move after this one. | Q13: 2 | R13: reveal_next_intent | T13: Reveal the opponent's move after next
A14: C13 | B14: Present the Stats | C14: 統計提示 | D14: Tōkei Teiji | E14: Data Driven | F14: 実証 | G14: 10 | H14: Attack | I14: 1 | J14: 1 | K14: 2 | L14: 0 | M14: 0 | N14: 0 | O14: Any | P14: Gain 1. Opponent −2. | Q14: 2
A15: C14 | B15: Document Request | C15: 資料請求 | D15: Shiryō Seikyū | E15: Data Driven | F15: 実証 | G15: 5 | H15: Attack | I15: 1 | J15: 0 | K15: 1 | L15: 0 | M15: 1 | N15: 0 | O15: Bureaucrats | P15: Opponent −1. Draw 1. | Q15: 0
A16: C15 | B16: Pursue the Contradiction | C16: 矛盾追及 | D16: Mujun Tsuikyū | E16: Data Driven | F16: 実証 | G16: 10 | H16: Attack | I16: 2 | J16: 1 | K16: 4 | L16: 0 | M16: 0 | N16: 0 | O16: Any | P16: Gain 1. Opponent −4. | Q16: 2 | S16: 2
A17: C16 | B17: Table the White Paper | C17: 白書を突きつける | D17: Hakusho o Tsukitsukeru | E17: Data Driven | F17: 実証 | G17: 15 | H17: Attack | I17: 3 | J17: 0 | K17: 8 | L17: 0 | M17: 0 | N17: 0 | O17: Bureaucrats | P17: Opponent −8. Ignores 3 of the opponent's Guard. | Q17: 3 | R17: pierce_guard | S17: 3 | T17: Subtract 3 from the opponent's active Guard before applying Opp −
A18: C17 | B18: Labeling | C18: レッテル貼り | D18: Retteru-bari | E18: Divisive | F18: 分断 | G18: 5 | H18: Attack | I18: 1 | J18: 0 | K18: 3 | L18: 0 | M18: 0 | N18: 0 | O18: Any | P18: Opponent −3. | Q18: 1
A19: C18 | B19: Drawing Battle Lines | C19: 敵味方の線引き | D19: Tekimikata no Senbiki | E19: Divisive | F19: 分断 | G19: 10 | H19: Attack | I19: 2 | J19: 3 | K19: 3 | L19: 0 | M19: 0 | N19: 1 | O19: Party Members | P19: Gain 3. Opponent −3. Gaffe +1. +2 more to gain if Party Members ≥ 50%. | Q19: 2 | R19: bonus_if_target_segment_ge_50 | S19: 2 | T19: +2 if Party Members >= 50% (reads Target segment)
A20: C19 | B20: Agitation | C20: 煽動 | D20: Sendō | E20: Divisive | F20: 分断 | G20: 5 | H20: Gain | I20: 2 | J20: 5 | K20: 2 | L20: 0 | M20: 0 | N20: 2 | O20: Constituents | P20: Gain 5. Opponent −2. Gaffe +2. +2 more to gain if Constituents ≥ 50%. | Q20: 0 | R20: bonus_if_target_segment_ge_50 | S20: 2 | T20: +2 if Constituents >= 50% (reads Target segment)
A21: C20 | B21: Loyalty Test | C21: 踏み絵 | D21: Fumie | E21: Divisive | F21: 分断 | G21: 10 | H21: Attack | I21: 2 | J21: 1 | K21: 7 | L21: 0 | M21: 0 | N21: 3 | O21: Party Members | P21: Gain 1. Opponent −7. Gaffe +3. | Q21: 2
A22: C21 | B22: Iridescent Answer | C22: 玉虫色の答弁 | D22: Tamamushi-iro no Tōben | E22: Duplicitous | F22: 二枚舌 | G22: 10 | H22: Defend | I22: 1 | J22: 3 | K22: 0 | L22: 4 | M22: 0 | N22: 2 | O22: Press | P22: Gain 3. Guard 4. Gaffe +2. | Q22: 2
A23: C22 | B23: "I Have No Recollection" | C23: 記憶にございません | D23: Kioku ni Gozaimasen | E23: Duplicitous | F23: 二枚舌 | G23: 5 | H23: Defend | I23: 1 | J23: 0 | K23: 0 | L23: 5 | M23: 1 | N23: 2 | O23: Press | P23: Guard 5. Draw 1. Gaffe +2. | Q23: 1
A24: C23 | B24: Shifting the Issue | C24: 論点ずらし | D24: Ronten-zurashi | E24: Duplicitous | F24: 二枚舌 | G24: 5 | H24: Attack | I24: 1 | J24: 2 | K24: 3 | L24: 0 | M24: 0 | N24: 1 | O24: Press | P24: Gain 2. Opponent −3. Gaffe +1. | Q24: 0
A25: C24 | B25: Offer a Quiet Assurance | C25: 密約を持ちかける | D25: Mitsuyaku o Mochikakeru | E25: Duplicitous | F25: 二枚舌 | G25: 10 | H25: Gain | I25: 2 | J25: 7 | K25: 0 | L25: 0 | M25: 0 | N25: 1 | O25: Boosters | P25: Gain 7. Gaffe +1. +1 more to gain for every 20% Boosters (up to +5). | Q25: 2 | R25: scale_per_20_target_segment | S25: 1 | T25: +1 per 20% of the target audience, capped at +5 (reads Target segment)
A26: C25 | B26: Point to the Promise Kept | C26: 公約履行を訴える | D26: Kōyaku Rikō o Uttaeru | E26: Earnest | F26: 誠実 | G26: 10 | H26: Gain | I26: 2 | J26: 5 | K26: 0 | L26: 0 | M26: 0 | N26: 0 | O26: Any | P26: Gain 5; +2 more if your gaffe meter is 0. | Q26: 2 | R26: bonus_if_self_gaffe_0 | S26: 2 | T26: Gain +2 more if the player's gaffe meter is exactly 0
A27: C26 | B27: Own the Mistake | C27: 非を認める | D27: Hi o Mitomeru | E27: Earnest | F27: 誠実 | G27: 5 | H27: Buff | I27: 1 | J27: 0 | K27: 0 | L27: 0 | M27: 0 | N27: -2 | O27: Any | P27: Reduce your gaffe meter by 2. | Q27: 1
A28: C27 | B28: Appeal Across the Aisle | C28: 超党派に呼びかける | D28: Chōtōha ni Yobikakeru | E28: Earnest | F28: 誠実 | G28: 10 | H28: Attack | I28: 2 | J28: 3 | K28: 2 | L28: 0 | M28: 0 | N28: 0 | O28: Any | P28: Gain 3. Opponent −2. | Q28: 2
A29: C28 | B29: Read the Letters Aloud | C29: 陳情を読み上げる | D29: Chinjō o Yomiageru | E29: Earnest | F29: 誠実 | G29: 5 | H29: Gain | I29: 2 | J29: 3 | K29: 0 | L29: 0 | M29: 1 | N29: 0 | O29: Constituents | P29: Gain 3. Draw 1. +1 more to gain for every 20% Constituents (up to +5). | Q29: 1 | R29: scale_per_20_target_segment | S29: 1 | T29: +1 per 20% of the target audience, capped at +5 (reads Target segment)
A30: C29 | B30: Appeal to Conscience | C30: 良心に訴える | D30: Ryōshin ni Uttaeru | E30: Earnest | F30: 誠実 | G30: 15 | H30: Gain | I30: 3 | J30: 8 | K30: 2 | L30: 0 | M30: 0 | N30: 0 | O30: Any | P30: Gain 8. Opponent −2. +3 more to gain if your gaffe meter is 0. | Q30: 3 | R30: bonus_if_self_gaffe_0 | S30: 3 | T30: Gain +3 more if the player's gaffe meter is exactly 0
A31: C30 | B31: Rally the Faithful | C31: 支持者を鼓舞する | D31: Shijisha o Kobu Suru | E31: Emotional | F31: 情熱 | G31: 5 | H31: Gain | I31: 1 | J31: 4 | K31: 0 | L31: 0 | M31: 0 | N31: 1 | O31: Party Members | P31: Gain 4. Gaffe +1. +2 more to gain if Party Members ≥ 50%. | Q31: 1 | R31: bonus_if_target_segment_ge_50 | S31: 2 | T31: +2 if Party Members >= 50% (reads Target segment)
A32: C31 | B32: Righteous Anger | C32: 義憤 | D32: Gifun | E32: Emotional | F32: 情熱 | G32: 10 | H32: Attack | I32: 2 | J32: 1 | K32: 5 | L32: 0 | M32: 0 | N32: 2 | O32: Any | P32: Gain 1. Opponent −5. Gaffe +2. | Q32: 2
A33: C32 | B33: Raise Your Voice | C33: 声を荒げる | D33: Koe o Aragaru | E33: Emotional | F33: 情熱 | G33: 10 | H33: Gain | I33: 2 | J33: 5 | K33: 2 | L33: 0 | M33: 0 | N33: 1 | O33: Any | P33: Gain 5. Opponent −2. Gaffe +1. | Q33: 2
A34: C33 | B34: Refuse to Yield | C34: 一歩も引かない | D34: Ippo mo Hikanai | E34: Emotional | F34: 情熱 | G34: 5 | H34: Gain | I34: 2 | J34: 3 | K34: 0 | L34: 0 | M34: 1 | N34: 0 | O34: Any | P34: Gain 3. Draw 1. +3 more to gain if you trail the opponent in support. | Q34: 1 | R34: bonus_if_behind | S34: 3 | T34: Gain +3 more if the player's support total is below the opponent's
A35: C34 | B35: Bring the Room to Its Feet | C35: 満場を沸かせる | D35: Manjō o Wakaseru | E35: Emotional | F35: 情熱 | G35: 10 | H35: Gain | I35: 2 | J35: 7 | K35: 0 | L35: 0 | M35: 0 | N35: 1 | O35: Constituents | P35: Gain 7. Gaffe +1. +3 more to gain if Constituents ≥ 50%. | Q35: 2 | R35: bonus_if_target_segment_ge_50 | S35: 3 | T35: +3 if Constituents >= 50% (reads Target segment)
A36: C35 | B36: Invoke Party Discipline | C36: 党議拘束を持ち出す | D36: Tōgi Kōsoku o Mochidasu | E36: Appeal | F36: 求心 | G36: 10 | H36: Gain | I36: 2 | J36: 4 | K36: 1 | L36: 0 | M36: 0 | N36: 0 | O36: Party Members | P36: Gain 4. Opponent −1. | Q36: 2
A37: C36 | B37: Offer a Private Word | C37: 耳打ち | D37: Mimiuchi | E37: Appeal | F37: 求心 | G37: 10 | H37: Buff | I37: 1 | J37: 2 | K37: 0 | L37: 0 | M37: 0 | N37: 0 | O37: Boosters | P37: Gain 2. Your next card this turn costs 1 less. | Q37: 2 | R37: discount_next_card_this_turn | S37: 1 | T37: Next card played this turn costs 1 less (minimum 0)
A38: C37 | B38: Call for Common Cause | C38: 連携を呼びかける | D38: Renkei o Yobikakeru | E38: Appeal | F38: 求心 | G38: 15 | H38: Gain | I38: 3 | J38: 8 | K38: 2 | L38: 0 | M38: 0 | N38: 0 | O38: Any | P38: Gain 8. Opponent −2. | Q38: 3
A39: C38 | B39: Call In a Favor | C39: 貸しを返してもらう | D39: Kashi o Kaeshite Morau | E39: Appeal | F39: 求心 | G39: 5 | H39: Gain | I39: 1 | J39: 2 | K39: 0 | L39: 0 | M39: 0 | N39: 0 | O39: Party Members | P39: Gain 2. +2 more to gain if Party Members ≥ 50%. | Q39: 1 | R39: bonus_if_target_segment_ge_50 | S39: 2 | T39: +2 if Party Members >= 50% (reads Target segment)
A40: C39 | B40: We Have the Votes | C40: 数の力を示す | D40: Kazu no Chikara o Shimesu | E40: Appeal | F40: 求心 | G40: 15 | H40: Gain | I40: 3 | J40: 9 | K40: 1 | L40: 0 | M40: 0 | N40: 0 | O40: Party Members | P40: Gain 9. Opponent −1. +3 more to gain if Party Members ≥ 50%. | Q40: 3 | R40: bonus_if_target_segment_ge_50 | S40: 3 | T40: +3 if Party Members >= 50% (reads Target segment)
A41: C40 | B41: Question the Funding | C41: 資金の出所を問う | D41: Shikin no Dedokoro o Tou | E41: Data Driven | F41: 実証 | G41: 10 | H41: Attack | I41: 2 | J41: 1 | K41: 4 | L41: 0 | M41: 0 | N41: 0 | O41: Boosters | P41: Gain 1. Opponent −4. | Q41: 2
A42: C41 | B42: Set the Record Straight | C42: 事実誤認の訂正 | D42: Jijitsu Gonin no Teisei | E42: Data Driven | F42: 実証 | G42: 15 | H42: Gain | I42: 1 | J42: 1 | K42: 0 | L42: 0 | M42: 1 | N42: -1 | O42: Press | P42: Gain 1. Draw 1. Reduce your gaffe meter by 1. | Q42: 3
A43: C42 | B43: Press for a Straight Answer | C43: 明確な答弁を求める | D43: Meikaku na Tōben o Motomeru | E43: Data Driven | F43: 実証 | G43: 10 | H43: Attack | I43: 2 | J43: 0 | K43: 4 | L43: 0 | M43: 1 | N43: 0 | O43: Bureaucrats | P43: Opponent −4. Draw 1. Ignores 2 of the opponent's Guard. | Q43: 2 | R43: pierce_guard | S43: 2 | T43: Subtract 2 from the opponent's active Guard before applying Opp −
A44: C43 | B44: Check Their Facts | C44: 事実確認を迫る | D44: Jijitsu Kakunin o Semaru | E44: Data Driven | F44: 実証 | G44: 5 | H44: Attack | I44: 1 | J44: 0 | K44: 2 | L44: 1 | M44: 0 | N44: 0 | O44: Press | P44: Opponent −2. Guard 1. | Q44: 1 | S44: 3
A45: C44 | B45: Demand an Outside Review | C45: 第三者委員会を求める | D45: Daisansha Iinkai o Motomeru | E45: Data Driven | F45: 実証 | G45: 15 | H45: Attack | I45: 3 | J45: 1 | K45: 7 | L45: 0 | M45: 0 | N45: -1 | O45: Bureaucrats | P45: Gain 1. Opponent −7. Reduce your gaffe meter by 1. | Q45: 3 | S45: 3
A46: C45 | B46: Name and Shame | C46: 名指し批判 | D46: Nazashi Hihan | E46: Divisive | F46: 分断 | G46: 10 | H46: Attack | I46: 2 | J46: 1 | K46: 6 | L46: 0 | M46: 0 | N46: 1 | O46: Any | P46: Gain 1. Opponent −6. Gaffe +1. | Q46: 2
A47: C46 | B47: Force the Choice | C47: 二者択一を迫る | D47: Nisha Takuitsu o Semaru | E47: Divisive | F47: 分断 | G47: 10 | H47: Attack | I47: 2 | J47: 2 | K47: 3 | L47: 0 | M47: 0 | N47: 0 | O47: Constituents | P47: Gain 2. Opponent −3. +2 more to gain if Constituents ≥ 50%. | Q47: 2 | R47: bonus_if_target_segment_ge_50 | S47: 2 | T47: +2 if Constituents >= 50% (reads Target segment)
A48: C47 | B48: Question Their Loyalty | C48: 忠誠を問う | D48: Chūsei o Tou | E48: Divisive | F48: 分断 | G48: 10 | H48: Attack | I48: 2 | J48: 2 | K48: 5 | L48: 0 | M48: 0 | N48: 3 | O48: Party Members | P48: Gain 2. Opponent −5. Gaffe +3. +3 more to gain if Party Members ≥ 50%. | Q48: 2 | R48: bonus_if_target_segment_ge_50 | S48: 3 | T48: +3 if Party Members >= 50% (reads Target segment)
A49: C48 | B49: Media Appeal | C49: メディアへの訴え | D49: Media e no Uttae | E49: Divisive | F49: 分断 | G49: 10 | H49: Gain | I49: 2 | J49: 3 | K49: 2 | L49: 0 | M49: 1 | N49: 0 | O49: Press | P49: Gain 3. Opponent −2. Draw 1. +2 more to gain if Press ≥ 50%. | Q49: 2 | R49: bonus_if_target_segment_ge_50 | S49: 2 | T49: +2 if Press >= 50% (reads Target segment)
A50: C49 | B50: Declare Them Unfit | C50: 不信任を突きつける | D50: Fushinnin o Tsukitsukeru | E50: Divisive | F50: 分断 | G50: 15 | H50: Attack | I50: 3 | J50: 0 | K50: 11 | L50: 0 | M50: 0 | N50: 3 | O50: Any | P50: Opponent −11. Gaffe +3. Ignores 3 of the opponent's Guard. | Q50: 3 | R50: pierce_guard | S50: 3 | T50: Subtract 3 from the opponent's active Guard before applying Opp −
A51: C50 | B51: Take It Under Advisement | C51: 前向きに検討します | D51: Maemuki ni Kentō Shimasu | E51: Duplicitous | F51: 二枚舌 | G51: 10 | H51: Defend | I51: 1 | J51: 1 | K51: 2 | L51: 3 | M51: 0 | N51: 1 | O51: Press | P51: Gain 1. Opponent −2. Guard 3. Gaffe +1. | Q51: 2
A52: C51 | B52: Feed the Press a Line | C52: 記者に吹き込む | D52: Kisha ni Fukikomu | E52: Duplicitous | F52: 二枚舌 | G52: 10 | H52: Attack | I52: 2 | J52: 1 | K52: 4 | L52: 0 | M52: 0 | N52: 1 | O52: Press | P52: Gain 1. Opponent −4. Gaffe +1. +2 more to gain if Press ≥ 50%. | Q52: 2 | R52: bonus_if_target_segment_ge_50 | S52: 2 | T52: +2 if Press >= 50% (reads Target segment)
A53: C52 | B53: Drown Them in Detail | C53: 細部で煙に巻く | D53: Saibu de Kemu ni Maku | E53: Duplicitous | F53: 二枚舌 | G53: 10 | H53: Gain | I53: 2 | J53: 4 | K53: 0 | L53: 0 | M53: 1 | N53: 1 | O53: Bureaucrats | P53: Gain 4. Draw 1. Gaffe +1. +1 more to gain for every 20% Bureaucrats (up to +5). | Q53: 2 | R53: scale_per_20_target_segment | S53: 1 | T53: +1 per 20% of the target audience, capped at +5 (reads Target segment)
A54: C53 | B54: Tell the Room What It Wants | C54: 相手によって話を変える | D54: Aite ni Yotte Hanashi o Kaeru | E54: Duplicitous | F54: 二枚舌 | G54: 15 | H54: Gain | I54: 2 | J54: 9 | K54: 0 | L54: 0 | M54: 0 | N54: 2 | O54: Any | P54: Gain 9. Gaffe +2. +3 more to gain if you trail the opponent in support. | Q54: 3 | R54: bonus_if_behind | S54: 3 | T54: Gain +3 more if the player's support total is below the opponent's
A55: C54 | B55: Off the Record | C55: オフレコ | D55: Ofureko | E55: Duplicitous | F55: 二枚舌 | G55: 10 | H55: Defend | I55: 2 | J55: 5 | K55: 0 | L55: 2 | M55: 0 | N55: 1 | O55: Press | P55: Gain 5. Guard 2. Gaffe +1. | Q55: 2
A56: C55 | B56: Trim the Appendix | C56: 付録を削る | D56: Furoku o Kezuru | E56: Data Driven | F56: 実証 | G56: 5 | H56: Attack | I56: 1 | J56: 0 | K56: 2 | L56: 0 | M56: 1 | N56: 0 | O56: Any | P56: Discard 1 other card. Opponent −2. Draw 1. | Q56: 1 | V56: 1
A57: C56 | B57: Review the Record | C57: 記録を見直す | D57: Kiroku o Minaosu | E57: Data Driven | F57: 実証 | G57: 10 | H57: Attack | I57: 1 | J57: 0 | K57: 3 | L57: 0 | M57: 2 | N57: 0 | O57: Any | P57: Discard 1 other card. Opponent −3. Draw 2. | Q57: 2 | V57: 1
A58: C57 | B58: Burn the Draft | C58: 草案を焼く | D58: Sōan o Yaku | E58: Divisive | F58: 分断 | G58: 5 | H58: Attack | I58: 1 | J58: 1 | K58: 1 | L58: 0 | M58: 1 | N58: 1 | O58: Any | P58: Discard 1 other card. Gain 1. Opponent −1. Draw 1. Gaffe +1. | Q58: 1 | V58: 1
A59: C58 | B59: Cut Your Losses | C59: 損切り | D59: Songiri | E59: Divisive | F59: 分断 | G59: 10 | H59: Attack | I59: 1 | J59: 0 | K59: 2 | L59: 0 | M59: 2 | N59: 1 | O59: Any | P59: Discard 1 other card. Opponent −2. Draw 2. Gaffe +1. | Q59: 2 | V59: 1
A60: C59 | B60: Let It Go | C60: 思いを手放す | D60: Omoi o Tebanasu | E60: Emotional | F60: 情熱 | G60: 5 | H60: Gain | I60: 1 | J60: 3 | K60: 0 | L60: 0 | M60: 1 | N60: 0 | O60: Any | P60: Discard 1 other card. Gain 3. Draw 1. | Q60: 1 | V60: 1
A61: C60 | B61: A Fresh Start | C61: 出直し | D61: Denaoshi | E61: Emotional | F61: 情熱 | G61: 10 | H61: Gain | I61: 1 | J61: 3 | K61: 0 | L61: 0 | M61: 2 | N61: 1 | O61: Any | P61: Discard 1 other card. Gain 3. Draw 2. Gaffe +1. | Q61: 2 | V61: 1
A62: C61 | B62: Shuffle the Papers | C62: 書類をさばく | D62: Shorui o Sabaku | E62: Duplicitous | F62: 二枚舌 | G62: 5 | H62: Defend | I62: 1 | J62: 2 | K62: 0 | L62: 2 | M62: 1 | N62: 1 | O62: Any | P62: Discard 1 other card. Gain 2. Guard 2. Draw 1. Gaffe +1. | Q62: 1 | V62: 1
A63: C62 | B63: Lose the Evidence | C63: 証拠を隠す | D63: Shōko o Kakusu | E63: Duplicitous | F63: 二枚舌 | G63: 10 | H63: Defend | I63: 1 | J63: 2 | K63: 0 | L63: 2 | M63: 2 | N63: 1 | O63: Any | P63: Discard 1 other card. Gain 2. Guard 2. Draw 2. Gaffe +1. | Q63: 2 | V63: 1
A64: C63 | B64: Compile the Dossier | C64: 資料をまとめる | D64: Shiryō o Matomeru | E64: Data Driven | F64: 実証 | G64: 5 | H64: Attack | I64: 1 | J64: 0 | K64: 9 | L64: 1 | M64: 0 | N64: 0 | O64: Any | P64: Discard 2 other cards to play. Opponent −9. Guard 1. | Q64: 1 | U64: 2
A65: C64 | B65: The Full Audit | C65: 全面監査 | D65: Zenmen Kansa | E65: Data Driven | F65: 実証 | G65: 10 | H65: Attack | I65: 2 | J65: 2 | K65: 11 | L65: 0 | M65: 0 | N65: -1 | O65: Any | P65: Discard 1 other card to play. Gain 2. Opponent −11. Reduce your gaffe meter by 1. | Q65: 2 | U65: 1
A66: C65 | B66: Burn the Bridge | C66: 橋を焼く | D66: Hashi o Yaku | E66: Divisive | F66: 分断 | G66: 5 | H66: Attack | I66: 1 | J66: 0 | K66: 11 | L66: 0 | M66: 0 | N66: 2 | O66: Any | P66: Discard 2 other cards to play. Opponent −11. Gaffe +2. | Q66: 1 | U66: 2
A67: C66 | B67: No Quarter | C67: 容赦なし | D67: Yōsha Nashi | E67: Divisive | F67: 分断 | G67: 10 | H67: Attack | I67: 2 | J67: 2 | K67: 13 | L67: 0 | M67: 0 | N67: 2 | O67: Any | P67: Discard 1 other card to play. Gain 2. Opponent −13. Gaffe +2. | Q67: 2 | U67: 1
A68: C67 | B68: Give Everything | C68: 全てを捧げる | D68: Subete o Sasageru | E68: Emotional | F68: 情熱 | G68: 5 | H68: Gain | I68: 1 | J68: 11 | K68: 0 | L68: 0 | M68: 0 | N68: 1 | O68: Any | P68: Discard 2 other cards to play. Gain 11. Gaffe +1. | Q68: 1 | U68: 2
A69: C68 | B69: Words From the Soul | C69: 魂の訴え | D69: Tamashii no Uttae | E69: Emotional | F69: 情熱 | G69: 10 | H69: Gain | I69: 2 | J69: 12 | K69: 0 | L69: 0 | M69: 1 | N69: 1 | O69: Any | P69: Discard 1 other card to play. Gain 12. Draw 1. Gaffe +1. | Q69: 2 | U69: 1
A70: C69 | B70: The Quiet Deal | C70: 密約 | D70: Mitsuyaku | E70: Duplicitous | F70: 二枚舌 | G70: 5 | H70: Defend | I70: 1 | J70: 10 | K70: 0 | L70: 3 | M70: 0 | N70: 2 | O70: Any | P70: Discard 2 other cards to play. Gain 10. Guard 3. Gaffe +2. | Q70: 1 | U70: 2
A71: C70 | B71: Back-Room Bargain | C71: 密室の取引 | D71: Misshitsu no Torihiki | E71: Duplicitous | F71: 二枚舌 | G71: 10 | H71: Defend | I71: 2 | J71: 12 | K71: 0 | L71: 4 | M71: 0 | N71: 2 | O71: Any | P71: Discard 1 other card to play. Gain 12. Guard 4. Gaffe +2. | Q71: 2 | U71: 1

Sheet Segments
A1: Segment ID | B1: Segment (EN) | C1: Segment (JP) | D1: Romaji | E1: Description | F1: Initial Favorability %
